Workbook
Name Action: '[1]Data Call Management'!$A$3:$A$12
Name Action: '[1]Data Call Management'!$A$3:$A$12
Name Action: '[1]Data Call Management'!$A$3:$A$12
Name Action: '[1]Data Call Management'!$A$3:$A$12
Name Action: '[1]Data Call Management'!$A$3:$A$12
Name Action: '[1]Data Call Management'!$A$3:$A$12
Name Action: '[1]Data Call Management'!$A$3:$A$12
Name Action: '[1]Data Call Management'!$A$3:$A$12
Name Action: '[1]Data Call Management'!$A$3:$A$12
Name Action: '[1]Data Call Management'!$A$3:$A$12
Name Action: '[1]Data Call Management'!$A$3:$A$12
Name Action: '[1]Data Call Management'!$A$3:$A$12
Name Action: '[1]Data Call Management'!$A$3:$A$12
Name Action: [2]Reference!$A$3:$A$12
Name Action: '[1]Data Call Management'!$A$3:$A$12
Name Action: [3]Reference!$A$3:$A$12
Name Action: '[1]Data Call Management'!$A$3:$A$12
Name Action: [2]Reference!$A$3:$A$12
Name Crit: [4]Reference!$D$3:$D$18
Name Critical: '[1]Data Call Management'!$B$3:$B$18
Name Critical: '[1]Data Call Management'!$B$3:$B$18
Name Critical: '[1]Data Call Management'!$B$3:$B$18
Name Critical: '[1]Data Call Management'!$B$3:$B$18
Name Critical: '[1]Data Call Management'!$B$3:$B$18
Name Critical: '[1]Data Call Management'!$B$3:$B$18
Name Critical: '[1]Data Call Management'!$B$3:$B$18
Name Critical: '[1]Data Call Management'!$B$3:$B$18
Name Critical: '[1]Data Call Management'!$B$3:$B$18
Name Critical: '[1]Data Call Management'!$B$3:$B$18
Name Critical: '[1]Data Call Management'!$B$3:$B$18
Name Critical: '[1]Data Call Management'!$B$3:$B$18
Name Critical: '[1]Data Call Management'!$B$3:$B$18
Name Critical: [2]Reference!$B$3:$B$18
Name Critical: '[1]Data Call Management'!$B$3:$B$18
Name Critical: [3]Reference!$B$3:$B$18
Name Critical: '[1]Data Call Management'!$B$3:$B$18
Name Critical: [2]Reference!$B$3:$B$18
Name CVTTable: #REF!
Name CVTTable: TEMP!$C$3:$W$235
Name CVTTable: 'CVT Master List'!$C$4:$W$248
Name PriorityRange: #REF!
Name PriorityRange: TEMP!$S$3:$U$84
Name PriorityRange: 'CVT Master List'!$S$5:$U$97
Name WSMS_108: #REF!
Name WSMS_108: #REF!
Name WSMS_108: #REF!
Name WSMS_108: #REF!
Name WSMS_108: #REF!
Name WSMS_108: #REF!
Name WSMS_108: #REF!
Name WSMS_108: #REF!
Name WSMS_108: #REF!
Name WSMS_108: #REF!
Name WSMS_108: #REF!
Name WSMS_108: #REF!
Name WSMS_108: #REF!
Name WSMS_108: #REF!
Name WSMS_108: #REF!
Name WSMS_108: #REF!
Name WSMS_108: #REF!

Sheet DELETE Comments 
A1: Comment # | B1: Scenario | C1: Tab | D1: CVT No | E1: Step No | F1: Pass | G1: 1 | H1: 2 | I1: 3 | J1: 4 | K1: 5 | L1: Comment | M1: Submit By | N1: Sub Date | O1: Status | P1: Resolution Type | Q1: Resolution
A2: 1 | B2: 4.4 | C2: File Maintenance | D2: FS10 | E2: 1 | F2: P | L2: Please list the "appropriate column" that the tester must verify. | M2: AMR | N2: 40106 | O2: Retest | P2: CVT | Q2: Changed step to "select row" to update funding
A3: 2 | B3: 4.4 | C3: File Maintenance | D3: FS10 | E3: 2 | K3: F | L3: What values should be displaying for a particular PCN/Task. For example, the dollar amounts are based on your filter. | M3: AMR | N3: 40106 | O3: Retest | P3: CVT | Q3: Added note that totals are limited by filter applied
A4: 3 | B4: 4.4 | C4: File Maintenance | D4: FS10 | E4: 2 | K4: F | L4: Not working. I didn't think we were testing this yet. | M4: AMR | N4: 40106 | O4: Retest | P4: CVT | Q4: Removed
A5: 4 | B5: 4.4 | C5: File Maintenance | D5: FS10 | E5: 3 | K5: F | L5: Straggler step | M5: AMR | N5: 40106 | O5: Retest | P5: CVT | Q5: Removed - straggler step
A6: 5 | B6: 4.4 | C6: File Maintenance | D6: FS10 | E6: 3 | K6: F | L6: Tester wasn't required to make any changes to the Funds Spread. Cannot click "save." | M6: AMR | N6: 40106 | O6: Retest | P6: CVT | Q6: Added step to edit a fund spread amount
A7: 6 | B7: 4.4 | C7: File Maintenance | D7: FS10 | E7: 4 | F7: P | L7: Shouldn't they be reviewing the peace target to the peace funded? Why are they comparing to the target reference or ABIDES? | M7: AMR | N7: 40106 | O7: Retest | P7: CVT | Q7: Replaced with "Review the Summary Totals at the top of the grid to compare funding to requirements."
A8: 7 | B8: 4.4 | C8: File Maintenance | D8: FS10 | E8: 5 | F8: P | L8: When I clicked on excess funding, it resorted the PCNs. Items that had requirements unfunded showed up on the list, but were near the bottom. Should they be showing up? Also, I don't think there shouldn't be any excess funding in a FYDP data call. System won't let you overfund requirements. | M8: AMR | N8: 40106 | O8: Open | P8: Question | Q8: The Excess funding option should not be visible within FYDP
A9: 8 | B9: 4.4 | C9: File Maintenance | D9: FS10 | E9: 6 | F9: P | L9: Suggestion: specify that it is the refresh button next to the Funds Spread Drop Down. There is another refresh at the top lefthand corner of the page. | M9: AMR | N9: 40106 | O9: Retest | P9: CVT | Q9: Updated verbiage
A10: 9 | B10: 4.4 | C10: File Maintenance | D10: FS10 | E10: PRE | K10: F | L10: Suggestion: List steps to determine if data is in input or verification status. Also, isn't the data call either "Closed" or "Open." I thought we got rid of the different statuses. | M10: AMR | N10: 40106 | O10: Retest | P10: CVT | Q10: Removed 'status' comment, used this space to explain why user would be doing this.
A11: 10 | B11: 4.4 | C11: File Maintenance | D11: FS4 | E11: 3 | K11: F | L11: Actual radial button is labeled "Fully Fund to Target by Priority." | M11: AMR | N11: 40106 | O11: Retest | P11: CVT | Q11: Added "by priority"
A12: 11 | B12: 4.4 | C12: File Maintenance | D12: FS4 | E12: 4 | F12: P | L12: Suggestion: Reference that the appropriate data call must be chosen as well as the desired year. | M12: AMR | N12: 40106 | O12: Retest | P12: CVT | Q12: Add note to select data call and year.
A13: 12 | B13: 4.4 | C13: File Maintenance | D13: FS4 | E13: 5 | G13: F | L13: Must first choose a Mass Change Option (Peace or Supplemental) before saving. For CVT purposes, I chose both Peace and Supplemental and clicked save. | M13: AMR | N13: 40106 | O13: Retest | P13: CVT | Q13: Add note to select peace, supp or both
A14: 13 | B14: 4.4 | C14: File Maintenance | D14: FS4 | E14: PRE | F14: P | L14: Suggestion: List steps to check that Target has been inputted or list CVT test that shows how you check target. | M14: AMR | N14: 40106 | O14: Retest | P14: CVT | Q14: Referenced CVT TGT7
A15: 14 | B15: 4.4 | C15: File Maintenance | D15: NAV1 | E15: 5 | F15: Pass | L15: Please specify "Data Call" name for CVT purposes. | M15: AMR | N15: 40106 | O15: Retest | P15: CVT | Q15: Updated step to state: Select Data Call. Reference scenario / data call instructions for specific data call to select. Will also clarify on scenarios
A16: 15 | B16: 4.4 | C16: File Maintenance | D16: NAV2 | E16: 2 | F16: Pass | L16: FYDP Data Call Tools. | M16: AMR | N16: 40106 | O16: Retest | P16: CVT | Q16: Updated comment
A17: 16 | B17: 4.4 | C17: File Maintenance | D17: NAV2 | E17: 2 | F17: P | L17: FYDP Data Call Tools. | M17: AMR | N17: 40106 | O17: Retest | P17: CVT | Q17: Added "Data Call"
A18: 17 | B18: 4.4 | C18: File Maintenance | D18: NAV2 | E18: 9 | F18: Pass | L18: Please change to QM Requirement | M18: AMR | N18: 40106 | O18: Retest | P18: CVT | Q18: Fixed Typo
A19: 18 | B19: 4.4 | C19: File Maintenance | D19: NAV2 | E19: NOTE | F19: P | L19: Suggestion: Please add Program Group, PEC, and AFFEIC in parentheses. This will give them a parameter for filtering, which is helpful for people who do not typically use FRM. | M19: AMR | N19: 40106 | O19: Retest | P19: CVT | Q19: updated note
A20: 19 | B20: 4.4 | C20: File Maintenance | D20: NAV4 | E20: 1 | F20: P | L20: FYDP Data Call Tools. | M20: AMR | N20: 40106 | O20: Retest | P20: CVT | Q20: Added "Data Call"
A21: 20 | B21: 4.4 | C21: File Maintenance | D21: NAV4 | E21: 3 | F21: P | L21: Should already have filters from NAV2. | M21: AMR | N21: 40106 | O21: Retest | P21: CVT | Q21: Removed step
A22: 21 | B22: 4.4 | C22: File Maintenance | D22: RPT1 | E22: 2 | F22: Pass | L22: FYDP Data Call Tools | M22: AMR | N22: 40106 | O22: Retest | P22: CVT | Q22: Updated CVT
A23: 22 | B23: 4.4 | C23: File Maintenance | D23: RPT1 | E23: 6 | F23: Pass | L23: Suggestion: Check Program Group, PEC, and AFEEIC | M23: AMR | N23: 40106 | O23: Retest | P23: CVT | Q23: Done
A24: 23 | B24: 4.4 | C24: File Maintenance | D24: RPT1 | E24: 7 | J24: F | L24: This should be on the Execution Custom Datasheet not the FYDP. | M24: AMR | N24: 40106 | O24: Retest | P24: CVT | Q24: Deleted
A25: 24 | B25: 4.4 | C25: File Maintenance | D25: RPT1 | E25: 8 | F25: F | L25: This should be on the Execution Custom Datasheet not the FYDP. | M25: AMR | N25: 40106 | O25: Retest | P25: CVT | Q25: Deleted
A26: 25 | B26: 4.4 | C26: File Maintenance | D26: RPT1 | E26: 9 | F26: F | L26: This should be on the Execution Custom Datasheet not the FYDP. | M26: AMR | N26: 40106 | O26: Retest | P26: CVT | Q26: Deleted
A27: 26 | B27: 4.4 | C27: File Maintenance | D27: RPT1 | E27: 10 | F27: Pass | L27: Suggestion: Tester should make sure that Amount and a year are checked under Cost Type and Years. | M27: AMR | N27: 40106 | O27: Retest | P27: CVT | Q27: Added note
A28: 27 | B28: 4.4 | C28: File Maintenance | D28: RPT1 | E28: 11 | I28: F | L28: There isn't a button to "Preview Datasheet." Should be "Export Data to Excel." | M28: AMR | N28: 40106 | O28: Retest | P28: CVT | Q28: Done
A29: 28 | B29: 4.4 | C29: File Maintenance | D29: RPT1 | E29: 12 | G29: f | L29: I clicked on download report. Once loading was complete, I was never prompted to open a spreadsheet even though I gave permission to download file. Spreadsheet never opened even though I had excel already open. (I tried three times) Also, I would like to see another step to verify that the report actually pulled what it was supposed to. | M29: AMR | N29: 40106 | O29: ITI Test | P29: Bug | Q29: Updated steps for new navigation due to report queue. Pop up is still an issue
A30: 29 | B30: 2.6 | C30: User Mgmt | D30: DC1 | E30: 3 | F30: P | L30: Is it necessary to check one or the other for the purposes of this CVT? | M30: AMR | N30: 40106 | O30: Retest | P30: CVT | Q30: Added "active for purpose of this CVT"
A31: 30 | B31: 2.6 | C31: User Mgmt | D31: DC1 | E31: 5.A | F31: P | L31: Suggestion: Have them choose a paticular data call from the list for CVT purposes. | M31: AMR | N31: 40106 | O31: Retest | P31: CVT | Q31: Added to Scenario
A32: 31 | B32: 2.6 | C32: User Mgmt | D32: DC1 | E32: 5.C | F32: P | L32: Suggestion: Identify what needs to be selected. For example, radial button needs to be selected under RQMT option? It might make a difference what parameters are selected. | M32: AMR | N32: 40106 | O32: Retest | P32: CVT | Q32: Added to Scenario
A33: 32 | B33: 2.6 | C33: User Mgmt | D33: DC1 | E33: 6.A | F33: P | L33: What parameters should be selected based on quick copy data call? | M33: AMR | N33: 40106 | O33: Retest | P33: CVT | Q33: Added to Scenario
A34: 33 | B34: 2.6 | C34: User Mgmt | D34: DC1 | E34: 7.B | F34: P | L34: Cannot change Source Data Call data. Users have the ability to change Destination Data Call only. Please take out edit/update as desired. Also, the Source Data Call grid only shows the year and source rqmt. Data Call and Data Set are not there. | M34: AMR | N34: 40106 | O34: Retest | P34: CVT | Q34: Removed "edit / update" and "data call and data set
A35: 34 | B35: 2.6 | C35: User Mgmt | D35: DC1 | E35: 8.A | F35: P | L35: Note: Should keep all boxes checked to finish CVT. | M35: AMR | N35: 40106 | O35: Retest | P35: CVT | Q35: Added Note
A36: 35 | B36: 2.6 | C36: User Mgmt | D36: DC4 | E36: PRE | L36: Remove year function forth coming. | M36: AMR | N36: 40106 | O36: Retest | P36: CVT | Q36: Removed comment
A37: 36 | B37: 2.6 | C37: User Mgmt | D37: DC5 | E37: 1 | K37: F | L37: Please state that this is the data call that was just created. It is unclear if it is any data call or the one that was created. | M37: AMR | N37: 40106 | O37: Retest | P37: CVT | Q37: Added "Note: When using this function to validate a newly created data call, select the newly created data call and the source data call for the comparison
A38: 37 | B38: 2.6 | C38: User Mgmt | D38: DC5 | E38: 3 | F38: P | L38: This should be the data call you copied from. | M38: AMR | N38: 40106 | O38: Retest | P38: CVT | Q38: Added "Note: When using this function to validate a newly created data call, select the newly created data call and the source data call for the comparison"
A39: 38 | B39: 2.6 | C39: User Mgmt | D39: DC5 | E39: 4 | F39: P | L39: Refresh next to Audit Data Call. There is another refresh at the top, left corner of the screen. | M39: AMR | N39: 40106 | O39: Retest | P39: CVT | Q39: Added next to "Audit Data Call"
A40: 39 | B40: 2.6 | C40: User Mgmt | D40: DC5 | E40: 5 | G40: F | L40: Both the data call I created and the data call I copied have RQMTS of zero. When I checked the RQMTs of the TEST Exec, it had RQMTS. I chose the radial option "Use Data Call RQMT" in STEP 1: Data Call Options when I created my data call. Also, I left the "Load RQMTS" checked in Step 4 of the create Data Call. | M40: AMR | N40: 40106 | O40: Assigned | P40: BUG | Q40: BUG
A41: 40 | B41: 2.6 | C41: User Mgmt | D41: DC5 | E41: PRE | K41: F | L41: Please list steps for how I verify target parameters are the same or fewer. Also, how do you verify the Factor Set it the same? Need to have specific steps or a separate CVT. | M41: AMR | N41: 40106 | O41: Retest | P41: CVT | Q41: Removed this as a precondition and added steps to direct tester to CVT DC3 if they are uncertain about what factor set is used or target parameters
A42: 41 | B42: 2.6 | C42: User Mgmt | D42: DC6 | E42: 1 | K42: F | L42: Please state that this is the data call that was just created. It is unclear if it is any data call or the one that was created. | M42: AMR | N42: 40106 | O42: Retest | P42: CVT | Q42: Added statement
A43: 42 | B43: 2.6 | C43: User Mgmt | D43: DC6 | E43: 3 | F43: P | L43: This should be the data call you copied from. | M43: AMR | N43: 40106 | O43: Retest | P43: CVT | Q43: Added "Note: When using this function to validate a newly created data call, select the newly created data call and the source data call for the comparison"
A44: 43 | B44: 2.6 | C44: User Mgmt | D44: DC6 | E44: 4 | F44: P | L44: Refresh next to Audit Data Call. There is another refresh at the top, left corner of the screen. | M44: AMR | N44: 40106 | O44: Retest | P44: CVT | Q44: Added reference
A45: 44 | B45: 2.6 | C45: User Mgmt | D45: DC6 | E45: 5 | L45: The data call I created had $0 for a Target. I left "Baseline Target" checked in Step 4 of the create data call. | M45: AMR | N45: 40106 | O45: Assigned | P45: Bug | Q45: BUG
A46: 45 | B46: 2.6 | C46: User Mgmt | D46: DC6 | E46: PRE | K46: F | L46: Please list steps for how I verify target parameters are the same or fewer. Also, how do you verify the Factor Set it the same? Need to have specific steps or a separate CVT. | M46: AMR | N46: 40106 | O46: Retest | P46: CVT | Q46: Removed this as a precondition and added steps to direct tester to CVT DC3 if they are uncertain about what factor set is used or target parameters
A47: 46 | B47: 2.6 | C47: User Mgmt | D47: DC7 | E47: 1 | K47: F | L47: Please state that this is the data call that was just created. It is unclear if it is any data call or the one that was created. | M47: AMR | N47: 40106 | O47: Retest | P47: CVT | Q47: Added Note
A48: 47 | B48: 2.6 | C48: User Mgmt | D48: DC7 | E48: 2 | I48: F | L48: This should read "Funds Spread" instead of Target. | M48: AMR | N48: 40106 | O48: Retest | P48: CVT | Q48: Changed to funds spread
A49: 48 | B49: 2.6 | C49: User Mgmt | D49: DC7 | E49: 6 | H49: P | L49: This should be the data call you copied from. | M49: AMR | N49: 40106 | O49: Retest | P49: CVT | Q49: Added notation
A50: 49 | B50: 2.6 | C50: User Mgmt | D50: DC7 | E50: 7 | H50: P | L50: Refresh next to Audit Data Call. There is another refresh at the top, left corner of the screen. | M50: AMR | N50: 40106 | O50: Retest | P50: CVT | Q50: Clarified refresh button
A51: 50 | B51: 2.6 | C51: User Mgmt | D51: DC7 | E51: 8 | H51: P | L51: The data call I created had a Funds Spread of $0. I left "Load Funds Spread" checked in Step 4 of the create data call. | M51: AMR | N51: 40106 | O51: Assigned | P51: BUG | Q51: BUG
A52: 51 | B52: 2.6 | C52: User Mgmt | D52: DC7 | E52: PRE | K52: F | L52: Please list steps for how I verify target parameters are the same or fewer. Also, how do you verify the Factor Set it the same? Need to have specific steps or a separate CVT. | M52: AMR | N52: 40106 | O52: Retest | P52: CVT | Q52: Removed from PRE and added steps to verify
A53: 52 | B53: 2.7 | C53: File Mainteance | D53: NAV1 | E53: 5 | F53: F | L53: Some testers may have access to TEST Actual data call too. | M53: AMR | N53: 40107 | O53: Retest | P53: CVT | Q53: CVT Updated
A54: 53 | B54: 2.7 | C54: File Mainteance | D54: NAV2 | E54: 2 | F54: F | L54: Formally FYDP Tool, which does not exist in the Execution Section. | M54: AMR | N54: 40107 | O54: Retest | P54: CVT | Q54: CVT Updated
A55: 54 | C55: File Mainteance | D55: NAV2 | E55: 4 | L55: Suggestion: Create a unique two number-one letter title for each option. Example, 02B will always be associated with QM Funds Spread regardless of user rights or data calls. | M55: AMR | N55: 40107 | O55: Retest | P55: Bug | Q55: Bug: Recommendation. Numbers and syncing completed
A56: 55 | B56: 2.7 | C56: File Mainteance | D56: NAV2 | E56: 7 | L56: Note: In FRM, the report is labeled "SF" FM Datasheet. Please change to "SAF" FM Datasheet. | M56: AMR | N56: 40107 | O56: Retest | P56: CVT | Q56: Label fixed - CVT Updated
A57: 56 | B57: 2.7 | C57: File Mainteance | D57: NAV2 | E57: 12 | F57: F | L57: Is this the same thing as the "Trended Datasheet" in the FYDP section? If so, why does it have a different name? | M57: AMR | N57: 40107 | O57: Retest | P57: CVT | Q57: Label fixed - CVT Updated
A58: 57 | C58: File Mainteance | D58: TGT7 | E58: PRE | F58: P | L58: Didn't we get rid of the "Finalized" status. Please explain how you check if they are in the correct status. | M58: AMR | N58: 40107 | O58: Retest | P58: Question | Q58: CVT
A59: 58 | C59: File Mainteance | D59: TGT7 | E59: 1 | H59: F | L59: Cannot complete this task because the dat call is supposed to be closed | M59: AMR | N59: 40107 | O59: Retest | P59: Bug | Q59: Bug - submitted to Dev Team via e-mail - fixed
A60: 59 | C60: File Mainteance | D60: TGT7 | E60: 2 | F60: F | L60: Please add some details about what values. For example, the dollar amounts are based on my filter. Should they be? | M60: AMR | N60: 40107 | O60: Open | P60: Question | Q60: Question/CVT Updated
A61: 60 | C61: File Mainteance | D61: TGT7 | E61: 3 | G61: F | L61: Cannot click save because the data call is closed. | M61: AMR | N61: 40107 | O61: Retest | P61: Bug | Q61: Bug
A62: 61 | B62: 2.7 | C62: File Mainteance | D62: TGT7 | E62: 4 | F62: P | L62: Changed because we aren't entering data | M62: AMR | N62: 40107 | O62: Retest | P62: CVT | Q62: Added to scenarios
A63: 62 | B63: 2.7 | C63: File Mainteance | D63: TGT7 | E63: 5 | F63: P | L63: Changed because we aren't entering data | M63: AMR | N63: 40107 | O63: Retest | P63: CVT | Q63: Added to scenarios
A64: 63 | B64: 2.7 | C64: File Mainteance | D64: TGT7 | E64: 7 | K64: F | L64: There are two refreshes on the screen. | M64: AMR | N64: 40107 | O64: Retest | P64: CVT | Q64: CVT Updated
A65: 64 | B65: 2.7 | C65: File Mainteance | D65: TGT7 | E65: 9 | K65: F | L65: Execution data call only has one year | M65: AMR | N65: 40107 | O65: Retest | P65: CVT | Q65: CVT
A66: 65 | B66: 2.7 | C66: File Mainteance | D66: TGT7 | E66: 10 | K66: F | L66: Please elaborate. Not sure what this means. | M66: AMR | N66: 40107 | O66: Retest | P66: CVT | Q66: Explain "Data Positions" in CVT
A67: 66 | B67: 2.7 | C67: File Mainteance | D67: TGT7 | E67: 11 | K67: F | L67: Isn't this is in the CVT FS4? | M67: AMR | N67: 40107 | O67: Retest | P67: CVT | Q67: Remove or elaborate on Step in CVT
A68: 67 | B68: 2.7 | C68: File Mainteance | D68: FS4 | E68: PRE | L68: Note: The tester must open QM Funds Spread. The previous CVT is in QM Target | M68: AMR | N68: 40107 | O68: Retest | P68: CVT | Q68: CVT
A69: 68 | B69: 2.7 | C69: File Mainteance | D69: FS4 | E69: 3 | K69: F | L69: Wrong label | M69: AMR | N69: 40107 | O69: Retest | P69: CVT | Q69: CVT
A70: 69 | B70: 2.7 | C70: File Mainteance | D70: FS4 | E70: 5 | G70: F | L70: Missing Step | M70: AMR | N70: 40107 | O70: Retest | P70: CVT | Q70: CVT
A71: 70 | C71: File Mainteance | D71: FS4 | E71: 6 | G71: F | L71: Note: Must click refresh to update numbers at the top of the grid. CVT failed because the data call was locked and should not have allowed me to update funding via Mass funds change. The original number of the locked data call was $179,996 (filtered on A010), but it is now $155,821. It unlocked the data call because I can input/change funding for just the data I was filtered on. | M71: AMR | N71: 40107 | O71: Open | P71: Bug | Q71: Bug/Explanation
A72: 71 | B72: 2.7 | C72: File Mainteance | D72: NAV5 | E72: 2 | K72: F | L72: Previously, FYDP tool | M72: AMR | N72: 40107 | O72: Retest | P72: CVT | Q72: CVT
A73: 72 | B73: 2.7 | C73: File Maintenance | D73: NAV5 | E73: 3 | F73: P | L73: I changed to "Target" from Requirement because the rest of the scenario deals with Targets | M73: AMR | N73: 40107 | O73: Retest | P73: Scenario | Q73: CVT - Scenario referenced incorrect CVT. NAV3 refers to Target
A74: 73 | B74: 2.7 | C74: File Maintenance | D74: NAV5 | E74: 4 | G74: F | L74: I was not prompted for a year because I am in the TEST Exec data call and there is only one year available. | M74: AMR | N74: 40107 | O74: Retest | P74: CVT | Q74: CVT - Updated by removing Select year for Execution CVT.
A75: 74 | B75: 2.7 | C75: File Maintenance | D75: NAV5 | E75: 5 | G75: F | L75: I was not prompted for a year because I am in the TEST Exec data call and there is only one year available. | M75: AMR | N75: 40107 | O75: Retest | P75: CVT | Q75: CVT - Updated by removing Select year for Execution CVT and additional information.
A76: 75 | B76: 2.7 | C76: File Maintenance | D76: FS10 | E76: all | K76: F | L76: This scenario is supposed to verify that maintenance cannot be done on a data call after it has been locked. | M76: AMR | N76: 40107 | O76: Retest | P76: CVT | Q76: CVT Passed based upon Scenario "Expected Results" Task was to lock data call and verify that DC could not be updated. Test failed due to closed(locked) Data Call.
A77: 76 | B77: 5.1 | C77: Data Call Management | D77: DC10 | E77: 3 | K77: F | L77: Note: Previously, this step was missing from the CVT. | M77: AMR | N77: 40107 | O77: Open | P77: Bug | Q77: DC10 has been closed for testing until resolution is complete.
A78: 77 | B78: 5.1 | C78: Data Call Management | D78: DC10 | E78: 4 | G78: F | L78: Cannot check box. It is grayed out. Please reference a powerpoint file that has screen shots. In order to continue with the scenario, I found a work around. | M78: AMR | N78: 40107 | O78: Retest | P78: Bug | Q78: Bug
A79: 78 | B79: 5.1 | C79: Data Call Management | D79: DC10 | E79: NOTE | K79: F | L79: Please list steps to verify if data was moved to a FINALIZED status. Also, I thought we changed this and now the data is either open or closed. | M79: AMR | N79: 40107 | O79: Retest | P79: question | Q79: Question - CVT Update
A80: 79 | B80: 5.1 | C80: File Maintenance | D80: NAV2 | E80: 3 | F80: P | L80: Change to read: "Select option below and Click "Get Data"" | M80: AMR | N80: 40108 | O80: Retest | P80: CVT | Q80: CVT Updated
A81: 80 | B81: 5.1 | C81: File Maintenance | D81: NAV2 | E81: 7 | F81: P | L81: Change to read: "03A QM Funds Spread (Choose year after clicking "Get Data")" | M81: AMR | N81: 40108 | O81: Retest | P81: CVT | Q81: CVT Updated
A82: 81 | B82: 5.1 | C82: File Maintenance | D82: NAV2 | E82: 8 | F82: P | L82: Change to read: "03B QM Target (Choose year after clicking "Get Data")" | M82: AMR | N82: 40108 | O82: Retest | P82: CVT | Q82: CVT Updated
A83: 82 | B83: 5.1 | C83: File Maintenance | D83: NAV2 | E83: 9 | F83: P | L83: Change to read: "03C QM Requirement (Choose year after clicking "Get Data")" | M83: AMR | N83: 40108 | O83: Retest | P83: CVT | Q83: CVT Updated
A84: 83 | B84: 5.1 | C84: File Maintenance | D84: NAV2 | E84: 10 | F84: P | L84: Change to read: "03D FRM Grid (Choose year after clicking "Get Data")" | M84: AMR | N84: 40108 | O84: Retest | P84: CVT | Q84: CVT Updated
A85: 84 | B85: 5.1 | C85: File Maintenance | D85: NAV5 | E85: 2 | F85: P | L85: Click on the double arrow icon to expand the section, click "FYDP Data Call Tool" | M85: AMR | N85: 40108 | O85: Retest | P85: CVT | Q85: CVT Updated
A86: 85 | B86: 5.1 | C86: File Maintenance | D86: NAV5 | E86: NOTE | F86: P | L86: For increased performance, apply filter or search. (Program Group, PEC, and/ or AFFEIC) | M86: AMR | N86: 40108 | O86: Retest | P86: CVT | Q86: CVT Updated
A87: 86 | B87: 5.1 | C87: File Maintenance | D87: RQMT1 | E87: 1 | F87: P | L87: Change to read as follows: "Choose a PCN/Task and adjust the requirement by typing a dollar amount into the RQMT column on the QM - Requirement Grid." Adjustments to Requirements are entered into the appropriate columns in the QM- Requirements grid . | M87: AMR | N87: 40108 | O87: Retest | P87: CVT | Q87: CVT Updated
A88: 87 | B88: 5.1 | C88: File Maintenance | D88: RQMT1 | E88: 2 | F88: P | L88: Change to read as follows: "After adjusting/inputting a requirement, click "save" to save changes. " | M88: AMR | N88: 40108 | O88: Retest | P88: CVT | Q88: CVT Updated
A89: 88 | B89: 5.1 | C89: File Maintenance | D89: RQMT1 | E89: 3 | F89: P | L89: Change to read as follows: "Verify that the adjustment/input made is displaying correctly on the QM - Requirement Grid." | M89: AMR | N89: 40108 | O89: Retest | P89: CVT | Q89: CVT Updated
A90: 89 | B90: 5.1 | C90: File Maintenance | D90: RQMT1 | E90: 4 | F90: P | L90: Change to read as follows: "Select a row on the QM - Requirement Grid by clicking on a single row. " | M90: AMR | N90: 40108 | O90: Retest | P90: CVT | Q90: CVT Updated
A91: 90 | B91: 5.1 | C91: File Maintenance | D91: RQMT1 | E91: 5 | F91: P | L91: Change to read as follows: "Note that the values for that row will display in the PCN/Task Summary row on the tool bar above the QM - Requirement Grid." | M91: AMR | N91: 40108 | O91: Retest | P91: CVT | Q91: CVT Updated
A92: 91 | B92: 5.1 | C92: File Maintenance | D92: RQMT1 | E92: 6 | J92: F | L92: Change to read as follows: "Verify that values are displaying correctly on the PCN/Task Summary row by comparing those values to those on the QM - Requirement Grid" | M92: AMR | N92: 40108 | O92: Retest | P92: CVT | Q92: CVT Updated
A93: 92 | B93: 5.1 | C93: File Maintenance | D93: RQMT1 | E93: 2 | K93: F | L93: Delete this step; new step 2 added above. "Once a row is highlighted, the values for that row will be displayed in the PCN Summary row on the tool bar. " | M93: AMR | N93: 40108 | O93: Retest | P93: CVT | Q93: CVT Updated
A94: 93 | B94: 5.1 | C94: File Maintenance | D94: RQMT1 | E94: 3 | K94: F | L94: Delete this step; new step 3 added above. "Input adjustment values for requirement. " | M94: AMR | N94: 40108 | O94: Retest | P94: CVT | Q94: CVT Updated
A95: 94 | B95: 5.1 | C95: File Maintenance | D95: RQMT1 | E95: 4 | K95: F | L95: Delete this step; new step 4 added above. "Click “Save ” to save changes. " | M95: AMR | N95: 40108 | O95: Retest | P95: CVT | Q95: CVT Updated
A96: 95 | B96: 5.1 | C96: File Maintenance | D96: RPT1 | E96: 5 | F96: P | L96: This is confusing since selecting fields is in the following step. Delete the following: “Check fields to include in Datasheet view” | M96: AMR | N96: 40108 | O96: Retest | P96: CVT | Q96: CVT Updated
A97: 96 | B97: 5.1 | C97: File Maintenance | D97: RPT1 | E97: 7 | F97: P | L97: Suggest adding the following to test script: "Confirm that "Funded" and/or "Required (TY)" are checked under Resource Type. Check "Total w Supp," "Test FYDP," and/or "Supplemental TEST FYDP" at the top of the custom datasheet view." | M97: AMR | N97: 40108 | O97: Retest | P97: CVT | Q97: CVT Updated
A98: 97 | B98: 5.1 | C98: File Maintenance | D98: RPT1 | E98: 11 | G98: F | L98: I checked "Supplemental TEST FYDP" and that data did not appear in the report. Suggest changing to read as follows: "Review and confirm that report contents match the criteria selected on the custom datasheet interface." | M98: AMR | N98: 40108 | O98: Retest | P98: Bug | Q98: CVT Updated
A99: 98 | B99: 5.1 | C99: File Maintenance | D99: RPT1 | E99: 11 | K99: F | L99: Not clear that users/testers needed to compare the data to make sure it matched their selections. Suggest deleting this step; new step 11 added above: "Review report contents based on criteria that you selected and data content." | M99: AMR | N99: 40108 | O99: Retest | P99: CVT | Q99: CVT Updated
A100: 99 | B100: 5.1 | C100: File Maintenance | D100: NAV4 | E100: PRE | F100: P | L100: I understand that these CVTs are used in mulitple scenarios, but it interupts the flow of the scenario. For example, in Scenario 5.1, I have already completed Steps 1-4. | M100: AMR | N100: 40108 | O100: open | P100: CVT | Q100: deferred to meeting
...

Sheet Index
A2: INDEX | C2: 13.2 RELEASE TABS LEGEND | D2: ABOUT
A3: I3 - CVT Master | C3: Pink Tab = Index | D3: ECT - Electronic Case Tracking
A4: (BT44) WWD Memos | C4: Blue Tab = CVT Master
A5: (BT44) IRILO Memos | C5: Orange Tabs = Workflows: WWD Memos, IRILO Memos, MEB Memos, BMT, Informal LOD,
A6: (BT44) MEB Memos | C6: Participation Waiver, Medical Holds, Deployment Waiver, Non Emergent Surgery,
A7: (BT44) BMT WF | C7: Modifications, BCMR, Congressionals, PEPP, Full Search | D7: Version: | E7: 1
A8: Informal LOD | C8: Brown Tab = Common Tools
A9: (BT44) Participation Waiver WF
A10: (BT44) Medical Holds WF | D10: Date: | E10: 41865
A11: (BT44) Deployment Waiver WF
A12: (BT44) Non Emergent Surgery WF
A13: (BT44) Modification WF
A14: (BT44) BCMR WF
A15: (BT44) Congressionals WF
A16: (BT44) PEPP WF
A17: Full Search
A18: TC Common Tools
A24: Status Levels: Requirement or CVT Script
A25: Level | B25: Title | C25: Definition
A27: IP-1 | B27: Development Testing | C27: IP-1: Contractor will provides test materials to test director. The Test Director reviews all test materials and reviews application functionality for functional fit. All test results are compiled and analyzed. The Test Director will approve the release for the next IP based on agreed-upon business rules.
A28: IP-2 | B28: Integration Testing | C28: IP-2: Testing is extended to the test manager. The test manager will perform testing and denote defects using the same methodology used in IP-1. Test results are forwarded to the Test Director. The Test Director will review problem reports and provide direction to ITI based on the failure criticality and requirement priority. When testing aligns with agreed-upon business rules, the Test Director will approve the release for Customer Acceptance Testing.
A29: IP-3 | B29: System Testing | C29: IP-3: During IP-3 Testing, the test group is expanded to a broad set of users selected by the test managers time in the production-simulated environment. Testing is performed with defects denoted using the same methodology used in IP-1/IP-2. Test results are forwarded to ITI and the Test Director for analysis and interpretation. When testing aligns with agreed-upon business rules, the Test Director will approve the testing activities and recommend the release for approval by the LCMB.
A32: MIL-STD-498 DR Definitions
A34: Failure - Cannot proceed to the next step.
A35: Failure | B35: 1a | C35: Prevent the accomplishment of an operational or mission essential capability.
B36: 1b | C36: Jeopardize safety, security, or other requirements designated "critical"
B37: 2a | C37: Adversely affects the accomplishment of an operational or mission essential capability and no work-around solution is known
B38: 2b | C38: Adversely affects technical, cost, or schedule risks to the project or to life cycle support of the system, and no work-around solution
A39: Acceptable: Problems identified but able to advance to the next step.
A40: Acceptable | B40: 3a | C40: Adversely affects the accomplishment of an operation or mission essential capability but a work-around solution is known
B41: 3b | C41: Adversely affects technical, cost or schedule risks to the project or to life cycle support of the system, but a work-around solution is known
B42: 4a | C42: Results in user/operator inconvenience or annoyance but does not affect a required operational or mission essential capability
B43: 4b | C43: Results in inconvenience or annoyance for development or support personnel but does not prevent the accomplishment of those responsibilities.
B44: 5 | C44: Any other effect
A48: Script Status Definitions
A50: P | B50: Pass | C50: CVT Passes; no DRs received.
A51: A | B51: Acceptable | C51: Deficiencies identified but work around exists.
A52: F | B52: Fail | C52: Work Stoppage has been encountered
A53: 0 | B53: Not Tested | C53: CVT is available, but results do not exist due to "in-work" or testing has not started.

Sheet CVT Master List
A1: Audit - Customer Verification Test (CVT)
A2: RQMT # | B2: Priority | C2: CVT | D2: CVT Script Title | E2: Test Status | F2: IP-1 Pass Date | G2: IP-2 Pass Date | H2: IP-3 Pass Date | I2: CVT Status FYDP | M2: CVT Status (NT,A,P,F) | N2: DR # | V2: Comment | W2: CR #, if applicable
J3: Critical | K3: Major | L3: Minor | N3: 1 | O3: 2 | P3: 3 | Q3: 4 | R3: 5 | S3: Critical | T3: Major | U3: Minor
D4: Navigation
A5: FRM 4.3. FRM 4.27 | B5: Major | C5: NAV1 | D5: Select a Data Call | E5: Ready | I5: P | J5: =IF($B5=J$3,$I5,"") | K5: =IF($B5=K$3,$I5,"") -> P | L5: =IF($B5=L$3,$I5,"") | M5: P | S5: =IF($B5=S$3,$M5,"") | T5: =IF($B5=T$3,$M5,"") -> P | U5: =IF($B5=U$3,$M5,"")
A6: N/A | B6: Major | C6: NAV2 | D6: FRM Sections: (Navigate to Inputs, Data Sheet Views, Reports) | E6: Ready | I6: P | J6: =IF($B6=J$3,$I6,"") | K6: =IF($B6=K$3,$I6,"") -> P | L6: =IF($B6=L$3,$I6,"") | M6: P | S6: =IF($B6=S$3,$M6,"") | T6: =IF($B6=T$3,$M6,"") -> P | U6: =IF($B6=U$3,$M6,"") | V6: CVT Updates Applied
A7: FM 5.1-5.2 | B7: Major | C7: NAV3 | D7: Navigate to "Target Maintenance" | E7: Ready | I7: P | J7: =IF($B7=J$3,$I7,"") | K7: =IF($B7=K$3,$I7,"") -> P | L7: =IF($B7=L$3,$I7,"") | M7: P | S7: =IF($B7=S$3,$M7,"") | T7: =IF($B7=T$3,$M7,"") -> P | U7: =IF($B7=U$3,$M7,"") | V7: CVT Updates Applied
A8: FRM 6.1-6.2 | B8: Critical | C8: NAV4 | D8: Navigate to "QM Funds Spread" | E8: Ready | I8: P | J8: =IF($B8=J$3,$I8,"") -> P | K8: =IF($B8=K$3,$I8,"") | L8: =IF($B8=L$3,$I8,"") | M8: P | N8: X | R8: X | S8: =IF($B8=S$3,$M8,"") -> P | T8: =IF($B8=T$3,$M8,"") | U8: =IF($B8=U$3,$M8,"") | V8: CVT Updates Applied
A9: FRM 7.1 | B9: Critical | C9: NAV5 | D9: RQMT ADJUSTMENT: QM (Quick Maintenance) Requirement: Access Grid | E9: Ready | I9: P | J9: =IF($B9=J$3,$I9,"") -> P | K9: =IF($B9=K$3,$I9,"") | L9: =IF($B9=L$3,$I9,"") | M9: P | N9: X | S9: =IF($B9=S$3,$M9,"") -> P | T9: =IF($B9=T$3,$M9,"") | U9: =IF($B9=U$3,$M9,"")
D10: User Mgmt
A11: - | B11: Critical | C11: UM1 | D11: FRM Basics: Register for FRM | E11: Ready | I11: N/A | J11: =IF($B11=J$3,$I11,"") -> N/A | K11: =IF($B11=K$3,$I11,"") | L11: =IF($B11=L$3,$I11,"") | M11: N/A | S11: =IF($B11=S$3,$M11,"") -> N/A | T11: =IF($B11=T$3,$M11,"") | U11: =IF($B11=U$3,$M11,"") | V11: Recommend removing from this test agenda
A12: FRM 1.1 - 1.5 | B12: Critical | C12: UM2 | D12: Activate User (Generic) | E12: Ready | I12: P | J12: =IF($B12=J$3,$I12,"") -> P | K12: =IF($B12=K$3,$I12,"") | L12: =IF($B12=L$3,$I12,"") | M12: P | S12: =IF($B12=S$3,$M12,"") -> P | T12: =IF($B12=T$3,$M12,"") | U12: =IF($B12=U$3,$M12,"")
A13: FRM 1.1 - 1.5 | B13: Critical | C13: UM3 | D13: Confirm Activated User | E13: Ready | I13: P | J13: =IF($B13=J$3,$I13,"") -> P | K13: =IF($B13=K$3,$I13,"") | L13: =IF($B13=L$3,$I13,"") | M13: P | S13: =IF($B13=S$3,$M13,"") -> P | T13: =IF($B13=T$3,$M13,"") | U13: =IF($B13=U$3,$M13,"")
A14: FRM 1.1 - 1.5 | B14: Critical | C14: UM4 | D14: Confirm Filter | E14: Ready | I14: R | J14: =IF($B14=J$3,$I14,"") -> R | K14: =IF($B14=K$3,$I14,"") | L14: =IF($B14=L$3,$I14,"") | M14: R | S14: =IF($B14=S$3,$M14,"") -> R | T14: =IF($B14=T$3,$M14,"") | U14: =IF($B14=U$3,$M14,"") | V14: Change to be made to add PEC
A15: FRM 1.1 - 1.5 | B15: Major | C15: UM5 | D15: Confirm User Management Roles | E15: Ready | I15: P | J15: =IF($B15=J$3,$I15,"") | K15: =IF($B15=K$3,$I15,"") -> P | L15: =IF($B15=L$3,$I15,"") | M15: P | S15: =IF($B15=S$3,$M15,"") | T15: =IF($B15=T$3,$M15,"") -> P | U15: =IF($B15=U$3,$M15,"")
D16: Data Call Roles
A17: 4.8, 1.1, 1.2 | B17: Critical | C17: DCROLE1 | D17: Manage Roles and Responsibility | E17: Ready | I17: P | J17: =IF($B17=J$3,$I17,"") -> P | K17: =IF($B17=K$3,$I17,"") | L17: =IF($B17=L$3,$I17,"") | M17: P | S17: =IF($B17=S$3,$M17,"") -> P | T17: =IF($B17=T$3,$M17,"") | U17: =IF($B17=U$3,$M17,"")
A18: 4.8 | B18: Major | C18: DCROLE2 | D18: Review Roles and Responsibilities by Users | E18: Ready | I18: P | J18: =IF($B18=J$3,$I18,"") | K18: =IF($B18=K$3,$I18,"") -> P | L18: =IF($B18=L$3,$I18,"") | M18: P | S18: =IF($B18=S$3,$M18,"") | T18: =IF($B18=T$3,$M18,"") -> P | U18: =IF($B18=U$3,$M18,"")
A19: 4.8, 4.12 | B19: Major | C19: DCROLE3 | D19: Review Roles and Responsibilities by Affiliation | E19: Ready | I19: P | J19: =IF($B19=J$3,$I19,"") | K19: =IF($B19=K$3,$I19,"") -> P | L19: =IF($B19=L$3,$I19,"") | M19: P | S19: =IF($B19=S$3,$M19,"") | T19: =IF($B19=T$3,$M19,"") -> P | U19: =IF($B19=U$3,$M19,"")
A20: 2.3 | B20: Critical | C20: DCROLE4 | D20: Search for User | E20: Ready | I20: P | J20: =IF($B20=J$3,$I20,"") -> P | K20: =IF($B20=K$3,$I20,"") | L20: =IF($B20=L$3,$I20,"") | M20: P | S20: =IF($B20=S$3,$M20,"") -> P | T20: =IF($B20=T$3,$M20,"") | U20: =IF($B20=U$3,$M20,"")
A21: 4.4, 4.8 | B21: Major | C21: DCROLE5 | D21: Mass Change User Roles - Add Roles | E21: Ready | I21: P | J21: =IF($B21=J$3,$I21,"") | K21: =IF($B21=K$3,$I21,"") -> P | L21: =IF($B21=L$3,$I21,"") | M21: P | S21: =IF($B21=S$3,$M21,"") | T21: =IF($B21=T$3,$M21,"") -> P | U21: =IF($B21=U$3,$M21,"")
A22: 4.4, 4.8 | B22: Major | C22: DCROLE6 | D22: Mass Change User Roles - Remove Roles | E22: Ready | I22: P | J22: =IF($B22=J$3,$I22,"") | K22: =IF($B22=K$3,$I22,"") -> P | L22: =IF($B22=L$3,$I22,"") | M22: P | S22: =IF($B22=S$3,$M22,"") | T22: =IF($B22=T$3,$M22,"") -> P | U22: =IF($B22=U$3,$M22,"")
D23: Create Data Call
A24: 4.9, 4.10 | B24: Critical | C24: DC1 | D24: Create Execution Data Call | E24: unpredictable results | I24: Data call | J24: =IF($B24=J$3,$I24,"") -> Data call | K24: =IF($B24=K$3,$I24,"") | L24: =IF($B24=L$3,$I24,"") | M24: NT | S24: =IF($B24=S$3,$M24,"") -> NT | T24: =IF($B24=T$3,$M24,"") | U24: =IF($B24=U$3,$M24,"")
A25: 4.9, 4.10 | B25: Critical | C25: DC2 | D25: Create FYDP FRM Data Call | E25: unpredictable results | I25: Data call | J25: =IF($B25=J$3,$I25,"") -> Data call | K25: =IF($B25=K$3,$I25,"") | L25: =IF($B25=L$3,$I25,"") | M25: NT | S25: =IF($B25=S$3,$M25,"") -> NT | T25: =IF($B25=T$3,$M25,"") | U25: =IF($B25=U$3,$M25,"")
A26: FRM 4.12, 4.15-4.17 | B26: Critical | C26: DC3 | D26: Review Data Call Options | E26: Ready | I26: R | J26: =IF($B26=J$3,$I26,"") -> R | K26: =IF($B26=K$3,$I26,"") | L26: =IF($B26=L$3,$I26,"") | M26: R | S26: =IF($B26=S$3,$M26,"") -> R | T26: =IF($B26=T$3,$M26,"") | U26: =IF($B26=U$3,$M26,"") | V26: CVT updates applied
A27: FRM 4.11 | B27: Critical | C27: DC4 | D27: Add Years to Data Call | E27: Ready | I27: Data call | J27: =IF($B27=J$3,$I27,"") -> Data call | K27: =IF($B27=K$3,$I27,"") | L27: =IF($B27=L$3,$I27,"") | M27: NT | S27: =IF($B27=S$3,$M27,"") -> NT | T27: =IF($B27=T$3,$M27,"") | U27: =IF($B27=U$3,$M27,"")
A28: FRM 7.6, 4.2 | B28: Critical | C28: DC5 | D28: Audit Requirement | E28: Ready | I28: Data call | J28: =IF($B28=J$3,$I28,"") -> Data call | K28: =IF($B28=K$3,$I28,"") | L28: =IF($B28=L$3,$I28,"") | M28: NT | S28: =IF($B28=S$3,$M28,"") -> NT | T28: =IF($B28=T$3,$M28,"") | U28: =IF($B28=U$3,$M28,"")
A29: FRM 5.6 | B29: Major | C29: DC6 | D29: Audit Target | E29: Ready | I29: Data call | J29: =IF($B29=J$3,$I29,"") | K29: =IF($B29=K$3,$I29,"") -> Data call | L29: =IF($B29=L$3,$I29,"") | M29: NT | S29: =IF($B29=S$3,$M29,"") | T29: =IF($B29=T$3,$M29,"") -> NT | U29: =IF($B29=U$3,$M29,"")
A30: FRM 6.8, FRM 6.9 | B30: Major | C30: DC7 | D30: Audit Funds Spread | E30: Ready | I30: Data call | J30: =IF($B30=J$3,$I30,"") | K30: =IF($B30=K$3,$I30,"") -> Data call | L30: =IF($B30=L$3,$I30,"") | M30: NT | S30: =IF($B30=S$3,$M30,"") | T30: =IF($B30=T$3,$M30,"") -> NT | U30: =IF($B30=U$3,$M30,"")
A31: Missing | B31: Minor | C31: DC8 | D31: Delete Data Call | E31: Ready | I31: Data call | J31: =IF($B31=J$3,$I31,"") | K31: =IF($B31=K$3,$I31,"") | L31: =IF($B31=L$3,$I31,"") -> Data call | M31: NT | S31: =IF($B31=S$3,$M31,"") | T31: =IF($B31=T$3,$M31,"") | U31: =IF($B31=U$3,$M31,"") -> NT
A32: 4.8,4.4 | B32: Major | C32: DC9 | D32: Certify Data Call Ready for File Maintenance | E32: Ready | I32: Data call | J32: =IF($B32=J$3,$I32,"") | K32: =IF($B32=K$3,$I32,"") -> Data call | L32: =IF($B32=L$3,$I32,"") | M32: NT | S32: =IF($B32=S$3,$M32,"") | T32: =IF($B32=T$3,$M32,"") -> NT | U32: =IF($B32=U$3,$M32,"")
A33: 4.4, 5.12, 6.11 | B33: Critical | C33: DC10 | D33: Close Data Call | E33: Ready | I33: Data call | J33: =IF($B33=J$3,$I33,"") -> Data call | K33: =IF($B33=K$3,$I33,"") | L33: =IF($B33=L$3,$I33,"") | M33: NT | S33: =IF($B33=S$3,$M33,"") -> NT | T33: =IF($B33=T$3,$M33,"") | U33: =IF($B33=U$3,$M33,"")
D34: Prepare Data Call Data
A35: FRM 4.4, 4.13, 6.3 | B35: Major | C35: MassDC1 | D35: Overlay DC Funding | E35: DUPLICATE | I35: DUP | J35: =IF($B35=J$3,$I35,"") | K35: =IF($B35=K$3,$I35,"") -> DUP | L35: =IF($B35=L$3,$I35,"") | M35: DUP | S35: =IF($B35=S$3,$M35,"") | T35: =IF($B35=T$3,$M35,"") -> DUP | U35: =IF($B35=U$3,$M35,"") | V35: =+"Refer to FS9, Status: "& M64 -> Refer to FS9, Status: P
A36: FRM 4.4, 4.13 | B36: Major | C36: MassDC2 | D36: Mass Change: Update Status | E36: Ready | I36: NA | J36: =IF($B36=J$3,$I36,"") | K36: =IF($B36=K$3,$I36,"") -> NA | L36: =IF($B36=L$3,$I36,"") | M36: NA | S36: =IF($B36=S$3,$M36,"") | T36: =IF($B36=T$3,$M36,"") -> NA | U36: =IF($B36=U$3,$M36,"")
A37: FRM 4.4, 4.13, 6.3 | B37: Major | C37: MassDC3 | D37: Mass Change: 70% Spread to Target by Priority | E37: DUPLICATE | I37: DUP | J37: =IF($B37=J$3,$I37,"") | K37: =IF($B37=K$3,$I37,"") -> DUP | L37: =IF($B37=L$3,$I37,"") | M37: DUP | S37: =IF($B37=S$3,$M37,"") | T37: =IF($B37=T$3,$M37,"") -> DUP | U37: =IF($B37=U$3,$M37,"") | V37: =+"Refer to FS3, Status: "& +M58 -> Refer to FS3, Status: R
A38: FRM 4.4, 4.13, 6.3 | B38: Critical | C38: MassDC4 | D38: Mass Change: Fully Fund to Target | E38: DUPLICATE | I38: DUP | J38: =IF($B38=J$3,$I38,"") -> DUP | K38: =IF($B38=K$3,$I38,"") | L38: =IF($B38=L$3,$I38,"") | M38: DUP | S38: =IF($B38=S$3,$M38,"") -> DUP | T38: =IF($B38=T$3,$M38,"") | U38: =IF($B38=U$3,$M38,"") | V38: =+"Refer to FS4, Status: "& +M59 -> Refer to FS4, Status: P
A39: FRM 4.4, 4.13, 6.3 | B39: Major | C39: MassDC5 | D39: Mass Change: OP30 Spread; next 70% Spread to Target by Priority | E39: DUPLICATE | I39: DUP | J39: =IF($B39=J$3,$I39,"") | K39: =IF($B39=K$3,$I39,"") -> DUP | L39: =IF($B39=L$3,$I39,"") | M39: DUP | S39: =IF($B39=S$3,$M39,"") | T39: =IF($B39=T$3,$M39,"") -> DUP | U39: =IF($B39=U$3,$M39,"") | V39: =+"Refer to FS5, Status: "& +M60 -> Refer to FS5, Status: R
A40: FRM 4.4, 4.13, 6.3 | B40: Major | C40: MassDC6 | D40: Mass Change: Fully Fund | E40: DUPLICATE | I40: DUP | J40: =IF($B40=J$3,$I40,"") | K40: =IF($B40=K$3,$I40,"") -> DUP | L40: =IF($B40=L$3,$I40,"") | M40: DUP | S40: =IF($B40=S$3,$M40,"") | T40: =IF($B40=T$3,$M40,"") -> DUP | U40: =IF($B40=U$3,$M40,"") | V40: =+"Refer to FS6, Status: "& +M61 -> Refer to FS6, Status: R
A41: FRM 4.4, 4.13, 6.3 | B41: Major | C41: MassDC7 | D41: Mass Change: Unfund | E41: DUPLICATE | I41: DUP | J41: =IF($B41=J$3,$I41,"") | K41: =IF($B41=K$3,$I41,"") -> DUP | L41: =IF($B41=L$3,$I41,"") | M41: DUP | S41: =IF($B41=S$3,$M41,"") | T41: =IF($B41=T$3,$M41,"") -> DUP | U41: =IF($B41=U$3,$M41,"") | V41: =+"Refer to FS7, Status: "& +M62 -> Refer to FS7, Status: P
A42: FRM 4.4, 4.13,5.2 | B42: Major | C42: MassDC8 | D42: Overlay Target | E42: DUPLICATE | I42: DUP | J42: =IF($B42=J$3,$I42,"") | K42: =IF($B42=K$3,$I42,"") -> DUP | L42: =IF($B42=L$3,$I42,"") | M42: DUP | S42: =IF($B42=S$3,$M42,"") | T42: =IF($B42=T$3,$M42,"") -> DUP | U42: =IF($B42=U$3,$M42,"")
A43: FRM 4.4, 4.13,5.2 | B43: Major | C43: MassDC9 | D43: Copy Target to Target | E43: DUPLICATE | I43: DUP | J43: =IF($B43=J$3,$I43,"") | K43: =IF($B43=K$3,$I43,"") -> DUP | L43: =IF($B43=L$3,$I43,"") | M43: DUP | S43: =IF($B43=S$3,$M43,"") | T43: =IF($B43=T$3,$M43,"") -> DUP | U43: =IF($B43=U$3,$M43,"") | V43: Refer to TGT2, Status:
A44: FRM 4.4, 4.13,5.2 | B44: Major | C44: MassDC10 | D44: Get (Append) Target | E44: DUPLICATE | I44: DUP | J44: =IF($B44=J$3,$I44,"") | K44: =IF($B44=K$3,$I44,"") -> DUP | L44: =IF($B44=L$3,$I44,"") | M44: DUP | S44: =IF($B44=S$3,$M44,"") | T44: =IF($B44=T$3,$M44,"") -> DUP | U44: =IF($B44=U$3,$M44,"")
D45: Targets
A46: 5.2, 5.13, 4.4 | B46: Major | C46: TGT2 | D46: DATA MAINTENANCE: Mass Change: Copy Target to Target | E46: Ready | I46: P | J46: =IF($B46=J$3,$I46,"") | K46: =IF($B46=K$3,$I46,"") -> P | L46: =IF($B46=L$3,$I46,"") | M46: P | S46: =IF($B46=S$3,$M46,"") | T46: =IF($B46=T$3,$M46,"") -> P | U46: =IF($B46=U$3,$M46,"")
A47: 5.2, 5.13, 4.4 | B47: Major | C47: TGT3 | D47: Target Maintenance: Mass Change: Zero out all Targets | E47: Ready | I47: P | J47: =IF($B47=J$3,$I47,"") | K47: =IF($B47=K$3,$I47,"") -> P | L47: =IF($B47=L$3,$I47,"") | M47: P | S47: =IF($B47=S$3,$M47,"") | T47: =IF($B47=T$3,$M47,"") -> P | U47: =IF($B47=U$3,$M47,"")
A48: 5.2, 5.13, 4.4 | B48: Major | C48: TGT4 | D48: Target Maintenance: Mass Change: Reset Target to Reference (Baseline) | E48: Ready | I48: P | J48: =IF($B48=J$3,$I48,"") | K48: =IF($B48=K$3,$I48,"") -> P | L48: =IF($B48=L$3,$I48,"") | M48: P | S48: =IF($B48=S$3,$M48,"") | T48: =IF($B48=T$3,$M48,"") -> P | U48: =IF($B48=U$3,$M48,"")
A49: 5.2, 5.13, 4.4 | B49: Major | C49: TGT5 | D49: Target Maintenance: Balance Target Amounts | E49: Ready | I49: A | J49: =IF($B49=J$3,$I49,"") | K49: =IF($B49=K$3,$I49,"") -> A | L49: =IF($B49=L$3,$I49,"") | M49: A | S49: =IF($B49=S$3,$M49,"") | T49: =IF($B49=T$3,$M49,"") -> A | U49: =IF($B49=U$3,$M49,"")
A50: FRM 4.4 | B50: Major | C50: TGT6 | D50: DATA MAINTENANCE: Mass Change: Update Status | E50: Ready | I50: HOLD | J50: =IF($B50=J$3,$I50,"") | K50: =IF($B50=K$3,$I50,"") -> HOLD | L50: =IF($B50=L$3,$I50,"") | M50: HOLD | S50: =IF($B50=S$3,$M50,"") | T50: =IF($B50=T$3,$M50,"") -> HOLD | U50: =IF($B50=U$3,$M50,"")
A51: 5.2 | B51: Critical | C51: TGT7 | D51: Maintain Target Amounts (Quick Maintenance) | E51: Ready | I51: P | J51: =IF($B51=J$3,$I51,"") -> P | K51: =IF($B51=K$3,$I51,"") | L51: =IF($B51=L$3,$I51,"") | M51: P | S51: =IF($B51=S$3,$M51,"") -> P | T51: =IF($B51=T$3,$M51,"") | U51: =IF($B51=U$3,$M51,"")
A52: 4.4, 5.10 | B52: Critical | C52: TGT8 | D52: Target Maintenance: Mass change: Copy Budget Reference to Budget Reference. | E52: Ready | I52: P | J52: =IF($B52=J$3,$I52,"") -> P | K52: =IF($B52=K$3,$I52,"") | L52: =IF($B52=L$3,$I52,"") | M52: P | S52: =IF($B52=S$3,$M52,"") -> P | T52: =IF($B52=T$3,$M52,"") | U52: =IF($B52=U$3,$M52,"")
A53: 4.4, 5.10 | B53: Critical | C53: TGT9 | D53: Target Maintenance: Mass change: Overlay Reference to Target | E53: Ready | I53: P | J53: =IF($B53=J$3,$I53,"") -> P | K53: =IF($B53=K$3,$I53,"") | L53: =IF($B53=L$3,$I53,"") | M53: P | S53: =IF($B53=S$3,$M53,"") -> P | T53: =IF($B53=T$3,$M53,"") | U53: =IF($B53=U$3,$M53,"")
A54: 4.4, 5.10 | B54: Critical | C54: TGT10 | D54: Target Maintenance: Mass change: Show Budget Reference w/o RQMT | E54: Ready | I54: R | J54: =IF($B54=J$3,$I54,"") -> R | K54: =IF($B54=K$3,$I54,"") | L54: =IF($B54=L$3,$I54,"") | M54: R | S54: =IF($B54=S$3,$M54,"") -> R | T54: =IF($B54=T$3,$M54,"") | U54: =IF($B54=U$3,$M54,"")
B55: Major | C55: TGT11 | D55: Target Maintenance: Overlay Target | E55: Ready | I55: NT | J55: =IF($B55=J$3,$I55,"") | K55: =IF($B55=K$3,$I55,"") -> NT | L55: =IF($B55=L$3,$I55,"") | M55: NT | S55: =IF($B55=S$3,$M55,"") | T55: =IF($B55=T$3,$M55,"") -> NT | U55: =IF($B55=U$3,$M55,"") | V55: NEWLY ADDED, 11/17
B56: Major | C56: TGT12 | D56: Target Maintenance: Get (Append) Target | E56: Ready | I56: R | J56: =IF($B56=J$3,$I56,"") | K56: =IF($B56=K$3,$I56,"") -> R | L56: =IF($B56=L$3,$I56,"") | M56: R | S56: =IF($B56=S$3,$M56,"") | T56: =IF($B56=T$3,$M56,"") -> R | U56: =IF($B56=U$3,$M56,"") | V56: NEWLY ADDED, 11/17
D57: Funds Spread
A58: FRM 6.1 - 6.13 | B58: Critical | C58: FS3 | D58: Mass Change: 70% Spread to Target by Priority | E58: Ready | I58: R | J58: =IF($B58=J$3,$I58,"") -> R | K58: =IF($B58=K$3,$I58,"") | L58: =IF($B58=L$3,$I58,"") | M58: R | S58: =IF($B58=S$3,$M58,"") -> R | T58: =IF($B58=T$3,$M58,"") | U58: =IF($B58=U$3,$M58,"") | V58: Not 70%
A59: FRM 6.1 - 6.13 | B59: Critical | C59: FS4 | D59: Mass Change: Fully Fund to Target | E59: Ready | I59: P | J59: =IF($B59=J$3,$I59,"") -> P | K59: =IF($B59=K$3,$I59,"") | L59: =IF($B59=L$3,$I59,"") | M59: P | S59: =IF($B59=S$3,$M59,"") -> P | T59: =IF($B59=T$3,$M59,"") | U59: =IF($B59=U$3,$M59,"")
A60: FRM 6.1 - 6.13 | B60: Critical | C60: FS5 | D60: Mass Change: OP30 Spread by Priority; Next Spread to Remaining PCNs/Task by Priority | E60: Ready | I60: R | J60: =IF($B60=J$3,$I60,"") -> R | K60: =IF($B60=K$3,$I60,"") | L60: =IF($B60=L$3,$I60,"") | M60: R | S60: =IF($B60=S$3,$M60,"") -> R | T60: =IF($B60=T$3,$M60,"") | U60: =IF($B60=U$3,$M60,"") | V60: #2 priority is not being funded
A61: FRM 6.1 - 6.13 | B61: Critical | C61: FS6 | D61: Mass Change: Fully Fund | E61: Ready | I61: R | J61: =IF($B61=J$3,$I61,"") -> R | K61: =IF($B61=K$3,$I61,"") | L61: =IF($B61=L$3,$I61,"") | M61: R | S61: =IF($B61=S$3,$M61,"") -> R | T61: =IF($B61=T$3,$M61,"") | U61: =IF($B61=U$3,$M61,"") | V61: Verbiage added to advise users to review results for rounding errors
A62: FRM 6.1 - 6.13 | B62: Critical | C62: FS7 | D62: Mass Change: Unfund | E62: Ready | I62: P | J62: =IF($B62=J$3,$I62,"") -> P | K62: =IF($B62=K$3,$I62,"") | L62: =IF($B62=L$3,$I62,"") | M62: P | S62: =IF($B62=S$3,$M62,"") -> P | T62: =IF($B62=T$3,$M62,"") | U62: =IF($B62=U$3,$M62,"")
A63: FRM 6.1 - 6.13 | B63: Critical | C63: FS8 | D63: Straight Line Requirement | E63: Ready | I63: A | J63: =IF($B63=J$3,$I63,"") -> A | K63: =IF($B63=K$3,$I63,"") | L63: =IF($B63=L$3,$I63,"") | M63: A | S63: =IF($B63=S$3,$M63,"") -> A | T63: =IF($B63=T$3,$M63,"") | U63: =IF($B63=U$3,$M63,"") | V63: Need to add note that this is for new RQMT only
A64: FRM 6.1 - 6.13 | B64: Critical | C64: FS9 | D64: Overlay DC Funding | E64: Ready | I64: P | J64: =IF($B64=J$3,$I64,"") -> P | K64: =IF($B64=K$3,$I64,"") | L64: =IF($B64=L$3,$I64,"") | M64: P | S64: =IF($B64=S$3,$M64,"") -> P | T64: =IF($B64=T$3,$M64,"") | U64: =IF($B64=U$3,$M64,"")
A65: FRM 6.1 - 6.13 | B65: Critical | C65: FS10 | D65: FUNDS SPREADS: Update Individual Funds Spreads | E65: Ready | I65: R | J65: =IF($B65=J$3,$I65,"") -> R | K65: =IF($B65=K$3,$I65,"") | L65: =IF($B65=L$3,$I65,"") | M65: R | S65: =IF($B65=S$3,$M65,"") -> R | T65: =IF($B65=T$3,$M65,"") | U65: =IF($B65=U$3,$M65,"") | V65: Program group HH60/FY11/ Qty field is not working. PCN AAJRTR
D66: Analysis and Reporting
A67: FRM 4.23, 4.25, 6.4, 6.24 | B67: Critical | C67: RPT1 | D67: DATASHEET VIEW: 02* Custom | E67: Ready | I67: A | J67: =IF($B67=J$3,$I67,"") -> A | K67: =IF($B67=K$3,$I67,"") | L67: =IF($B67=L$3,$I67,"") | M67: A | S67: =IF($B67=S$3,$M67,"") -> A | T67: =IF($B67=T$3,$M67,"") | U67: =IF($B67=U$3,$M67,"") | V67: email option not working
A68: FRM 3.6 | B68: Critical | C68: RPT2 | D68: DATASHEET VIEW: Analysis: Check Data Positions ( $ Summary Grid:) | E68: Ready | I68: R | J68: =IF($B68=J$3,$I68,"") -> R | K68: =IF($B68=K$3,$I68,"") | L68: =IF($B68=L$3,$I68,"") | M68: R | S68: =IF($B68=S$3,$M68,"") -> R | T68: =IF($B68=T$3,$M68,"") | U68: =IF($B68=U$3,$M68,"") | V68: Changes ready for review
A69: FRM 6.4, 6.24 | B69: Major | C69: RPT3 | D69: DATASHEET VIEW: Compare: Compare Requirement from Past Exercises (Growth Analysis - Chart icon)) | E69: Do Not Test | I69: REM | J69: =IF($B69=J$3,$I69,"") | K69: =IF($B69=K$3,$I69,"") -> REM | L69: =IF($B69=L$3,$I69,"") | M69: REM | S69: =IF($B69=S$3,$M69,"") | T69: =IF($B69=T$3,$M69,"") -> REM | U69: =IF($B69=U$3,$M69,"")
A70: FRM 5.1 | B70: Major | C70: RPT4 | D70: DATASHEET VIEW: 02A-Target Audit | E70: Ready | I70: R | J70: =IF($B70=J$3,$I70,"") | K70: =IF($B70=K$3,$I70,"") -> R | L70: =IF($B70=L$3,$I70,"") | M70: R | S70: =IF($B70=S$3,$M70,"") | T70: =IF($B70=T$3,$M70,"") -> R | U70: =IF($B70=U$3,$M70,"") | V70: Updates to ZBT
A71: FRM 3.2-3.5 | B71: Major | C71: RPT5 | D71: DATASHEET VIEW: Workload Summary, view progress of a data call | E71: Ready | I71: R | J71: =IF($B71=J$3,$I71,"") | K71: =IF($B71=K$3,$I71,"") -> R | L71: =IF($B71=L$3,$I71,"") | M71: R | S71: =IF($B71=S$3,$M71,"") | T71: =IF($B71=T$3,$M71,"") -> R | U71: =IF($B71=U$3,$M71,"") | V71: No Scrolling
A72: FRM 4.23, 4.25 | B72: Major | C72: RPT6 | D72: FYDP Tool: 02E - Compare Datasheet | E72: Ready | I72: R | J72: =IF($B72=J$3,$I72,"") | K72: =IF($B72=K$3,$I72,"") -> R | L72: =IF($B72=L$3,$I72,"") | M72: R | S72: =IF($B72=S$3,$M72,"") | T72: =IF($B72=T$3,$M72,"") -> R | U72: =IF($B72=U$3,$M72,"") | V72: Report timed out
A73: FRM 3.6 | B73: Major | C73: RPT7 | D73: FYDP Tool: 02F - Trended Datasheet | E73: Ready | I73: P | J73: =IF($B73=J$3,$I73,"") | K73: =IF($B73=K$3,$I73,"") -> P | L73: =IF($B73=L$3,$I73,"") | M73: P | S73: =IF($B73=S$3,$M73,"") | T73: =IF($B73=T$3,$M73,"") -> P | U73: =IF($B73=U$3,$M73,"")
A74: FRM 4.23, 4.25, 6.4 | B74: Critical | C74: RPT8 | D74: FYDP Tool: 02C - SAF FM Datasheet | E74: Ready | I74: P | J74: =IF($B74=J$3,$I74,"") -> P | K74: =IF($B74=K$3,$I74,"") | L74: =IF($B74=L$3,$I74,"") | M74: P | S74: =IF($B74=S$3,$M74,"") -> P | T74: =IF($B74=T$3,$M74,"") | U74: =IF($B74=U$3,$M74,"")
A75: FRM 7.4 | B75: Major | C75: RPT9 | D75: DATASHEET VIEW: 02G Factors | E75: Ready | I75: P | J75: =IF($B75=J$3,$I75,"") | K75: =IF($B75=K$3,$I75,"") -> P | L75: =IF($B75=L$3,$I75,"") | M75: P | S75: =IF($B75=S$3,$M75,"") | T75: =IF($B75=T$3,$M75,"") -> P | U75: =IF($B75=U$3,$M75,"")
A76: FRM 4.18 | B76: Major | C76: RPT10 | D76: Execution Section: 01A Report FRM Distribution | E76: Ready | I76: Execution | J76: =IF($B76=J$3,$I76,"") | K76: =IF($B76=K$3,$I76,"") -> Execution | L76: =IF($B76=L$3,$I76,"") | M76: NT | S76: =IF($B76=S$3,$M76,"") | T76: =IF($B76=T$3,$M76,"") -> NT | U76: =IF($B76=U$3,$M76,"")
A77: FRM 4.19 | B77: Major | C77: RPT11 | D77: Execution Section: 01B Report FRM Obligation | E77: Ready | I77: Execution | J77: =IF($B77=J$3,$I77,"") | K77: =IF($B77=K$3,$I77,"") -> Execution | L77: =IF($B77=L$3,$I77,"") | M77: NT | S77: =IF($B77=S$3,$M77,"") | T77: =IF($B77=T$3,$M77,"") -> NT | U77: =IF($B77=U$3,$M77,"")
D78: Common Tools
A79: FRM 2.3 | B79: Major | C79: TOOLS1 | D79: Find a PCN | E79: Ready | I79: P | J79: =IF($B79=J$3,$I79,"") | K79: =IF($B79=K$3,$I79,"") -> P | L79: =IF($B79=L$3,$I79,"") | M79: P | S79: =IF($B79=S$3,$M79,"") | T79: =IF($B79=T$3,$M79,"") -> P | U79: =IF($B79=U$3,$M79,"")
A80: FRM 2.4 | B80: Major | C80: TOOLS2 | D80: Find a Task | E80: Ready | I80: P | J80: =IF($B80=J$3,$I80,"") | K80: =IF($B80=K$3,$I80,"") -> P | L80: =IF($B80=L$3,$I80,"") | M80: P | S80: =IF($B80=S$3,$M80,"") | T80: =IF($B80=T$3,$M80,"") -> P | U80: =IF($B80=U$3,$M80,"")
A81: FRM 2.1, 2.2, 2.5 | B81: Major | C81: TOOLS3 | D81: Applied Filter: Limit Data | E81: Ready | I81: P | J81: =IF($B81=J$3,$I81,"") | K81: =IF($B81=K$3,$I81,"") -> P | L81: =IF($B81=L$3,$I81,"") | M81: P | S81: =IF($B81=S$3,$M81,"") | T81: =IF($B81=T$3,$M81,"") -> P | U81: =IF($B81=U$3,$M81,"")
B82: Minor | C82: TOOLS4 | D82: Sort Grid Data | E82: Ready | I82: P | J82: =IF($B82=J$3,$I82,"") | K82: =IF($B82=K$3,$I82,"") | L82: =IF($B82=L$3,$I82,"") -> P | M82: P | S82: =IF($B82=S$3,$M82,"") | T82: =IF($B82=T$3,$M82,"") | U82: =IF($B82=U$3,$M82,"") -> P
A83: FRM 4.1 | B83: Critical | C83: TOOLS 5 | D83: DATA MAINTENANCE: Add New PCN/Task | E83: Ready | I83: P | J83: =IF($B83=J$3,$I83,"") -> P | K83: =IF($B83=K$3,$I83,"") | L83: =IF($B83=L$3,$I83,"") | M83: P | S83: =IF($B83=S$3,$M83,"") -> P | T83: =IF($B83=T$3,$M83,"") | U83: =IF($B83=U$3,$M83,"")
A84: FRM 4.1 | B84: Critical | C84: TOOLS6 | D84: DATA MAINTENANCE: Edit PCN Attributes | E84: Ready | I84: P | J84: =IF($B84=J$3,$I84,"") -> P | K84: =IF($B84=K$3,$I84,"") | L84: =IF($B84=L$3,$I84,"") | M84: P | S84: =IF($B84=S$3,$M84,"") -> P | T84: =IF($B84=T$3,$M84,"") | U84: =IF($B84=U$3,$M84,"")
B85: Critical | C85: TOOLS7 | D85: COMMON TOOLS: Delta Icon | E85: Ready | I85: P | J85: =IF($B85=J$3,$I85,"") -> P | K85: =IF($B85=K$3,$I85,"") | L85: =IF($B85=L$3,$I85,"") | M85: P | S85: =IF($B85=S$3,$M85,"") -> P | T85: =IF($B85=T$3,$M85,"") | U85: =IF($B85=U$3,$M85,"")
D86: Requirements
A87: FRM 4.2 | B87: Critical | C87: RQMT1 | D87: RQMT ADJUSTMENT: QM Requirement: Adjust Reqirements | E87: Ready | I87: P | J87: =IF($B87=J$3,$I87,"") -> P | K87: =IF($B87=K$3,$I87,"") | L87: =IF($B87=L$3,$I87,"") | M87: P | S87: =IF($B87=S$3,$M87,"") -> P | T87: =IF($B87=T$3,$M87,"") | U87: =IF($B87=U$3,$M87,"") | V87: Verbiage changes applied, outstanding question on PCN / Task Summary row
A88: FRM 4.2, FRM 4.4 | B88: Critical | C88: RQMT2 | D88: Mass Change RQMT | E88: Ready | I88: F | J88: =IF($B88=J$3,$I88,"") -> F | K88: =IF($B88=K$3,$I88,"") | L88: =IF($B88=L$3,$I88,"") | M88: F | S88: =IF($B88=S$3,$M88,"") -> F | T88: =IF($B88=T$3,$M88,"") | U88: =IF($B88=U$3,$M88,"") | V88: Performance concern
A89: FRM 4.19 | B89: Major | D89: Distribution
B90: Major | C90: DIST2 | D90: Input Distribution Amounts | E90: Ready | I90: Execution | J90: =IF($B90=J$3,$I90,"") | K90: =IF($B90=K$3,$I90,"") -> Execution | L90: =IF($B90=L$3,$I90,"") | M90: NT | S90: =IF($B90=S$3,$M90,"") | T90: =IF($B90=T$3,$M90,"") -> NT | U90: =IF($B90=U$3,$M90,"")
B91: Major | D91: Obligation
A92: FRM 4.18 | B92: Major | C92: OBL2 | D92: Input Obligation Amounts: 03D QM Obligation(new) | E92: Ready | I92: Execution | J92: =IF($B92=J$3,$I92,"") | K92: =IF($B92=K$3,$I92,"") -> Execution | L92: =IF($B92=L$3,$I92,"") | M92: NT | S92: =IF($B92=S$3,$M92,"") | T92: =IF($B92=T$3,$M92,"") -> NT | U92: =IF($B92=U$3,$M92,"")
A93: FRM 4.18, FRM 4.4 | B93: Major | C93: OBL3 | D93: Mass Change Field Value (Like Status from old value to New Value) | E93: Ready | I93: Execution | J93: =IF($B93=J$3,$I93,"") | K93: =IF($B93=K$3,$I93,"") -> Execution | L93: =IF($B93=L$3,$I93,"") | M93: NT | S93: =IF($B93=S$3,$M93,"") | T93: =IF($B93=T$3,$M93,"") -> NT | U93: =IF($B93=U$3,$M93,"")
A94: FRM 4.18, FRM 4.4 | B94: Major | C94: OBL4 | D94: Mass Change: Spread PBA to Projected | E94: Ready | I94: Execution | J94: =IF($B94=J$3,$I94,"") | K94: =IF($B94=K$3,$I94,"") -> Execution | L94: =IF($B94=L$3,$I94,"") | M94: NT | S94: =IF($B94=S$3,$M94,"") | T94: =IF($B94=T$3,$M94,"") -> NT | U94: =IF($B94=U$3,$M94,"")
A95: FRM 4.18, FRM 4.4 | B95: Major | C95: OBL5 | D95: Mass Change: Copy Obligation to Distribution | E95: Ready | I95: Execution | J95: =IF($B95=J$3,$I95,"") | K95: =IF($B95=K$3,$I95,"") -> Execution | L95: =IF($B95=L$3,$I95,"") | M95: NT | S95: =IF($B95=S$3,$M95,"") | T95: =IF($B95=T$3,$M95,"") -> NT | U95: =IF($B95=U$3,$M95,"")
A96: FRM 4.18, FRM 4.4 | B96: Major | C96: OBL6 | D96: Mass Change: Copy Distribution to Obligation | E96: Ready | I96: Execution | J96: =IF($B96=J$3,$I96,"") | K96: =IF($B96=K$3,$I96,"") -> Execution | L96: =IF($B96=L$3,$I96,"") | M96: NT | S96: =IF($B96=S$3,$M96,"") | T96: =IF($B96=T$3,$M96,"") -> NT | U96: =IF($B96=U$3,$M96,"")
A97: FRM 4.18, FRM 4.4 | B97: Major | C97: OBL7 | D97: Mass Change: Overlay Distribution to Funding | E97: Ready | I97: Execution | J97: =IF($B97=J$3,$I97,"") | K97: =IF($B97=K$3,$I97,"") -> Execution | L97: =IF($B97=L$3,$I97,"") | M97: NT | S97: =IF($B97=S$3,$M97,"") | T97: =IF($B97=T$3,$M97,"") -> NT | U97: =IF($B97=U$3,$M97,"")
A98: FRM 4.18, FRM 4.4 | B98: Major | C98: OBL8 | D98: Mass Change: Overlay Obligation to Funding | E98: Ready | I98: Execution | J98: =IF($B98=J$3,$I98,"") | K98: =IF($B98=K$3,$I98,"") -> Execution | L98: =IF($B98=L$3,$I98,"") | M98: NT | S98: =IF($B98=S$3,$M98,"") | T98: =IF($B98=T$3,$M98,"") -> NT | U98: =IF($B98=U$3,$M98,"")
K100: =COUNTIF(K4:K98,"NT") -> 1

Sheet TEMP
A1: RQMT # | B1: Priority | C1: CVT | D1: CVT Script Title | E1: Test Status | F1: IP-1 Pass Date | G1: IP-2 Pass Date | H1: IP-3 Pass Date | I1: CVT Status FYDP | M1: CVT Status (NT,A,P,F) | N1: DR # | V1: Comment | W1: CR #, if applicable
J2: Critical | K2: Major | L2: Minor | N2: 1 | O2: 2 | P2: 3 | Q2: 4 | R2: 5 | S2: Critical | T2: Major | U2: Minor
A3: FRM 4.3. FRM 4.27 | B3: Major | C3: NAV1 | D3: Select a Data Call | E3: Ready | I3: P | J3: =IF($B3=J$2,$I3,"") | K3: =IF($B3=K$2,$I3,"") -> P | L3: =IF($B3=L$2,$I3,"") | M3: P | S3: =IF($B3=S$2,$M3,"") | T3: =IF($B3=T$2,$M3,"") -> P | U3: =IF($B3=U$2,$M3,"")
A4: N/A | B4: Major | C4: NAV2 | D4: FRM Sections: (Navigate to Inputs, Data Sheet Views, Reports) | E4: Ready | I4: P | J4: =IF($B4=J$2,$I4,"") | K4: =IF($B4=K$2,$I4,"") -> P | L4: =IF($B4=L$2,$I4,"") | M4: P | S4: =IF($B4=S$2,$M4,"") | T4: =IF($B4=T$2,$M4,"") -> P | U4: =IF($B4=U$2,$M4,"") | V4: CVT Updates Applied
A5: FM 5.1-5.2 | B5: Major | C5: NAV3 | D5: Navigate to "Target Maintenance" | E5: Ready | I5: P | J5: =IF($B5=J$2,$I5,"") | K5: =IF($B5=K$2,$I5,"") -> P | L5: =IF($B5=L$2,$I5,"") | M5: P | S5: =IF($B5=S$2,$M5,"") | T5: =IF($B5=T$2,$M5,"") -> P | U5: =IF($B5=U$2,$M5,"") | V5: CVT Updates Applied
A6: FRM 6.1-6.2 | B6: Critical | C6: NAV4 | D6: Navigate to "QM Funds Spread" | E6: Ready | I6: P | J6: =IF($B6=J$2,$I6,"") -> P | K6: =IF($B6=K$2,$I6,"") | L6: =IF($B6=L$2,$I6,"") | M6: P | N6: X | R6: X | S6: =IF($B6=S$2,$M6,"") -> P | T6: =IF($B6=T$2,$M6,"") | U6: =IF($B6=U$2,$M6,"") | V6: CVT Updates Applied
A7: FRM 7.1 | B7: Critical | C7: NAV5 | D7: RQMT ADJUSTMENT: QM (Quick Maintenance) Requirement: Access Grid | E7: Ready | I7: P | J7: =IF($B7=J$2,$I7,"") -> P | K7: =IF($B7=K$2,$I7,"") | L7: =IF($B7=L$2,$I7,"") | M7: P | N7: X | S7: =IF($B7=S$2,$M7,"") -> P | T7: =IF($B7=T$2,$M7,"") | U7: =IF($B7=U$2,$M7,"")
A8: - | B8: Critical | C8: UM1 | D8: FRM Basics: Register for FRM | E8: Ready | I8: N/A | J8: =IF($B8=J$2,$I8,"") -> N/A | K8: =IF($B8=K$2,$I8,"") | L8: =IF($B8=L$2,$I8,"") | M8: N/A | S8: =IF($B8=S$2,$M8,"") -> N/A | T8: =IF($B8=T$2,$M8,"") | U8: =IF($B8=U$2,$M8,"") | V8: Recommend removing from this test agenda
A9: FRM 1.1 - 1.5 | B9: Critical | C9: UM2 | D9: Activate User (Generic) | E9: Ready | I9: P | J9: =IF($B9=J$2,$I9,"") -> P | K9: =IF($B9=K$2,$I9,"") | L9: =IF($B9=L$2,$I9,"") | M9: P | S9: =IF($B9=S$2,$M9,"") -> P | T9: =IF($B9=T$2,$M9,"") | U9: =IF($B9=U$2,$M9,"")
A10: FRM 1.1 - 1.5 | B10: Critical | C10: UM3 | D10: Confirm Activated User | E10: Ready | I10: P | J10: =IF($B10=J$2,$I10,"") -> P | K10: =IF($B10=K$2,$I10,"") | L10: =IF($B10=L$2,$I10,"") | M10: P | S10: =IF($B10=S$2,$M10,"") -> P | T10: =IF($B10=T$2,$M10,"") | U10: =IF($B10=U$2,$M10,"")
A11: FRM 1.1 - 1.5 | B11: Critical | C11: UM4 | D11: Confirm Filter | E11: Ready | I11: R | J11: =IF($B11=J$2,$I11,"") -> R | K11: =IF($B11=K$2,$I11,"") | L11: =IF($B11=L$2,$I11,"") | M11: R | S11: =IF($B11=S$2,$M11,"") -> R | T11: =IF($B11=T$2,$M11,"") | U11: =IF($B11=U$2,$M11,"") | V11: Change to be made to add PEC
A12: FRM 1.1 - 1.5 | B12: Major | C12: UM5 | D12: Confirm User Management Roles | E12: Ready | I12: P | J12: =IF($B12=J$2,$I12,"") | K12: =IF($B12=K$2,$I12,"") -> P | L12: =IF($B12=L$2,$I12,"") | M12: P | S12: =IF($B12=S$2,$M12,"") | T12: =IF($B12=T$2,$M12,"") -> P | U12: =IF($B12=U$2,$M12,"")
A13: 4.8, 1.1, 1.2 | B13: Critical | C13: DCROLE1 | D13: Manage Roles and Responsibility | E13: Ready | I13: P | J13: =IF($B13=J$2,$I13,"") -> P | K13: =IF($B13=K$2,$I13,"") | L13: =IF($B13=L$2,$I13,"") | M13: P | S13: =IF($B13=S$2,$M13,"") -> P | T13: =IF($B13=T$2,$M13,"") | U13: =IF($B13=U$2,$M13,"")
A14: 4.8 | B14: Major | C14: DCROLE2 | D14: Review Roles and Responsibilities by Users | E14: Ready | I14: P | J14: =IF($B14=J$2,$I14,"") | K14: =IF($B14=K$2,$I14,"") -> P | L14: =IF($B14=L$2,$I14,"") | M14: P | S14: =IF($B14=S$2,$M14,"") | T14: =IF($B14=T$2,$M14,"") -> P | U14: =IF($B14=U$2,$M14,"")
A15: 4.8, 4.12 | B15: Major | C15: DCROLE3 | D15: Review Roles and Responsibilities by Affiliation | E15: Ready | I15: P | J15: =IF($B15=J$2,$I15,"") | K15: =IF($B15=K$2,$I15,"") -> P | L15: =IF($B15=L$2,$I15,"") | M15: P | S15: =IF($B15=S$2,$M15,"") | T15: =IF($B15=T$2,$M15,"") -> P | U15: =IF($B15=U$2,$M15,"")
A16: 2.3 | B16: Critical | C16: DCROLE4 | D16: Search for User | E16: Ready | I16: P | J16: =IF($B16=J$2,$I16,"") -> P | K16: =IF($B16=K$2,$I16,"") | L16: =IF($B16=L$2,$I16,"") | M16: P | S16: =IF($B16=S$2,$M16,"") -> P | T16: =IF($B16=T$2,$M16,"") | U16: =IF($B16=U$2,$M16,"")
A17: 4.4, 4.8 | B17: Major | C17: DCROLE5 | D17: Mass Change User Roles - Add Roles | E17: Ready | I17: P | J17: =IF($B17=J$2,$I17,"") | K17: =IF($B17=K$2,$I17,"") -> P | L17: =IF($B17=L$2,$I17,"") | M17: P | S17: =IF($B17=S$2,$M17,"") | T17: =IF($B17=T$2,$M17,"") -> P | U17: =IF($B17=U$2,$M17,"")
A18: 4.4, 4.8 | B18: Major | C18: DCROLE6 | D18: Mass Change User Roles - Remove Roles | E18: Ready | I18: P | J18: =IF($B18=J$2,$I18,"") | K18: =IF($B18=K$2,$I18,"") -> P | L18: =IF($B18=L$2,$I18,"") | M18: P | S18: =IF($B18=S$2,$M18,"") | T18: =IF($B18=T$2,$M18,"") -> P | U18: =IF($B18=U$2,$M18,"")
A19: 4.9, 4.10 | B19: Critical | C19: DC1 | D19: Create Execution Data Call | E19: unpredictable results | I19: Data call | J19: =IF($B19=J$2,$I19,"") -> Data call | K19: =IF($B19=K$2,$I19,"") | L19: =IF($B19=L$2,$I19,"") | M19: NT | S19: =IF($B19=S$2,$M19,"") -> NT | T19: =IF($B19=T$2,$M19,"") | U19: =IF($B19=U$2,$M19,"")
A20: 4.9, 4.10 | B20: Critical | C20: DC2 | D20: Create FYDP FRM Data Call | E20: unpredictable results | I20: Data call | J20: =IF($B20=J$2,$I20,"") -> Data call | K20: =IF($B20=K$2,$I20,"") | L20: =IF($B20=L$2,$I20,"") | M20: NT | S20: =IF($B20=S$2,$M20,"") -> NT | T20: =IF($B20=T$2,$M20,"") | U20: =IF($B20=U$2,$M20,"")
A21: FRM 4.12, 4.15-4.17 | B21: Critical | C21: DC3 | D21: Review Data Call Options | E21: Ready | I21: R | J21: =IF($B21=J$2,$I21,"") -> R | K21: =IF($B21=K$2,$I21,"") | L21: =IF($B21=L$2,$I21,"") | M21: R | S21: =IF($B21=S$2,$M21,"") -> R | T21: =IF($B21=T$2,$M21,"") | U21: =IF($B21=U$2,$M21,"") | V21: CVT updates applied
A22: FRM 4.11 | B22: Critical | C22: DC4 | D22: Add Years to Data Call | E22: Ready | I22: Data call | J22: =IF($B22=J$2,$I22,"") -> Data call | K22: =IF($B22=K$2,$I22,"") | L22: =IF($B22=L$2,$I22,"") | M22: NT | S22: =IF($B22=S$2,$M22,"") -> NT | T22: =IF($B22=T$2,$M22,"") | U22: =IF($B22=U$2,$M22,"")
A23: FRM 7.6, 4.2 | B23: Critical | C23: DC5 | D23: Audit Requirement | E23: Ready | I23: Data call | J23: =IF($B23=J$2,$I23,"") -> Data call | K23: =IF($B23=K$2,$I23,"") | L23: =IF($B23=L$2,$I23,"") | M23: NT | S23: =IF($B23=S$2,$M23,"") -> NT | T23: =IF($B23=T$2,$M23,"") | U23: =IF($B23=U$2,$M23,"")
A24: FRM 5.6 | B24: Major | C24: DC6 | D24: Audit Target | E24: Ready | I24: Data call | J24: =IF($B24=J$2,$I24,"") | K24: =IF($B24=K$2,$I24,"") -> Data call | L24: =IF($B24=L$2,$I24,"") | M24: NT | S24: =IF($B24=S$2,$M24,"") | T24: =IF($B24=T$2,$M24,"") -> NT | U24: =IF($B24=U$2,$M24,"")
A25: FRM 6.8, FRM 6.9 | B25: Major | C25: DC7 | D25: Audit Funds Spread | E25: Ready | I25: Data call | J25: =IF($B25=J$2,$I25,"") | K25: =IF($B25=K$2,$I25,"") -> Data call | L25: =IF($B25=L$2,$I25,"") | M25: NT | S25: =IF($B25=S$2,$M25,"") | T25: =IF($B25=T$2,$M25,"") -> NT | U25: =IF($B25=U$2,$M25,"")
A26: Missing | B26: Minor | C26: DC8 | D26: Delete Data Call | E26: Ready | I26: Data call | J26: =IF($B26=J$2,$I26,"") | K26: =IF($B26=K$2,$I26,"") | L26: =IF($B26=L$2,$I26,"") -> Data call | M26: NT | S26: =IF($B26=S$2,$M26,"") | T26: =IF($B26=T$2,$M26,"") | U26: =IF($B26=U$2,$M26,"") -> NT
A27: 4.8,4.4 | B27: Major | C27: DC9 | D27: Certify Data Call Ready for File Maintenance | E27: Ready | I27: Data call | J27: =IF($B27=J$2,$I27,"") | K27: =IF($B27=K$2,$I27,"") -> Data call | L27: =IF($B27=L$2,$I27,"") | M27: NT | S27: =IF($B27=S$2,$M27,"") | T27: =IF($B27=T$2,$M27,"") -> NT | U27: =IF($B27=U$2,$M27,"")
A28: 4.4, 5.12, 6.11 | B28: Critical | C28: DC10 | D28: Close Data Call | E28: Ready | I28: Data call | J28: =IF($B28=J$2,$I28,"") -> Data call | K28: =IF($B28=K$2,$I28,"") | L28: =IF($B28=L$2,$I28,"") | M28: NT | S28: =IF($B28=S$2,$M28,"") -> NT | T28: =IF($B28=T$2,$M28,"") | U28: =IF($B28=U$2,$M28,"")
A29: FRM 4.4, 4.13, 6.3 | B29: Major | C29: MassDC1 | D29: Overlay DC Funding | E29: DUPLICATE | I29: DUP | J29: =IF($B29=J$2,$I29,"") | K29: =IF($B29=K$2,$I29,"") -> DUP | L29: =IF($B29=L$2,$I29,"") | M29: DUP | S29: =IF($B29=S$2,$M29,"") | T29: =IF($B29=T$2,$M29,"") -> DUP | U29: =IF($B29=U$2,$M29,"") | V29: =+"Refer to FS9, Status: "& M56 -> Refer to FS9, Status: P
A30: FRM 4.4, 4.13 | B30: Major | C30: MassDC2 | D30: Mass Change: Update Status | E30: Ready | I30: NA | J30: =IF($B30=J$2,$I30,"") | K30: =IF($B30=K$2,$I30,"") -> NA | L30: =IF($B30=L$2,$I30,"") | M30: NA | S30: =IF($B30=S$2,$M30,"") | T30: =IF($B30=T$2,$M30,"") -> NA | U30: =IF($B30=U$2,$M30,"")
A31: FRM 4.4, 4.13, 6.3 | B31: Major | C31: MassDC3 | D31: Mass Change: 70% Spread to Target by Priority | E31: DUPLICATE | I31: DUP | J31: =IF($B31=J$2,$I31,"") | K31: =IF($B31=K$2,$I31,"") -> DUP | L31: =IF($B31=L$2,$I31,"") | M31: DUP | S31: =IF($B31=S$2,$M31,"") | T31: =IF($B31=T$2,$M31,"") -> DUP | U31: =IF($B31=U$2,$M31,"") | V31: =+"Refer to FS3, Status: "& +M50 -> Refer to FS3, Status: R
A32: FRM 4.4, 4.13, 6.3 | B32: Critical | C32: MassDC4 | D32: Mass Change: Fully Fund to Target | E32: DUPLICATE | I32: DUP | J32: =IF($B32=J$2,$I32,"") -> DUP | K32: =IF($B32=K$2,$I32,"") | L32: =IF($B32=L$2,$I32,"") | M32: DUP | S32: =IF($B32=S$2,$M32,"") -> DUP | T32: =IF($B32=T$2,$M32,"") | U32: =IF($B32=U$2,$M32,"") | V32: =+"Refer to FS4, Status: "& +M51 -> Refer to FS4, Status: P
A33: FRM 4.4, 4.13, 6.3 | B33: Major | C33: MassDC5 | D33: Mass Change: OP30 Spread; next 70% Spread to Target by Priority | E33: DUPLICATE | I33: DUP | J33: =IF($B33=J$2,$I33,"") | K33: =IF($B33=K$2,$I33,"") -> DUP | L33: =IF($B33=L$2,$I33,"") | M33: DUP | S33: =IF($B33=S$2,$M33,"") | T33: =IF($B33=T$2,$M33,"") -> DUP | U33: =IF($B33=U$2,$M33,"") | V33: =+"Refer to FS5, Status: "& +M52 -> Refer to FS5, Status: R
A34: FRM 4.4, 4.13, 6.3 | B34: Major | C34: MassDC6 | D34: Mass Change: Fully Fund | E34: DUPLICATE | I34: DUP | J34: =IF($B34=J$2,$I34,"") | K34: =IF($B34=K$2,$I34,"") -> DUP | L34: =IF($B34=L$2,$I34,"") | M34: DUP | S34: =IF($B34=S$2,$M34,"") | T34: =IF($B34=T$2,$M34,"") -> DUP | U34: =IF($B34=U$2,$M34,"") | V34: =+"Refer to FS6, Status: "& +M53 -> Refer to FS6, Status: R
A35: FRM 4.4, 4.13, 6.3 | B35: Major | C35: MassDC7 | D35: Mass Change: Unfund | E35: DUPLICATE | I35: DUP | J35: =IF($B35=J$2,$I35,"") | K35: =IF($B35=K$2,$I35,"") -> DUP | L35: =IF($B35=L$2,$I35,"") | M35: DUP | S35: =IF($B35=S$2,$M35,"") | T35: =IF($B35=T$2,$M35,"") -> DUP | U35: =IF($B35=U$2,$M35,"") | V35: =+"Refer to FS7, Status: "& +M54 -> Refer to FS7, Status: P
A36: FRM 4.4, 4.13,5.2 | B36: Major | C36: MassDC8 | D36: Overlay Target | E36: DUPLICATE | I36: DUP | J36: =IF($B36=J$2,$I36,"") | K36: =IF($B36=K$2,$I36,"") -> DUP | L36: =IF($B36=L$2,$I36,"") | M36: DUP | S36: =IF($B36=S$2,$M36,"") | T36: =IF($B36=T$2,$M36,"") -> DUP | U36: =IF($B36=U$2,$M36,"")
A37: FRM 4.4, 4.13,5.2 | B37: Major | C37: MassDC9 | D37: Copy Target to Target | E37: DUPLICATE | I37: DUP | J37: =IF($B37=J$2,$I37,"") | K37: =IF($B37=K$2,$I37,"") -> DUP | L37: =IF($B37=L$2,$I37,"") | M37: DUP | S37: =IF($B37=S$2,$M37,"") | T37: =IF($B37=T$2,$M37,"") -> DUP | U37: =IF($B37=U$2,$M37,"") | V37: Refer to TGT2, Status:
A38: FRM 4.4, 4.13,5.2 | B38: Major | C38: MassDC10 | D38: Get (Append) Target | E38: DUPLICATE | I38: DUP | J38: =IF($B38=J$2,$I38,"") | K38: =IF($B38=K$2,$I38,"") -> DUP | L38: =IF($B38=L$2,$I38,"") | M38: DUP | S38: =IF($B38=S$2,$M38,"") | T38: =IF($B38=T$2,$M38,"") -> DUP | U38: =IF($B38=U$2,$M38,"")
A39: 5.2, 5.13, 4.4 | B39: Major | C39: TGT2 | D39: DATA MAINTENANCE: Mass Change: Copy Target to Target | E39: Ready | I39: P | J39: =IF($B39=J$2,$I39,"") | K39: =IF($B39=K$2,$I39,"") -> P | L39: =IF($B39=L$2,$I39,"") | M39: P | S39: =IF($B39=S$2,$M39,"") | T39: =IF($B39=T$2,$M39,"") -> P | U39: =IF($B39=U$2,$M39,"")
A40: 5.2, 5.13, 4.4 | B40: Major | C40: TGT3 | D40: Target Maintenance: Mass Change: Zero out all Targets | E40: Ready | I40: P | J40: =IF($B40=J$2,$I40,"") | K40: =IF($B40=K$2,$I40,"") -> P | L40: =IF($B40=L$2,$I40,"") | M40: P | S40: =IF($B40=S$2,$M40,"") | T40: =IF($B40=T$2,$M40,"") -> P | U40: =IF($B40=U$2,$M40,"")
A41: 5.2, 5.13, 4.4 | B41: Major | C41: TGT4 | D41: Target Maintenance: Mass Change: Reset Target to Reference (Baseline) | E41: Ready | I41: P | J41: =IF($B41=J$2,$I41,"") | K41: =IF($B41=K$2,$I41,"") -> P | L41: =IF($B41=L$2,$I41,"") | M41: P | S41: =IF($B41=S$2,$M41,"") | T41: =IF($B41=T$2,$M41,"") -> P | U41: =IF($B41=U$2,$M41,"")
A42: 5.2, 5.13, 4.4 | B42: Major | C42: TGT5 | D42: Target Maintenance: Balance Target Amounts | E42: Ready | I42: A | J42: =IF($B42=J$2,$I42,"") | K42: =IF($B42=K$2,$I42,"") -> A | L42: =IF($B42=L$2,$I42,"") | M42: A | S42: =IF($B42=S$2,$M42,"") | T42: =IF($B42=T$2,$M42,"") -> A | U42: =IF($B42=U$2,$M42,"")
A43: FRM 4.4 | B43: Major | C43: TGT6 | D43: DATA MAINTENANCE: Mass Change: Update Status | E43: Ready | I43: HOLD | J43: =IF($B43=J$2,$I43,"") | K43: =IF($B43=K$2,$I43,"") -> HOLD | L43: =IF($B43=L$2,$I43,"") | M43: HOLD | S43: =IF($B43=S$2,$M43,"") | T43: =IF($B43=T$2,$M43,"") -> HOLD | U43: =IF($B43=U$2,$M43,"")
A44: 5.2 | B44: Critical | C44: TGT7 | D44: Maintain Target Amounts (Quick Maintenance) | E44: Ready | I44: P | J44: =IF($B44=J$2,$I44,"") -> P | K44: =IF($B44=K$2,$I44,"") | L44: =IF($B44=L$2,$I44,"") | M44: P | S44: =IF($B44=S$2,$M44,"") -> P | T44: =IF($B44=T$2,$M44,"") | U44: =IF($B44=U$2,$M44,"")
A45: 4.4, 5.10 | B45: Critical | C45: TGT8 | D45: Target Maintenance: Mass change: Copy Budget Reference to Budget Reference. | E45: Ready | I45: P | J45: =IF($B45=J$2,$I45,"") -> P | K45: =IF($B45=K$2,$I45,"") | L45: =IF($B45=L$2,$I45,"") | M45: P | S45: =IF($B45=S$2,$M45,"") -> P | T45: =IF($B45=T$2,$M45,"") | U45: =IF($B45=U$2,$M45,"")
A46: 4.4, 5.10 | B46: Critical | C46: TGT9 | D46: Target Maintenance: Mass change: Overlay Reference to Target | E46: Ready | I46: P | J46: =IF($B46=J$2,$I46,"") -> P | K46: =IF($B46=K$2,$I46,"") | L46: =IF($B46=L$2,$I46,"") | M46: P | S46: =IF($B46=S$2,$M46,"") -> P | T46: =IF($B46=T$2,$M46,"") | U46: =IF($B46=U$2,$M46,"")
A47: 4.4, 5.10 | B47: Critical | C47: TGT10 | D47: Target Maintenance: Mass change: Show Budget Reference w/o RQMT | E47: Ready | I47: R | J47: =IF($B47=J$2,$I47,"") -> R | K47: =IF($B47=K$2,$I47,"") | L47: =IF($B47=L$2,$I47,"") | M47: R | S47: =IF($B47=S$2,$M47,"") -> R | T47: =IF($B47=T$2,$M47,"") | U47: =IF($B47=U$2,$M47,"")
B48: Major | C48: TGT11 | D48: Target Maintenance: Overlay Target | E48: Ready | I48: NT | J48: =IF($B48=J$2,$I48,"") | K48: =IF($B48=K$2,$I48,"") -> NT | L48: =IF($B48=L$2,$I48,"") | M48: NT | S48: =IF($B48=S$2,$M48,"") | T48: =IF($B48=T$2,$M48,"") -> NT | U48: =IF($B48=U$2,$M48,"") | V48: NEWLY ADDED, 11/17
B49: Major | C49: TGT12 | D49: Target Maintenance: Get (Append) Target | E49: Ready | I49: R | J49: =IF($B49=J$2,$I49,"") | K49: =IF($B49=K$2,$I49,"") -> R | L49: =IF($B49=L$2,$I49,"") | M49: R | S49: =IF($B49=S$2,$M49,"") | T49: =IF($B49=T$2,$M49,"") -> R | U49: =IF($B49=U$2,$M49,"") | V49: NEWLY ADDED, 11/17
A50: FRM 6.1 - 6.13 | B50: Critical | C50: FS3 | D50: Mass Change: 70% Spread to Target by Priority | E50: Ready | I50: R | J50: =IF($B50=J$2,$I50,"") -> R | K50: =IF($B50=K$2,$I50,"") | L50: =IF($B50=L$2,$I50,"") | M50: R | S50: =IF($B50=S$2,$M50,"") -> R | T50: =IF($B50=T$2,$M50,"") | U50: =IF($B50=U$2,$M50,"") | V50: Not 70%
A51: FRM 6.1 - 6.13 | B51: Critical | C51: FS4 | D51: Mass Change: Fully Fund to Target | E51: Ready | I51: P | J51: =IF($B51=J$2,$I51,"") -> P | K51: =IF($B51=K$2,$I51,"") | L51: =IF($B51=L$2,$I51,"") | M51: P | S51: =IF($B51=S$2,$M51,"") -> P | T51: =IF($B51=T$2,$M51,"") | U51: =IF($B51=U$2,$M51,"")
A52: FRM 6.1 - 6.13 | B52: Critical | C52: FS5 | D52: Mass Change: OP30 Spread by Priority; Next Spread to Remaining PCNs/Task by Priority | E52: Ready | I52: R | J52: =IF($B52=J$2,$I52,"") -> R | K52: =IF($B52=K$2,$I52,"") | L52: =IF($B52=L$2,$I52,"") | M52: R | S52: =IF($B52=S$2,$M52,"") -> R | T52: =IF($B52=T$2,$M52,"") | U52: =IF($B52=U$2,$M52,"") | V52: #2 priority is not being funded
A53: FRM 6.1 - 6.13 | B53: Critical | C53: FS6 | D53: Mass Change: Fully Fund | E53: Ready | I53: R | J53: =IF($B53=J$2,$I53,"") -> R | K53: =IF($B53=K$2,$I53,"") | L53: =IF($B53=L$2,$I53,"") | M53: R | S53: =IF($B53=S$2,$M53,"") -> R | T53: =IF($B53=T$2,$M53,"") | U53: =IF($B53=U$2,$M53,"") | V53: Verbiage added to advise users to review results for rounding errors
A54: FRM 6.1 - 6.13 | B54: Critical | C54: FS7 | D54: Mass Change: Unfund | E54: Ready | I54: P | J54: =IF($B54=J$2,$I54,"") -> P | K54: =IF($B54=K$2,$I54,"") | L54: =IF($B54=L$2,$I54,"") | M54: P | S54: =IF($B54=S$2,$M54,"") -> P | T54: =IF($B54=T$2,$M54,"") | U54: =IF($B54=U$2,$M54,"")
A55: FRM 6.1 - 6.13 | B55: Critical | C55: FS8 | D55: Straight Line Requirement | E55: Ready | I55: A | J55: =IF($B55=J$2,$I55,"") -> A | K55: =IF($B55=K$2,$I55,"") | L55: =IF($B55=L$2,$I55,"") | M55: A | S55: =IF($B55=S$2,$M55,"") -> A | T55: =IF($B55=T$2,$M55,"") | U55: =IF($B55=U$2,$M55,"") | V55: Need to add note that this is for new RQMT only
A56: FRM 6.1 - 6.13 | B56: Critical | C56: FS9 | D56: Overlay DC Funding | E56: Ready | I56: P | J56: =IF($B56=J$2,$I56,"") -> P | K56: =IF($B56=K$2,$I56,"") | L56: =IF($B56=L$2,$I56,"") | M56: P | S56: =IF($B56=S$2,$M56,"") -> P | T56: =IF($B56=T$2,$M56,"") | U56: =IF($B56=U$2,$M56,"")
A57: FRM 6.1 - 6.13 | B57: Critical | C57: FS10 | D57: FUNDS SPREADS: Update Individual Funds Spreads | E57: Ready | I57: R | J57: =IF($B57=J$2,$I57,"") -> R | K57: =IF($B57=K$2,$I57,"") | L57: =IF($B57=L$2,$I57,"") | M57: R | S57: =IF($B57=S$2,$M57,"") -> R | T57: =IF($B57=T$2,$M57,"") | U57: =IF($B57=U$2,$M57,"") | V57: Program group HH60/FY11/ Qty field is not working. PCN AAJRTR
A58: FRM 4.23, 4.25, 6.4, 6.24 | B58: Critical | C58: RPT1 | D58: DATASHEET VIEW: 02* Custom | E58: Ready | I58: A | J58: =IF($B58=J$2,$I58,"") -> A | K58: =IF($B58=K$2,$I58,"") | L58: =IF($B58=L$2,$I58,"") | M58: A | S58: =IF($B58=S$2,$M58,"") -> A | T58: =IF($B58=T$2,$M58,"") | U58: =IF($B58=U$2,$M58,"") | V58: email option not working
A59: FRM 3.6 | B59: Critical | C59: RPT2 | D59: DATASHEET VIEW: Analysis: Check Data Positions ( $ Summary Grid:) | E59: Ready | I59: R | J59: =IF($B59=J$2,$I59,"") -> R | K59: =IF($B59=K$2,$I59,"") | L59: =IF($B59=L$2,$I59,"") | M59: R | S59: =IF($B59=S$2,$M59,"") -> R | T59: =IF($B59=T$2,$M59,"") | U59: =IF($B59=U$2,$M59,"") | V59: Changes ready for review
A60: FRM 6.4, 6.24 | B60: Major | C60: RPT3 | D60: DATASHEET VIEW: Compare: Compare Requirement from Past Exercises (Growth Analysis - Chart icon)) | E60: Do Not Test | I60: REM | J60: =IF($B60=J$2,$I60,"") | K60: =IF($B60=K$2,$I60,"") -> REM | L60: =IF($B60=L$2,$I60,"") | M60: REM | S60: =IF($B60=S$2,$M60,"") | T60: =IF($B60=T$2,$M60,"") -> REM | U60: =IF($B60=U$2,$M60,"")
A61: FRM 5.1 | B61: Major | C61: RPT4 | D61: DATASHEET VIEW: 02A-Target Audit | E61: Ready | I61: R | J61: =IF($B61=J$2,$I61,"") | K61: =IF($B61=K$2,$I61,"") -> R | L61: =IF($B61=L$2,$I61,"") | M61: R | S61: =IF($B61=S$2,$M61,"") | T61: =IF($B61=T$2,$M61,"") -> R | U61: =IF($B61=U$2,$M61,"") | V61: Updates to ZBT
A62: FRM 3.2-3.5 | B62: Major | C62: RPT5 | D62: DATASHEET VIEW: Workload Summary, view progress of a data call | E62: Do Not Test | I62: R | J62: =IF($B62=J$2,$I62,"") | K62: =IF($B62=K$2,$I62,"") -> R | L62: =IF($B62=L$2,$I62,"") | M62: R | S62: =IF($B62=S$2,$M62,"") | T62: =IF($B62=T$2,$M62,"") -> R | U62: =IF($B62=U$2,$M62,"") | V62: No Scrolling
A63: FRM 4.23, 4.25 | B63: Major | C63: RPT6 | D63: FYDP Tool: 02E - Compare Datasheet | E63: Ready | I63: R | J63: =IF($B63=J$2,$I63,"") | K63: =IF($B63=K$2,$I63,"") -> R | L63: =IF($B63=L$2,$I63,"") | M63: R | S63: =IF($B63=S$2,$M63,"") | T63: =IF($B63=T$2,$M63,"") -> R | U63: =IF($B63=U$2,$M63,"") | V63: Report timed out
A64: FRM 3.6 | B64: Major | C64: RPT7 | D64: FYDP Tool: 02F - Trended Datasheet | E64: Ready | I64: P | J64: =IF($B64=J$2,$I64,"") | K64: =IF($B64=K$2,$I64,"") -> P | L64: =IF($B64=L$2,$I64,"") | M64: P | S64: =IF($B64=S$2,$M64,"") | T64: =IF($B64=T$2,$M64,"") -> P | U64: =IF($B64=U$2,$M64,"")
A65: FRM 4.23, 4.25, 6.4 | B65: Critical | C65: RPT8 | D65: FYDP Tool: 02C - SAF FM Datasheet | E65: Ready | I65: P | J65: =IF($B65=J$2,$I65,"") -> P | K65: =IF($B65=K$2,$I65,"") | L65: =IF($B65=L$2,$I65,"") | M65: P | S65: =IF($B65=S$2,$M65,"") -> P | T65: =IF($B65=T$2,$M65,"") | U65: =IF($B65=U$2,$M65,"")
A66: FRM 7.4 | B66: Major | C66: RPT9 | D66: DATASHEET VIEW: 02G Factors | E66: Ready | I66: P | J66: =IF($B66=J$2,$I66,"") | K66: =IF($B66=K$2,$I66,"") -> P | L66: =IF($B66=L$2,$I66,"") | M66: P | S66: =IF($B66=S$2,$M66,"") | T66: =IF($B66=T$2,$M66,"") -> P | U66: =IF($B66=U$2,$M66,"")
A67: FRM 4.18 | B67: Major | C67: RPT10 | D67: Execution Section: 01A Report FRM Distribution | E67: Ready | I67: EXEC | J67: =IF($B67=J$2,$I67,"") | K67: =IF($B67=K$2,$I67,"") -> EXEC | L67: =IF($B67=L$2,$I67,"") | M67: NT | S67: =IF($B67=S$2,$M67,"") | T67: =IF($B67=T$2,$M67,"") -> NT | U67: =IF($B67=U$2,$M67,"")
A68: FRM 4.19 | B68: Major | C68: RPT11 | D68: Execution Section: 01B Report FRM Obligation | E68: Ready | I68: EXEC | J68: =IF($B68=J$2,$I68,"") | K68: =IF($B68=K$2,$I68,"") -> EXEC | L68: =IF($B68=L$2,$I68,"") | M68: NT | S68: =IF($B68=S$2,$M68,"") | T68: =IF($B68=T$2,$M68,"") -> NT | U68: =IF($B68=U$2,$M68,"")
A69: FRM 2.3 | B69: Major | C69: TOOLS1 | D69: Find a PCN | E69: Ready | I69: P | J69: =IF($B69=J$2,$I69,"") | K69: =IF($B69=K$2,$I69,"") -> P | L69: =IF($B69=L$2,$I69,"") | M69: P | S69: =IF($B69=S$2,$M69,"") | T69: =IF($B69=T$2,$M69,"") -> P | U69: =IF($B69=U$2,$M69,"")
A70: FRM 2.4 | B70: Major | C70: TOOLS2 | D70: Find a Task | E70: Ready | I70: P | J70: =IF($B70=J$2,$I70,"") | K70: =IF($B70=K$2,$I70,"") -> P | L70: =IF($B70=L$2,$I70,"") | M70: P | S70: =IF($B70=S$2,$M70,"") | T70: =IF($B70=T$2,$M70,"") -> P | U70: =IF($B70=U$2,$M70,"")
A71: FRM 2.1, 2.2, 2.5 | B71: Major | C71: TOOLS3 | D71: Applied Filter: Limit Data | E71: Ready | I71: P | J71: =IF($B71=J$2,$I71,"") | K71: =IF($B71=K$2,$I71,"") -> P | L71: =IF($B71=L$2,$I71,"") | M71: P | S71: =IF($B71=S$2,$M71,"") | T71: =IF($B71=T$2,$M71,"") -> P | U71: =IF($B71=U$2,$M71,"")
B72: Minor | C72: TOOLS4 | D72: Sort Grid Data | E72: Ready | I72: P | J72: =IF($B72=J$2,$I72,"") | K72: =IF($B72=K$2,$I72,"") | L72: =IF($B72=L$2,$I72,"") -> P | M72: P | S72: =IF($B72=S$2,$M72,"") | T72: =IF($B72=T$2,$M72,"") | U72: =IF($B72=U$2,$M72,"") -> P
A73: FRM 4.1 | B73: Critical | C73: TOOLS 5 | D73: DATA MAINTENANCE: Add New PCN/Task | E73: Ready | I73: P | J73: =IF($B73=J$2,$I73,"") -> P | K73: =IF($B73=K$2,$I73,"") | L73: =IF($B73=L$2,$I73,"") | M73: P | S73: =IF($B73=S$2,$M73,"") -> P | T73: =IF($B73=T$2,$M73,"") | U73: =IF($B73=U$2,$M73,"")
A74: FRM 4.1 | B74: Critical | C74: TOOLS6 | D74: DATA MAINTENANCE: Edit PCN Attributes | E74: Ready | I74: P | J74: =IF($B74=J$2,$I74,"") -> P | K74: =IF($B74=K$2,$I74,"") | L74: =IF($B74=L$2,$I74,"") | M74: P | S74: =IF($B74=S$2,$M74,"") -> P | T74: =IF($B74=T$2,$M74,"") | U74: =IF($B74=U$2,$M74,"")
B75: Critical | C75: TOOLS7 | D75: COMMON TOOLS: Delta Icon | E75: Ready | I75: P | J75: =IF($B75=J$2,$I75,"") -> P | K75: =IF($B75=K$2,$I75,"") | L75: =IF($B75=L$2,$I75,"") | M75: P | S75: =IF($B75=S$2,$M75,"") -> P | T75: =IF($B75=T$2,$M75,"") | U75: =IF($B75=U$2,$M75,"")
A76: FRM 4.2 | B76: Critical | C76: RQMT1 | D76: RQMT ADJUSTMENT: QM Requirement: Adjust Reqirements | E76: Ready | I76: P | J76: =IF($B76=J$2,$I76,"") -> P | K76: =IF($B76=K$2,$I76,"") | L76: =IF($B76=L$2,$I76,"") | M76: P | S76: =IF($B76=S$2,$M76,"") -> P | T76: =IF($B76=T$2,$M76,"") | U76: =IF($B76=U$2,$M76,"") | V76: Verbiage changes applied, outstanding question on PCN / Task Summary row
A77: FRM 4.2, FRM 4.4 | B77: Critical | C77: RQMT2 | D77: Mass Change RQMT | E77: Ready | I77: F | J77: =IF($B77=J$2,$I77,"") -> F | K77: =IF($B77=K$2,$I77,"") | L77: =IF($B77=L$2,$I77,"") | M77: F | S77: =IF($B77=S$2,$M77,"") -> F | T77: =IF($B77=T$2,$M77,"") | U77: =IF($B77=U$2,$M77,"") | V77: Performance concern
B78: Major | C78: DIST2 | D78: Input Distribution Amounts | E78: Ready | I78: EXEC | J78: =IF($B78=J$2,$I78,"") | K78: =IF($B78=K$2,$I78,"") -> EXEC | L78: =IF($B78=L$2,$I78,"") | M78: NT | S78: =IF($B78=S$2,$M78,"") | T78: =IF($B78=T$2,$M78,"") -> NT | U78: =IF($B78=U$2,$M78,"")
A79: FRM 4.18 | B79: Major | C79: OBL2 | D79: Input Obligation Amounts: 03D QM Obligation(new) | E79: Do Not Test | I79: EXEC | J79: =IF($B79=J$2,$I79,"") | K79: =IF($B79=K$2,$I79,"") -> EXEC | L79: =IF($B79=L$2,$I79,"") | M79: NT | S79: =IF($B79=S$2,$M79,"") | T79: =IF($B79=T$2,$M79,"") -> NT | U79: =IF($B79=U$2,$M79,"")
A80: FRM 4.18, FRM 4.4 | B80: Major | C80: OBL3 | D80: Mass Change Field Value (Like Status from old value to New Value) | E80: Do Not Test | I80: EXEC | J80: =IF($B80=J$2,$I80,"") | K80: =IF($B80=K$2,$I80,"") -> EXEC | L80: =IF($B80=L$2,$I80,"") | M80: NT | S80: =IF($B80=S$2,$M80,"") | T80: =IF($B80=T$2,$M80,"") -> NT | U80: =IF($B80=U$2,$M80,"")
A81: FRM 4.18, FRM 4.4 | B81: Major | C81: OBL4 | D81: Mass Change: Spread PBA to Projected | E81: Do Not Test | I81: EXEC | J81: =IF($B81=J$2,$I81,"") | K81: =IF($B81=K$2,$I81,"") -> EXEC | L81: =IF($B81=L$2,$I81,"") | M81: NT | S81: =IF($B81=S$2,$M81,"") | T81: =IF($B81=T$2,$M81,"") -> NT | U81: =IF($B81=U$2,$M81,"")
A82: FRM 4.18, FRM 4.4 | B82: Major | C82: OBL5 | D82: Mass Change: Copy Obligation to Distribution | E82: Do Not Test | I82: EXEC | J82: =IF($B82=J$2,$I82,"") | K82: =IF($B82=K$2,$I82,"") -> EXEC | L82: =IF($B82=L$2,$I82,"") | M82: NT | S82: =IF($B82=S$2,$M82,"") | T82: =IF($B82=T$2,$M82,"") -> NT | U82: =IF($B82=U$2,$M82,"")
A83: FRM 4.18, FRM 4.4 | B83: Major | C83: OBL6 | D83: Mass Change: Copy Distribution to Obligation | E83: Do Not Test | I83: EXEC | J83: =IF($B83=J$2,$I83,"") | K83: =IF($B83=K$2,$I83,"") -> EXEC | L83: =IF($B83=L$2,$I83,"") | M83: NT | S83: =IF($B83=S$2,$M83,"") | T83: =IF($B83=T$2,$M83,"") -> NT | U83: =IF($B83=U$2,$M83,"")
A84: FRM 4.18, FRM 4.4 | B84: Major | C84: OBL7 | D84: Mass Change: Overlay Distribution to Funding | E84: Do Not Test | I84: EXEC | J84: =IF($B84=J$2,$I84,"") | K84: =IF($B84=K$2,$I84,"") -> EXEC | L84: =IF($B84=L$2,$I84,"") | M84: NT | S84: =IF($B84=S$2,$M84,"") | T84: =IF($B84=T$2,$M84,"") -> NT | U84: =IF($B84=U$2,$M84,"")
A85: FRM 4.18, FRM 4.4 | B85: Major | C85: OBL8 | D85: Mass Change: Overlay Obligation to Funding | E85: Do Not Test | I85: EXEC | J85: =IF($B85=J$2,$I85,"") | K85: =IF($B85=K$2,$I85,"") -> EXEC | L85: =IF($B85=L$2,$I85,"") | M85: NT | S85: =IF($B85=S$2,$M85,"") | T85: =IF($B85=T$2,$M85,"") -> NT | U85: =IF($B85=U$2,$M85,"")
K87: =COUNTIF(K3:K85,"NT") -> 1

Sheet Priority
A2: RQMT # | B2: Description | C2: Priority | D2: CVT # | E2: CVT | F2: CVT | G2: =+'CVT Master List'!C5 -> NAV1 | H2: =+'CVT Master List'!C6 -> NAV2 | I2: =+'CVT Master List'!C7 -> NAV3 | J2: =+'CVT Master List'!C8 -> NAV4 | K2: =+'CVT Master List'!C9 -> NAV5 | L2: User Mgmt | M2: =+'CVT Master List'!C11 -> UM1 | N2: =+'CVT Master List'!C12 -> UM2 | O2: =+'CVT Master List'!C13 -> UM3 | P2: =+'CVT Master List'!C14 -> UM4 | Q2: =+'CVT Master List'!C15 -> UM5 | R2: DC Role | S2: =+'CVT Master List'!C17 -> DCROLE1 | T2: =+'CVT Master List'!C18 -> DCROLE2 | U2: =+'CVT Master List'!C19 -> DCROLE3 | V2: =+'CVT Master List'!C20 -> DCROLE4 | W2: =+'CVT Master List'!C21 -> DCROLE5 | X2: =+'CVT Master List'!C22 -> DCROLE6 | Y2: DC Mgmt | Z2: =+'CVT Master List'!C24 -> DC1 | AA2: =+'CVT Master List'!C25 -> DC2 | AB2: =+'CVT Master List'!C26 -> DC3 | AC2: =+'CVT Master List'!C27 -> DC4 | AD2: =+'CVT Master List'!C28 -> DC5 | AE2: =+'CVT Master List'!C29 -> DC6 | AF2: =+'CVT Master List'!C30 -> DC7 | AG2: =+'CVT Master List'!C31 -> DC8 | AH2: DC9 | AI2: DC10 | AJ2: Mass chng | AK2: =+'CVT Master List'!C35 -> MassDC1 | AL2: =+'CVT Master List'!C36 -> MassDC2 | AM2: =+'CVT Master List'!C37 -> MassDC3 | AN2: =+'CVT Master List'!C38 -> MassDC4 | AO2: =+'CVT Master List'!C39 -> MassDC5 | AP2: =+'CVT Master List'!C40 -> MassDC6 | AQ2: =+'CVT Master List'!C41 -> MassDC7 | AR2: =+'CVT Master List'!C42 -> MassDC8 | AS2: =+'CVT Master List'!C43 -> MassDC9 | AT2: =+'CVT Master List'!C44 -> MassDC10 | AU2: TGT | AV2: =+'CVT Master List'!#REF! -> #REF! | AW2: =+'CVT Master List'!C46 -> TGT2 | AX2: =+'CVT Master List'!C47 -> TGT3 | AY2: =+'CVT Master List'!C48 -> TGT4 | AZ2: =+'CVT Master List'!C49 -> TGT5 | BA2: =+'CVT Master List'!C50 -> TGT6 | BB2: =+'CVT Master List'!C51 -> TGT7 | BC2: F S | BD2: =+'CVT Master List'!C58 -> FS3 | BE2: =+'CVT Master List'!C59 -> FS4 | BF2: =+'CVT Master List'!C60 -> FS5 | BG2: =+'CVT Master List'!C61 -> FS6 | BH2: =+'CVT Master List'!C62 -> FS7 | BI2: =+'CVT Master List'!C63 -> FS8 | BJ2: =+'CVT Master List'!C64 -> FS9 | BK2: =+'CVT Master List'!C65 -> FS10 | BL2: =+'CVT Master List'!#REF! -> #REF! | BM2: RPT | BN2: =+'CVT Master List'!C67 -> RPT1 | BO2: =+'CVT Master List'!C68 -> RPT2 | BP2: =+'CVT Master List'!C69 -> RPT3 | BQ2: =+'CVT Master List'!C71 -> RPT5 | BR2: =+'CVT Master List'!C72 -> RPT6 | BS2: =+'CVT Master List'!C73 -> RPT7 | BT2: =+'CVT Master List'!C74 -> RPT8 | BU2: Tools | BV2: =+'CVT Master List'!C79 -> TOOLS1 | BW2: =+'CVT Master List'!C80 -> TOOLS2 | BX2: =+'CVT Master List'!C81 -> TOOLS3 | BY2: =+'CVT Master List'!C82 -> TOOLS4 | BZ2: =+'CVT Master List'!C83 -> TOOLS 5 | CA2: =+'CVT Master List'!C84 -> TOOLS6 | CB2: RQMT | CC2: =+'CVT Master List'!C87 -> RQMT1 | CD2: =+'CVT Master List'!C88 -> RQMT2 | CE2: =+'CVT Master List'!C89 -> 0 | CF2: =+'CVT Master List'!C92 -> OBL2
E3: STATUS | F3: DETAILS | G3: =IF(COUNTIFS(G5:G80,"CRITICAL")>0,"Critical",IF(COUNTIFS(G5:G80,"Major")>0,"Major",IF(COUNTIFS(G5:G80,"Minor")>0,"Minor","UNK"))) -> UNK | H3: =IF(COUNTIFS(H5:H80,"CRITICAL")>0,"Critical",IF(COUNTIFS(H5:H80,"Major")>0,"Major",IF(COUNTIFS(H5:H80,"Minor")>0,"Minor","UNK"))) -> UNK | I3: =IF(COUNTIFS(I5:I80,"CRITICAL")>0,"Critical",IF(COUNTIFS(I5:I80,"Major")>0,"Major",IF(COUNTIFS(I5:I80,"Minor")>0,"Minor","UNK"))) -> UNK | J3: =IF(COUNTIFS(J5:J80,"CRITICAL")>0,"Critical",IF(COUNTIFS(J5:J80,"Major")>0,"Major",IF(COUNTIFS(J5:J80,"Minor")>0,"Minor","UNK"))) -> UNK | K3: =IF(COUNTIFS(K5:K80,"CRITICAL")>0,"Critical",IF(COUNTIFS(K5:K80,"Major")>0,"Major",IF(COUNTIFS(K5:K80,"Minor")>0,"Minor","UNK"))) -> UNK | M3: =IF(COUNTIFS(M5:M80,"CRITICAL")>0,"Critical",IF(COUNTIFS(M5:M80,"Major")>0,"Major",IF(COUNTIFS(M5:M80,"Minor")>0,"Minor","UNK"))) -> UNK | N3: =IF(COUNTIFS(N5:N80,"CRITICAL")>0,"Critical",IF(COUNTIFS(N5:N80,"Major")>0,"Major",IF(COUNTIFS(N5:N80,"Minor")>0,"Minor","UNK"))) -> UNK | O3: =IF(COUNTIFS(O5:O80,"CRITICAL")>0,"Critical",IF(COUNTIFS(O5:O80,"Major")>0,"Major",IF(COUNTIFS(O5:O80,"Minor")>0,"Minor","UNK"))) -> UNK | P3: =IF(COUNTIFS(P5:P80,"CRITICAL")>0,"Critical",IF(COUNTIFS(P5:P80,"Major")>0,"Major",IF(COUNTIFS(P5:P80,"Minor")>0,"Minor","UNK"))) -> UNK | Q3: =IF(COUNTIFS(Q5:Q80,"CRITICAL")>0,"Critical",IF(COUNTIFS(Q5:Q80,"Major")>0,"Major",IF(COUNTIFS(Q5:Q80,"Minor")>0,"Minor","UNK"))) -> UNK | S3: =IF(COUNTIFS(S5:S80,"CRITICAL")>0,"Critical",IF(COUNTIFS(S5:S80,"Major")>0,"Major",IF(COUNTIFS(S5:S80,"Minor")>0,"Minor","UNK"))) -> UNK | T3: =IF(COUNTIFS(T5:T80,"CRITICAL")>0,"Critical",IF(COUNTIFS(T5:T80,"Major")>0,"Major",IF(COUNTIFS(T5:T80,"Minor")>0,"Minor","UNK"))) -> UNK | U3: =IF(COUNTIFS(U5:U80,"CRITICAL")>0,"Critical",IF(COUNTIFS(U5:U80,"Major")>0,"Major",IF(COUNTIFS(U5:U80,"Minor")>0,"Minor","UNK"))) -> UNK | V3: =IF(COUNTIFS(V5:V80,"CRITICAL")>0,"Critical",IF(COUNTIFS(V5:V80,"Major")>0,"Major",IF(COUNTIFS(V5:V80,"Minor")>0,"Minor","UNK"))) -> UNK | W3: =IF(COUNTIFS(W5:W80,"CRITICAL")>0,"Critical",IF(COUNTIFS(W5:W80,"Major")>0,"Major",IF(COUNTIFS(W5:W80,"Minor")>0,"Minor","UNK"))) -> UNK | X3: =IF(COUNTIFS(X5:X80,"CRITICAL")>0,"Critical",IF(COUNTIFS(X5:X80,"Major")>0,"Major",IF(COUNTIFS(X5:X80,"Minor")>0,"Minor","UNK"))) -> UNK | Z3: =IF(COUNTIFS(Z5:Z80,"CRITICAL")>0,"Critical",IF(COUNTIFS(Z5:Z80,"Major")>0,"Major",IF(COUNTIFS(Z5:Z80,"Minor")>0,"Minor","UNK"))) -> UNK | AA3: =IF(COUNTIFS(AA5:AA80,"CRITICAL")>0,"Critical",IF(COUNTIFS(AA5:AA80,"Major")>0,"Major",IF(COUNTIFS(AA5:AA80,"Minor")>0,"Minor","UNK"))) -> UNK | AB3: =IF(COUNTIFS(AB5:AB80,"CRITICAL")>0,"Critical",IF(COUNTIFS(AB5:AB80,"Major")>0,"Major",IF(COUNTIFS(AB5:AB80,"Minor")>0,"Minor","UNK"))) -> UNK | AC3: =IF(COUNTIFS(AC5:AC80,"CRITICAL")>0,"Critical",IF(COUNTIFS(AC5:AC80,"Major")>0,"Major",IF(COUNTIFS(AC5:AC80,"Minor")>0,"Minor","UNK"))) -> UNK | AD3: =IF(COUNTIFS(AD5:AD80,"CRITICAL")>0,"Critical",IF(COUNTIFS(AD5:AD80,"Major")>0,"Major",IF(COUNTIFS(AD5:AD80,"Minor")>0,"Minor","UNK"))) -> UNK | AE3: =IF(COUNTIFS(AE5:AE80,"CRITICAL")>0,"Critical",IF(COUNTIFS(AE5:AE80,"Major")>0,"Major",IF(COUNTIFS(AE5:AE80,"Minor")>0,"Minor","UNK"))) -> UNK | AF3: =IF(COUNTIFS(AF5:AF80,"CRITICAL")>0,"Critical",IF(COUNTIFS(AF5:AF80,"Major")>0,"Major",IF(COUNTIFS(AF5:AF80,"Minor")>0,"Minor","UNK"))) -> UNK | AG3: =IF(COUNTIFS(AG5:AG80,"CRITICAL")>0,"Critical",IF(COUNTIFS(AG5:AG80,"Major")>0,"Major",IF(COUNTIFS(AG5:AG80,"Minor")>0,"Minor","UNK"))) -> UNK | ... AI3: =IF(COUNTIFS(AI5:AI80,"CRITICAL")>0,"Critical",IF(COUNTIFS(AI5:AI80,"Major")>0,"Major",IF(COUNTIFS(AI5:AI80,"Minor")>0,"Minor","UNK"))) -> UNK | AK3: =IF(COUNTIFS(AK5:AK80,"CRITICAL")>0,"Critical",IF(COUNTIFS(AK5:AK80,"Major")>0,"Major",IF(COUNTIFS(AK5:AK80,"Minor")>0,"Minor","UNK"))) -> UNK | AL3: =IF(COUNTIFS(AL5:AL80,"CRITICAL")>0,"Critical",IF(COUNTIFS(AL5:AL80,"Major")>0,"Major",IF(COUNTIFS(AL5:AL80,"Minor")>0,"Minor","UNK"))) -> UNK | AM3: =IF(COUNTIFS(AM5:AM80,"CRITICAL")>0,"Critical",IF(COUNTIFS(AM5:AM80,"Major")>0,"Major",IF(COUNTIFS(AM5:AM80,"Minor")>0,"Minor","UNK"))) -> UNK | AN3: =IF(COUNTIFS(AN5:AN80,"CRITICAL")>0,"Critical",IF(COUNTIFS(AN5:AN80,"Major")>0,"Major",IF(COUNTIFS(AN5:AN80,"Minor")>0,"Minor","UNK"))) -> UNK | AO3: =IF(COUNTIFS(AO5:AO80,"CRITICAL")>0,"Critical",IF(COUNTIFS(AO5:AO80,"Major")>0,"Major",IF(COUNTIFS(AO5:AO80,"Minor")>0,"Minor","UNK"))) -> UNK | AP3: =IF(COUNTIFS(AP5:AP80,"CRITICAL")>0,"Critical",IF(COUNTIFS(AP5:AP80,"Major")>0,"Major",IF(COUNTIFS(AP5:AP80,"Minor")>0,"Minor","UNK"))) -> UNK | AQ3: =IF(COUNTIFS(AQ5:AQ80,"CRITICAL")>0,"Critical",IF(COUNTIFS(AQ5:AQ80,"Major")>0,"Major",IF(COUNTIFS(AQ5:AQ80,"Minor")>0,"Minor","UNK"))) -> UNK | AR3: =IF(COUNTIFS(AR5:AR80,"CRITICAL")>0,"Critical",IF(COUNTIFS(AR5:AR80,"Major")>0,"Major",IF(COUNTIFS(AR5:AR80,"Minor")>0,"Minor","UNK"))) -> UNK | ... AT3: =IF(COUNTIFS(AT5:AT80,"CRITICAL")>0,"Critical",IF(COUNTIFS(AT5:AT80,"Major")>0,"Major",IF(COUNTIFS(AT5:AT80,"Minor")>0,"Minor","UNK"))) -> UNK | AV3: =IF(COUNTIFS(AV5:AV80,"CRITICAL")>0,"Critical",IF(COUNTIFS(AV5:AV80,"Major")>0,"Major",IF(COUNTIFS(AV5:AV80,"Minor")>0,"Minor","UNK"))) -> UNK | AW3: =IF(COUNTIFS(AW5:AW80,"CRITICAL")>0,"Critical",IF(COUNTIFS(AW5:AW80,"Major")>0,"Major",IF(COUNTIFS(AW5:AW80,"Minor")>0,"Minor","UNK"))) -> UNK | AX3: =IF(COUNTIFS(AX5:AX80,"CRITICAL")>0,"Critical",IF(COUNTIFS(AX5:AX80,"Major")>0,"Major",IF(COUNTIFS(AX5:AX80,"Minor")>0,"Minor","UNK"))) -> UNK | AY3: =IF(COUNTIFS(AY5:AY80,"CRITICAL")>0,"Critical",IF(COUNTIFS(AY5:AY80,"Major")>0,"Major",IF(COUNTIFS(AY5:AY80,"Minor")>0,"Minor","UNK"))) -> UNK | AZ3: =IF(COUNTIFS(AZ5:AZ80,"CRITICAL")>0,"Critical",IF(COUNTIFS(AZ5:AZ80,"Major")>0,"Major",IF(COUNTIFS(AZ5:AZ80,"Minor")>0,"Minor","UNK"))) -> UNK | BA3: =IF(COUNTIFS(BA5:BA80,"CRITICAL")>0,"Critical",IF(COUNTIFS(BA5:BA80,"Major")>0,"Major",IF(COUNTIFS(BA5:BA80,"Minor")>0,"Minor","UNK"))) -> UNK | BB3: =IF(COUNTIFS(BB5:BB80,"CRITICAL")>0,"Critical",IF(COUNTIFS(BB5:BB80,"Major")>0,"Major",IF(COUNTIFS(BB5:BB80,"Minor")>0,"Minor","UNK"))) -> UNK | BD3: =IF(COUNTIFS(BD5:BD80,"CRITICAL")>0,"Critical",IF(COUNTIFS(BD5:BD80,"Major")>0,"Major",IF(COUNTIFS(BD5:BD80,"Minor")>0,"Minor","UNK"))) -> UNK | BE3: =IF(COUNTIFS(BE5:BE80,"CRITICAL")>0,"Critical",IF(COUNTIFS(BE5:BE80,"Major")>0,"Major",IF(COUNTIFS(BE5:BE80,"Minor")>0,"Minor","UNK"))) -> UNK | BF3: =IF(COUNTIFS(BF5:BF80,"CRITICAL")>0,"Critical",IF(COUNTIFS(BF5:BF80,"Major")>0,"Major",IF(COUNTIFS(BF5:BF80,"Minor")>0,"Minor","UNK"))) -> UNK | BG3: =IF(COUNTIFS(BG5:BG80,"CRITICAL")>0,"Critical",IF(COUNTIFS(BG5:BG80,"Major")>0,"Major",IF(COUNTIFS(BG5:BG80,"Minor")>0,"Minor","UNK"))) -> UNK | BH3: =IF(COUNTIFS(BH5:BH80,"CRITICAL")>0,"Critical",IF(COUNTIFS(BH5:BH80,"Major")>0,"Major",IF(COUNTIFS(BH5:BH80,"Minor")>0,"Minor","UNK"))) -> UNK | BI3: =IF(COUNTIFS(BI5:BI80,"CRITICAL")>0,"Critical",IF(COUNTIFS(BI5:BI80,"Major")>0,"Major",IF(COUNTIFS(BI5:BI80,"Minor")>0,"Minor","UNK"))) -> UNK | BJ3: =IF(COUNTIFS(BJ5:BJ80,"CRITICAL")>0,"Critical",IF(COUNTIFS(BJ5:BJ80,"Major")>0,"Major",IF(COUNTIFS(BJ5:BJ80,"Minor")>0,"Minor","UNK"))) -> UNK | BK3: =IF(COUNTIFS(BK5:BK80,"CRITICAL")>0,"Critical",IF(COUNTIFS(BK5:BK80,"Major")>0,"Major",IF(COUNTIFS(BK5:BK80,"Minor")>0,"Minor","UNK"))) -> UNK | BL3: =IF(COUNTIFS(BL5:BL80,"CRITICAL")>0,"Critical",IF(COUNTIFS(BL5:BL80,"Major")>0,"Major",IF(COUNTIFS(BL5:BL80,"Minor")>0,"Minor","UNK"))) -> UNK | BN3: =IF(COUNTIFS(BN5:BN80,"CRITICAL")>0,"Critical",IF(COUNTIFS(BN5:BN80,"Major")>0,"Major",IF(COUNTIFS(BN5:BN80,"Minor")>0,"Minor","UNK"))) -> UNK | BO3: =IF(COUNTIFS(BO5:BO80,"CRITICAL")>0,"Critical",IF(COUNTIFS(BO5:BO80,"Major")>0,"Major",IF(COUNTIFS(BO5:BO80,"Minor")>0,"Minor","UNK"))) -> UNK | BP3: =IF(COUNTIFS(BP5:BP80,"CRITICAL")>0,"Critical",IF(COUNTIFS(BP5:BP80,"Major")>0,"Major",IF(COUNTIFS(BP5:BP80,"Minor")>0,"Minor","UNK"))) -> UNK | BQ3: =IF(COUNTIFS(BQ5:BQ80,"CRITICAL")>0,"Critical",IF(COUNTIFS(BQ5:BQ80,"Major")>0,"Major",IF(COUNTIFS(BQ5:BQ80,"Minor")>0,"Minor","UNK"))) -> UNK | BR3: =IF(COUNTIFS(BR5:BR80,"CRITICAL")>0,"Critical",IF(COUNTIFS(BR5:BR80,"Major")>0,"Major",IF(COUNTIFS(BR5:BR80,"Minor")>0,"Minor","UNK"))) -> UNK | BS3: =IF(COUNTIFS(BS5:BS80,"CRITICAL")>0,"Critical",IF(COUNTIFS(BS5:BS80,"Major")>0,"Major",IF(COUNTIFS(BS5:BS80,"Minor")>0,"Minor","UNK"))) -> UNK | BT3: =IF(COUNTIFS(BT5:BT80,"CRITICAL")>0,"Critical",IF(COUNTIFS(BT5:BT80,"Major")>0,"Major",IF(COUNTIFS(BT5:BT80,"Minor")>0,"Minor","UNK"))) -> UNK | BV3: =IF(COUNTIFS(BV5:BV80,"CRITICAL")>0,"Critical",IF(COUNTIFS(BV5:BV80,"Major")>0,"Major",IF(COUNTIFS(BV5:BV80,"Minor")>0,"Minor","UNK"))) -> UNK | BW3: =IF(COUNTIFS(BW5:BW80,"CRITICAL")>0,"Critical",IF(COUNTIFS(BW5:BW80,"Major")>0,"Major",IF(COUNTIFS(BW5:BW80,"Minor")>0,"Minor","UNK"))) -> UNK | BX3: =IF(COUNTIFS(BX5:BX80,"CRITICAL")>0,"Critical",IF(COUNTIFS(BX5:BX80,"Major")>0,"Major",IF(COUNTIFS(BX5:BX80,"Minor")>0,"Minor","UNK"))) -> UNK | BY3: =IF(COUNTIFS(BY5:BY80,"CRITICAL")>0,"Critical",IF(COUNTIFS(BY5:BY80,"Major")>0,"Major",IF(COUNTIFS(BY5:BY80,"Minor")>0,"Minor","UNK"))) -> UNK | BZ3: =IF(COUNTIFS(BZ5:BZ80,"CRITICAL")>0,"Critical",IF(COUNTIFS(BZ5:BZ80,"Major")>0,"Major",IF(COUNTIFS(BZ5:BZ80,"Minor")>0,"Minor","UNK"))) -> UNK | CA3: =IF(COUNTIFS(CA5:CA80,"CRITICAL")>0,"Critical",IF(COUNTIFS(CA5:CA80,"Major")>0,"Major",IF(COUNTIFS(CA5:CA80,"Minor")>0,"Minor","UNK"))) -> UNK | CC3: =IF(COUNTIFS(CC5:CC80,"CRITICAL")>0,"Critical",IF(COUNTIFS(CC5:CC80,"Major")>0,"Major",IF(COUNTIFS(CC5:CC80,"Minor")>0,"Minor","UNK"))) -> UNK | CD3: =IF(COUNTIFS(CD5:CD80,"CRITICAL")>0,"Critical",IF(COUNTIFS(CD5:CD80,"Major")>0,"Major",IF(COUNTIFS(CD5:CD80,"Minor")>0,"Minor","UNK"))) -> UNK | CE3: =IF(COUNTIFS(CE5:CE80,"CRITICAL")>0,"Critical",IF(COUNTIFS(CE5:CE80,"Major")>0,"Major",IF(COUNTIFS(CE5:CE80,"Minor")>0,"Minor","UNK"))) -> UNK | CF3: =IF(COUNTIFS(CF5:CF80,"CRITICAL")>0,"Critical",IF(COUNTIFS(CF5:CF80,"Major")>0,"Major",IF(COUNTIFS(CF5:CF80,"Minor")>0,"Minor","UNK"))) -> UNK
A4: =#REF! -> #REF!
A5: =#REF! -> #REF! | B5: =#REF! -> #REF! | C5: =#REF! -> #REF! | D5: UM1-UM5 | E5: =IF(COUNTIFS(F5:CF5,"F")+COUNTIFS(F5:CF5,"NT")>0,"In Test",IF(COUNTIFS(F5:CF5,"P")+COUNTIFS(F5:CF5,"A")>0,"Pass","Pending")) -> Pending | F5: ="Pass: "& COUNTIFS(G5:CG5,"P")& " /Accept: "& COUNTIFS(G5:CG5,"A")& "/ Fail: "& COUNTIFS(G5:CG5,"Fail") & "/ NT: "& COUNTIFS(G5:CG5,"NT") -> Pass: 0 /Accept: 0/ Fail: 0/ NT: 0 | G5: =IF(#REF!<>"N/A",Priority!$C5,"") -> #REF! | H5: =IF(#REF!<>"N/A",Priority!$C5,"") -> #REF! | I5: =IF(#REF!<>"N/A",Priority!$C5,"") -> #REF! | J5: =IF(#REF!<>"N/A",Priority!$C5,"") -> #REF! | K5: =IF(#REF!<>"N/A",Priority!$C5,"") -> #REF! | M5: =IF(#REF!<>"N/A",Priority!$C5,"") -> #REF! | N5: =IF(#REF!<>"N/A",Priority!$C5,"") -> #REF! | O5: =IF(#REF!<>"N/A",Priority!$C5,"") -> #REF! | P5: =IF(#REF!<>"N/A",Priority!$C5,"") -> #REF! | Q5: =IF(#REF!<>"N/A",Priority!$C5,"") -> #REF! | S5: =IF(#REF!<>"N/A",Priority!$C5,"") -> #REF! | T5: =IF(#REF!<>"N/A",Priority!$C5,"") -> #REF! | U5: =IF(#REF!<>"N/A",Priority!$C5,"") -> #REF! | V5: =IF(#REF!<>"N/A",Priority!$C5,"") -> #REF! | W5: =IF(#REF!<>"N/A",Priority!$C5,"") -> #REF! | X5: =IF(#REF!<>"N/A",Priority!$C5,"") -> #REF! | Z5: =IF(#REF!<>"N/A",Priority!$C5,"") -> #REF! | AA5: =IF(#REF!<>"N/A",Priority!$C5,"") -> #REF! | AB5: =IF(#REF!<>"N/A",Priority!$C5,"") -> #REF! | AC5: =IF(#REF!<>"N/A",Priority!$C5,"") -> #REF! | AD5: =IF(#REF!<>"N/A",Priority!$C5,"") -> #REF! | AE5: =IF(#REF!<>"N/A",Priority!$C5,"") -> #REF! | AF5: =IF(#REF!<>"N/A",Priority!$C5,"") -> #REF! | AG5: =IF(#REF!<>"N/A",Priority!$C5,"") -> #REF! | ... AI5: =IF(#REF!<>"N/A",Priority!$C5,"") -> #REF! | AK5: =IF(#REF!<>"N/A",Priority!$C5,"") -> #REF! | AL5: =IF(#REF!<>"N/A",Priority!$C5,"") -> #REF! | AM5: =IF(#REF!<>"N/A",Priority!$C5,"") -> #REF! | AN5: =IF(#REF!<>"N/A",Priority!$C5,"") -> #REF! | AO5: =IF(#REF!<>"N/A",Priority!$C5,"") -> #REF! | AP5: =IF(#REF!<>"N/A",Priority!$C5,"") -> #REF! | AQ5: =IF(#REF!<>"N/A",Priority!$C5,"") -> #REF! | AR5: =IF(#REF!<>"N/A",Priority!$C5,"") -> #REF! | ... AT5: =IF(#REF!<>"N/A",Priority!$C5,"") -> #REF! | AV5: =IF(#REF!<>"N/A",Priority!$C5,"") -> #REF! | AW5: =IF(#REF!<>"N/A",Priority!$C5,"") -> #REF! | AX5: =IF(#REF!<>"N/A",Priority!$C5,"") -> #REF! | AY5: =IF(#REF!<>"N/A",Priority!$C5,"") -> #REF! | AZ5: =IF(#REF!<>"N/A",Priority!$C5,"") -> #REF! | BA5: =IF(#REF!<>"N/A",Priority!$C5,"") -> #REF! | BB5: =IF(#REF!<>"N/A",Priority!$C5,"") -> #REF! | BD5: =IF(#REF!<>"N/A",Priority!$C5,"") -> #REF! | BE5: =IF(#REF!<>"N/A",Priority!$C5,"") -> #REF! | BF5: =IF(#REF!<>"N/A",Priority!$C5,"") -> #REF! | BG5: =IF(#REF!<>"N/A",Priority!$C5,"") -> #REF! | BH5: =IF(#REF!<>"N/A",Priority!$C5,"") -> #REF! | BI5: =IF(#REF!<>"N/A",Priority!$C5,"") -> #REF! | BJ5: =IF(#REF!<>"N/A",Priority!$C5,"") -> #REF! | BK5: =IF(#REF!<>"N/A",Priority!$C5,"") -> #REF! | BL5: =IF(#REF!<>"N/A",Priority!$C5,"") -> #REF! | BN5: =IF(#REF!<>"N/A",Priority!$C5,"") -> #REF! | BO5: =IF(#REF!<>"N/A",Priority!$C5,"") -> #REF! | BP5: =IF(#REF!<>"N/A",Priority!$C5,"") -> #REF! | BQ5: =IF(#REF!<>"N/A",Priority!$C5,"") -> #REF! | BR5: =IF(#REF!<>"N/A",Priority!$C5,"") -> #REF! | BS5: =IF(#REF!<>"N/A",Priority!$C5,"") -> #REF! | BT5: =IF(#REF!<>"N/A",Priority!$C5,"") -> #REF! | BV5: =IF(#REF!<>"N/A",Priority!$C5,"") -> #REF! | BW5: =IF(#REF!<>"N/A",Priority!$C5,"") -> #REF! | BX5: =IF(#REF!<>"N/A",Priority!$C5,"") -> #REF! | BY5: =IF(#REF!<>"N/A",Priority!$C5,"") -> #REF! | BZ5: =IF(#REF!<>"N/A",Priority!$C5,"") -> #REF! | CA5: =IF(#REF!<>"N/A",Priority!$C5,"") -> #REF! | CC5: =IF(#REF!<>"N/A",Priority!$C5,"") -> #REF! | CD5: =IF(#REF!<>"N/A",Priority!$C5,"") -> #REF! | CE5: =IF(#REF!<>"N/A",Priority!$C5,"") -> #REF! | CF5: =IF(#REF!<>"N/A",Priority!$C5,"") -> #REF!
A6: =#REF! -> #REF! | B6: =#REF! -> #REF! | C6: =#REF! -> #REF! | D6: UM1-UM5 | E6: =IF(COUNTIFS(F6:CF6,"F")+COUNTIFS(F6:CF6,"NT")>0,"In Test",IF(COUNTIFS(F6:CF6,"P")+COUNTIFS(F6:CF6,"A")>0,"Pass","Pending")) -> Pending | F6: ="Pass: "& COUNTIFS(G6:CG6,"P")& " /Accept: "& COUNTIFS(G6:CG6,"A")& "/ Fail: "& COUNTIFS(G6:CG6,"Fail") & "/ NT: "& COUNTIFS(G6:CG6,"NT") -> Pass: 0 /Accept: 0/ Fail: 0/ NT: 0 | G6: =IF(#REF!<>"N/A",Priority!$C6,"") -> #REF! | H6: =IF(#REF!<>"N/A",Priority!$C6,"") -> #REF! | I6: =IF(#REF!<>"N/A",Priority!$C6,"") -> #REF! | J6: =IF(#REF!<>"N/A",Priority!$C6,"") -> #REF! | K6: =IF(#REF!<>"N/A",Priority!$C6,"") -> #REF! | M6: =IF(#REF!<>"N/A",Priority!$C6,"") -> #REF! | N6: =IF(#REF!<>"N/A",Priority!$C6,"") -> #REF! | O6: =IF(#REF!<>"N/A",Priority!$C6,"") -> #REF! | P6: =IF(#REF!<>"N/A",Priority!$C6,"") -> #REF! | Q6: =IF(#REF!<>"N/A",Priority!$C6,"") -> #REF! | S6: =IF(#REF!<>"N/A",Priority!$C6,"") -> #REF! | T6: =IF(#REF!<>"N/A",Priority!$C6,"") -> #REF! | U6: =IF(#REF!<>"N/A",Priority!$C6,"") -> #REF! | V6: =IF(#REF!<>"N/A",Priority!$C6,"") -> #REF! | W6: =IF(#REF!<>"N/A",Priority!$C6,"") -> #REF! | X6: =IF(#REF!<>"N/A",Priority!$C6,"") -> #REF! | Z6: =IF(#REF!<>"N/A",Priority!$C6,"") -> #REF! | AA6: =IF(#REF!<>"N/A",Priority!$C6,"") -> #REF! | AB6: =IF(#REF!<>"N/A",Priority!$C6,"") -> #REF! | AC6: =IF(#REF!<>"N/A",Priority!$C6,"") -> #REF! | AD6: =IF(#REF!<>"N/A",Priority!$C6,"") -> #REF! | AE6: =IF(#REF!<>"N/A",Priority!$C6,"") -> #REF! | AF6: =IF(#REF!<>"N/A",Priority!$C6,"") -> #REF! | AG6: =IF(#REF!<>"N/A",Priority!$C6,"") -> #REF! | ... AI6: =IF(#REF!<>"N/A",Priority!$C6,"") -> #REF! | AK6: =IF(#REF!<>"N/A",Priority!$C6,"") -> #REF! | AL6: =IF(#REF!<>"N/A",Priority!$C6,"") -> #REF! | AM6: =IF(#REF!<>"N/A",Priority!$C6,"") -> #REF! | AN6: =IF(#REF!<>"N/A",Priority!$C6,"") -> #REF! | AO6: =IF(#REF!<>"N/A",Priority!$C6,"") -> #REF! | AP6: =IF(#REF!<>"N/A",Priority!$C6,"") -> #REF! | AQ6: =IF(#REF!<>"N/A",Priority!$C6,"") -> #REF! | AR6: =IF(#REF!<>"N/A",Priority!$C6,"") -> #REF! | ... AT6: =IF(#REF!<>"N/A",Priority!$C6,"") -> #REF! | AV6: =IF(#REF!<>"N/A",Priority!$C6,"") -> #REF! | AW6: =IF(#REF!<>"N/A",Priority!$C6,"") -> #REF! | AX6: =IF(#REF!<>"N/A",Priority!$C6,"") -> #REF! | AY6: =IF(#REF!<>"N/A",Priority!$C6,"") -> #REF! | AZ6: =IF(#REF!<>"N/A",Priority!$C6,"") -> #REF! | BA6: =IF(#REF!<>"N/A",Priority!$C6,"") -> #REF! | BB6: =IF(#REF!<>"N/A",Priority!$C6,"") -> #REF! | BD6: =IF(#REF!<>"N/A",Priority!$C6,"") -> #REF! | BE6: =IF(#REF!<>"N/A",Priority!$C6,"") -> #REF! | BF6: =IF(#REF!<>"N/A",Priority!$C6,"") -> #REF! | BG6: =IF(#REF!<>"N/A",Priority!$C6,"") -> #REF! | BH6: =IF(#REF!<>"N/A",Priority!$C6,"") -> #REF! | BI6: =IF(#REF!<>"N/A",Priority!$C6,"") -> #REF! | BJ6: =IF(#REF!<>"N/A",Priority!$C6,"") -> #REF! | BK6: =IF(#REF!<>"N/A",Priority!$C6,"") -> #REF! | BL6: =IF(#REF!<>"N/A",Priority!$C6,"") -> #REF! | BN6: =IF(#REF!<>"N/A",Priority!$C6,"") -> #REF! | BO6: =IF(#REF!<>"N/A",Priority!$C6,"") -> #REF! | BP6: =IF(#REF!<>"N/A",Priority!$C6,"") -> #REF! | BQ6: =IF(#REF!<>"N/A",Priority!$C6,"") -> #REF! | BR6: =IF(#REF!<>"N/A",Priority!$C6,"") -> #REF! | BS6: =IF(#REF!<>"N/A",Priority!$C6,"") -> #REF! | BT6: =IF(#REF!<>"N/A",Priority!$C6,"") -> #REF! | BV6: =IF(#REF!<>"N/A",Priority!$C6,"") -> #REF! | BW6: =IF(#REF!<>"N/A",Priority!$C6,"") -> #REF! | BX6: =IF(#REF!<>"N/A",Priority!$C6,"") -> #REF! | BY6: =IF(#REF!<>"N/A",Priority!$C6,"") -> #REF! | BZ6: =IF(#REF!<>"N/A",Priority!$C6,"") -> #REF! | CA6: =IF(#REF!<>"N/A",Priority!$C6,"") -> #REF! | CC6: =IF(#REF!<>"N/A",Priority!$C6,"") -> #REF! | CD6: =IF(#REF!<>"N/A",Priority!$C6,"") -> #REF! | CE6: =IF(#REF!<>"N/A",Priority!$C6,"") -> #REF! | CF6: =IF(#REF!<>"N/A",Priority!$C6,"") -> #REF!
A7: =#REF! -> #REF! | B7: =#REF! -> #REF! | C7: =#REF! -> #REF! | D7: UM1-UM5 | E7: =IF(COUNTIFS(F7:CF7,"F")+COUNTIFS(F7:CF7,"NT")>0,"In Test",IF(COUNTIFS(F7:CF7,"P")+COUNTIFS(F7:CF7,"A")>0,"Pass","Pending")) -> Pending | F7: ="Pass: "& COUNTIFS(G7:CG7,"P")& " /Accept: "& COUNTIFS(G7:CG7,"A")& "/ Fail: "& COUNTIFS(G7:CG7,"Fail") & "/ NT: "& COUNTIFS(G7:CG7,"NT") -> Pass: 0 /Accept: 0/ Fail: 0/ NT: 0 | G7: =IF(#REF!<>"N/A",Priority!$C7,"") -> #REF! | H7: =IF(#REF!<>"N/A",Priority!$C7,"") -> #REF! | I7: =IF(#REF!<>"N/A",Priority!$C7,"") -> #REF! | J7: =IF(#REF!<>"N/A",Priority!$C7,"") -> #REF! | K7: =IF(#REF!<>"N/A",Priority!$C7,"") -> #REF! | M7: =IF(#REF!<>"N/A",Priority!$C7,"") -> #REF! | N7: =IF(#REF!<>"N/A",Priority!$C7,"") -> #REF! | O7: =IF(#REF!<>"N/A",Priority!$C7,"") -> #REF! | P7: =IF(#REF!<>"N/A",Priority!$C7,"") -> #REF! | Q7: =IF(#REF!<>"N/A",Priority!$C7,"") -> #REF! | S7: =IF(#REF!<>"N/A",Priority!$C7,"") -> #REF! | T7: =IF(#REF!<>"N/A",Priority!$C7,"") -> #REF! | U7: =IF(#REF!<>"N/A",Priority!$C7,"") -> #REF! | V7: =IF(#REF!<>"N/A",Priority!$C7,"") -> #REF! | W7: =IF(#REF!<>"N/A",Priority!$C7,"") -> #REF! | X7: =IF(#REF!<>"N/A",Priority!$C7,"") -> #REF! | Z7: =IF(#REF!<>"N/A",Priority!$C7,"") -> #REF! | AA7: =IF(#REF!<>"N/A",Priority!$C7,"") -> #REF! | AB7: =IF(#REF!<>"N/A",Priority!$C7,"") -> #REF! | AC7: =IF(#REF!<>"N/A",Priority!$C7,"") -> #REF! | AD7: =IF(#REF!<>"N/A",Priority!$C7,"") -> #REF! | AE7: =IF(#REF!<>"N/A",Priority!$C7,"") -> #REF! | AF7: =IF(#REF!<>"N/A",Priority!$C7,"") -> #REF! | AG7: =IF(#REF!<>"N/A",Priority!$C7,"") -> #REF! | ... AI7: =IF(#REF!<>"N/A",Priority!$C7,"") -> #REF! | AK7: =IF(#REF!<>"N/A",Priority!$C7,"") -> #REF! | AL7: =IF(#REF!<>"N/A",Priority!$C7,"") -> #REF! | AM7: =IF(#REF!<>"N/A",Priority!$C7,"") -> #REF! | AN7: =IF(#REF!<>"N/A",Priority!$C7,"") -> #REF! | AO7: =IF(#REF!<>"N/A",Priority!$C7,"") -> #REF! | AP7: =IF(#REF!<>"N/A",Priority!$C7,"") -> #REF! | AQ7: =IF(#REF!<>"N/A",Priority!$C7,"") -> #REF! | AR7: =IF(#REF!<>"N/A",Priority!$C7,"") -> #REF! | ... AT7: =IF(#REF!<>"N/A",Priority!$C7,"") -> #REF! | AV7: =IF(#REF!<>"N/A",Priority!$C7,"") -> #REF! | AW7: =IF(#REF!<>"N/A",Priority!$C7,"") -> #REF! | AX7: =IF(#REF!<>"N/A",Priority!$C7,"") -> #REF! | AY7: =IF(#REF!<>"N/A",Priority!$C7,"") -> #REF! | AZ7: =IF(#REF!<>"N/A",Priority!$C7,"") -> #REF! | BA7: =IF(#REF!<>"N/A",Priority!$C7,"") -> #REF! | BB7: =IF(#REF!<>"N/A",Priority!$C7,"") -> #REF! | BD7: =IF(#REF!<>"N/A",Priority!$C7,"") -> #REF! | BE7: =IF(#REF!<>"N/A",Priority!$C7,"") -> #REF! | BF7: =IF(#REF!<>"N/A",Priority!$C7,"") -> #REF! | BG7: =IF(#REF!<>"N/A",Priority!$C7,"") -> #REF! | BH7: =IF(#REF!<>"N/A",Priority!$C7,"") -> #REF! | BI7: =IF(#REF!<>"N/A",Priority!$C7,"") -> #REF! | BJ7: =IF(#REF!<>"N/A",Priority!$C7,"") -> #REF! | BK7: =IF(#REF!<>"N/A",Priority!$C7,"") -> #REF! | BL7: =IF(#REF!<>"N/A",Priority!$C7,"") -> #REF! | BN7: =IF(#REF!<>"N/A",Priority!$C7,"") -> #REF! | BO7: =IF(#REF!<>"N/A",Priority!$C7,"") -> #REF! | BP7: =IF(#REF!<>"N/A",Priority!$C7,"") -> #REF! | BQ7: =IF(#REF!<>"N/A",Priority!$C7,"") -> #REF! | BR7: =IF(#REF!<>"N/A",Priority!$C7,"") -> #REF! | BS7: =IF(#REF!<>"N/A",Priority!$C7,"") -> #REF! | BT7: =IF(#REF!<>"N/A",Priority!$C7,"") -> #REF! | BV7: =IF(#REF!<>"N/A",Priority!$C7,"") -> #REF! | BW7: =IF(#REF!<>"N/A",Priority!$C7,"") -> #REF! | BX7: =IF(#REF!<>"N/A",Priority!$C7,"") -> #REF! | BY7: =IF(#REF!<>"N/A",Priority!$C7,"") -> #REF! | BZ7: =IF(#REF!<>"N/A",Priority!$C7,"") -> #REF! | CA7: =IF(#REF!<>"N/A",Priority!$C7,"") -> #REF! | CC7: =IF(#REF!<>"N/A",Priority!$C7,"") -> #REF! | CD7: =IF(#REF!<>"N/A",Priority!$C7,"") -> #REF! | CE7: =IF(#REF!<>"N/A",Priority!$C7,"") -> #REF! | CF7: =IF(#REF!<>"N/A",Priority!$C7,"") -> #REF!
A8: =#REF! -> #REF!
A9: =#REF! -> #REF! | B9: =#REF! -> #REF! | C9: =#REF! -> #REF! | D9: UM4 | E9: =IF(COUNTIFS(F9:CF9,"F")+COUNTIFS(F9:CF9,"NT")>0,"In Test",IF(COUNTIFS(F9:CF9,"P")+COUNTIFS(F9:CF9,"A")>0,"Pass","Pending")) -> Pending | F9: ="Pass: "& COUNTIFS(G9:CG9,"P")& " /Accept: "& COUNTIFS(G9:CG9,"A")& "/ Fail: "& COUNTIFS(G9:CG9,"Fail") & "/ NT: "& COUNTIFS(G9:CG9,"NT") -> Pass: 0 /Accept: 0/ Fail: 0/ NT: 0 | G9: =IF(#REF!<>"N/A",Priority!$C9,"") -> #REF! | H9: =IF(#REF!<>"N/A",Priority!$C9,"") -> #REF! | I9: =IF(#REF!<>"N/A",Priority!$C9,"") -> #REF! | J9: =IF(#REF!<>"N/A",Priority!$C9,"") -> #REF! | K9: =IF(#REF!<>"N/A",Priority!$C9,"") -> #REF! | M9: =IF(#REF!<>"N/A",Priority!$C9,"") -> #REF! | N9: =IF(#REF!<>"N/A",Priority!$C9,"") -> #REF! | O9: =IF(#REF!<>"N/A",Priority!$C9,"") -> #REF! | P9: =IF(#REF!<>"N/A",Priority!$C9,"") -> #REF! | Q9: =IF(#REF!<>"N/A",Priority!$C9,"") -> #REF! | S9: =IF(#REF!<>"N/A",Priority!$C9,"") -> #REF! | T9: =IF(#REF!<>"N/A",Priority!$C9,"") -> #REF! | U9: =IF(#REF!<>"N/A",Priority!$C9,"") -> #REF! | V9: =IF(#REF!<>"N/A",Priority!$C9,"") -> #REF! | W9: =IF(#REF!<>"N/A",Priority!$C9,"") -> #REF! | X9: =IF(#REF!<>"N/A",Priority!$C9,"") -> #REF! | Z9: =IF(#REF!<>"N/A",Priority!$C9,"") -> #REF! | AA9: =IF(#REF!<>"N/A",Priority!$C9,"") -> #REF! | AB9: =IF(#REF!<>"N/A",Priority!$C9,"") -> #REF! | AC9: =IF(#REF!<>"N/A",Priority!$C9,"") -> #REF! | AD9: =IF(#REF!<>"N/A",Priority!$C9,"") -> #REF! | AE9: =IF(#REF!<>"N/A",Priority!$C9,"") -> #REF! | AF9: =IF(#REF!<>"N/A",Priority!$C9,"") -> #REF! | AG9: =IF(#REF!<>"N/A",Priority!$C9,"") -> #REF! | ... AI9: =IF(#REF!<>"N/A",Priority!$C9,"") -> #REF! | AK9: =IF(#REF!<>"N/A",Priority!$C9,"") -> #REF! | AL9: =IF(#REF!<>"N/A",Priority!$C9,"") -> #REF! | AM9: =IF(#REF!<>"N/A",Priority!$C9,"") -> #REF! | AN9: =IF(#REF!<>"N/A",Priority!$C9,"") -> #REF! | AO9: =IF(#REF!<>"N/A",Priority!$C9,"") -> #REF! | AP9: =IF(#REF!<>"N/A",Priority!$C9,"") -> #REF! | AQ9: =IF(#REF!<>"N/A",Priority!$C9,"") -> #REF! | AR9: =IF(#REF!<>"N/A",Priority!$C9,"") -> #REF! | ... AT9: =IF(#REF!<>"N/A",Priority!$C9,"") -> #REF! | AV9: =IF(#REF!<>"N/A",Priority!$C9,"") -> #REF! | AW9: =IF(#REF!<>"N/A",Priority!$C9,"") -> #REF! | AX9: =IF(#REF!<>"N/A",Priority!$C9,"") -> #REF! | AY9: =IF(#REF!<>"N/A",Priority!$C9,"") -> #REF! | AZ9: =IF(#REF!<>"N/A",Priority!$C9,"") -> #REF! | BA9: =IF(#REF!<>"N/A",Priority!$C9,"") -> #REF! | BB9: =IF(#REF!<>"N/A",Priority!$C9,"") -> #REF! | BD9: =IF(#REF!<>"N/A",Priority!$C9,"") -> #REF! | BE9: =IF(#REF!<>"N/A",Priority!$C9,"") -> #REF! | BF9: =IF(#REF!<>"N/A",Priority!$C9,"") -> #REF! | BG9: =IF(#REF!<>"N/A",Priority!$C9,"") -> #REF! | BH9: =IF(#REF!<>"N/A",Priority!$C9,"") -> #REF! | BI9: =IF(#REF!<>"N/A",Priority!$C9,"") -> #REF! | BJ9: =IF(#REF!<>"N/A",Priority!$C9,"") -> #REF! | BK9: =IF(#REF!<>"N/A",Priority!$C9,"") -> #REF! | BL9: =IF(#REF!<>"N/A",Priority!$C9,"") -> #REF! | BN9: =IF(#REF!<>"N/A",Priority!$C9,"") -> #REF! | BO9: =IF(#REF!<>"N/A",Priority!$C9,"") -> #REF! | BP9: =IF(#REF!<>"N/A",Priority!$C9,"") -> #REF! | BQ9: =IF(#REF!<>"N/A",Priority!$C9,"") -> #REF! | BR9: =IF(#REF!<>"N/A",Priority!$C9,"") -> #REF! | BS9: =IF(#REF!<>"N/A",Priority!$C9,"") -> #REF! | BT9: =IF(#REF!<>"N/A",Priority!$C9,"") -> #REF! | BV9: =IF(#REF!<>"N/A",Priority!$C9,"") -> #REF! | BW9: =IF(#REF!<>"N/A",Priority!$C9,"") -> #REF! | BX9: =IF(#REF!<>"N/A",Priority!$C9,"") -> #REF! | BY9: =IF(#REF!<>"N/A",Priority!$C9,"") -> #REF! | BZ9: =IF(#REF!<>"N/A",Priority!$C9,"") -> #REF! | CA9: =IF(#REF!<>"N/A",Priority!$C9,"") -> #REF! | CC9: =IF(#REF!<>"N/A",Priority!$C9,"") -> #REF! | CD9: =IF(#REF!<>"N/A",Priority!$C9,"") -> #REF! | CE9: =IF(#REF!<>"N/A",Priority!$C9,"") -> #REF! | CF9: =IF(#REF!<>"N/A",Priority!$C9,"") -> #REF!
A10: =#REF! -> #REF! | B10: =#REF! -> #REF! | C10: =#REF! -> #REF! | D10: TOOLS3 | E10: =IF(COUNTIFS(F10:CF10,"F")+COUNTIFS(F10:CF10,"NT")>0,"In Test",IF(COUNTIFS(F10:CF10,"P")+COUNTIFS(F10:CF10,"A")>0,"Pass","Pending")) -> Pending | F10: ="Pass: "& COUNTIFS(G10:CG10,"P")& " /Accept: "& COUNTIFS(G10:CG10,"A")& "/ Fail: "& COUNTIFS(G10:CG10,"Fail") & "/ NT: "& COUNTIFS(G10:CG10,"NT") -> Pass: 0 /Accept: 0/ Fail: 0/ NT: 0 | G10: =IF(#REF!<>"N/A",Priority!$C10,"") -> #REF! | H10: =IF(#REF!<>"N/A",Priority!$C10,"") -> #REF! | I10: =IF(#REF!<>"N/A",Priority!$C10,"") -> #REF! | J10: =IF(#REF!<>"N/A",Priority!$C10,"") -> #REF! | K10: =IF(#REF!<>"N/A",Priority!$C10,"") -> #REF! | M10: =IF(#REF!<>"N/A",Priority!$C10,"") -> #REF! | N10: =IF(#REF!<>"N/A",Priority!$C10,"") -> #REF! | O10: =IF(#REF!<>"N/A",Priority!$C10,"") -> #REF! | P10: =IF(#REF!<>"N/A",Priority!$C10,"") -> #REF! | Q10: =IF(#REF!<>"N/A",Priority!$C10,"") -> #REF! | S10: =IF(#REF!<>"N/A",Priority!$C10,"") -> #REF! | T10: =IF(#REF!<>"N/A",Priority!$C10,"") -> #REF! | U10: =IF(#REF!<>"N/A",Priority!$C10,"") -> #REF! | V10: =IF(#REF!<>"N/A",Priority!$C10,"") -> #REF! | W10: =IF(#REF!<>"N/A",Priority!$C10,"") -> #REF! | X10: =IF(#REF!<>"N/A",Priority!$C10,"") -> #REF! | Z10: =IF(#REF!<>"N/A",Priority!$C10,"") -> #REF! | AA10: =IF(#REF!<>"N/A",Priority!$C10,"") -> #REF! | AB10: =IF(#REF!<>"N/A",Priority!$C10,"") -> #REF! | AC10: =IF(#REF!<>"N/A",Priority!$C10,"") -> #REF! | AD10: =IF(#REF!<>"N/A",Priority!$C10,"") -> #REF! | AE10: =IF(#REF!<>"N/A",Priority!$C10,"") -> #REF! | AF10: =IF(#REF!<>"N/A",Priority!$C10,"") -> #REF! | AG10: =IF(#REF!<>"N/A",Priority!$C10,"") -> #REF! | ... AI10: =IF(#REF!<>"N/A",Priority!$C10,"") -> #REF! | AK10: =IF(#REF!<>"N/A",Priority!$C10,"") -> #REF! | AL10: =IF(#REF!<>"N/A",Priority!$C10,"") -> #REF! | AM10: =IF(#REF!<>"N/A",Priority!$C10,"") -> #REF! | AN10: =IF(#REF!<>"N/A",Priority!$C10,"") -> #REF! | AO10: =IF(#REF!<>"N/A",Priority!$C10,"") -> #REF! | AP10: =IF(#REF!<>"N/A",Priority!$C10,"") -> #REF! | AQ10: =IF(#REF!<>"N/A",Priority!$C10,"") -> #REF! | AR10: =IF(#REF!<>"N/A",Priority!$C10,"") -> #REF! | ... AT10: =IF(#REF!<>"N/A",Priority!$C10,"") -> #REF! | AV10: =IF(#REF!<>"N/A",Priority!$C10,"") -> #REF! | AW10: =IF(#REF!<>"N/A",Priority!$C10,"") -> #REF! | AX10: =IF(#REF!<>"N/A",Priority!$C10,"") -> #REF! | AY10: =IF(#REF!<>"N/A",Priority!$C10,"") -> #REF! | AZ10: =IF(#REF!<>"N/A",Priority!$C10,"") -> #REF! | BA10: =IF(#REF!<>"N/A",Priority!$C10,"") -> #REF! | BB10: =IF(#REF!<>"N/A",Priority!$C10,"") -> #REF! | BD10: =IF(#REF!<>"N/A",Priority!$C10,"") -> #REF! | BE10: =IF(#REF!<>"N/A",Priority!$C10,"") -> #REF! | BF10: =IF(#REF!<>"N/A",Priority!$C10,"") -> #REF! | BG10: =IF(#REF!<>"N/A",Priority!$C10,"") -> #REF! | BH10: =IF(#REF!<>"N/A",Priority!$C10,"") -> #REF! | BI10: =IF(#REF!<>"N/A",Priority!$C10,"") -> #REF! | BJ10: =IF(#REF!<>"N/A",Priority!$C10,"") -> #REF! | BK10: =IF(#REF!<>"N/A",Priority!$C10,"") -> #REF! | BL10: =IF(#REF!<>"N/A",Priority!$C10,"") -> #REF! | BN10: =IF(#REF!<>"N/A",Priority!$C10,"") -> #REF! | BO10: =IF(#REF!<>"N/A",Priority!$C10,"") -> #REF! | BP10: =IF(#REF!<>"N/A",Priority!$C10,"") -> #REF! | BQ10: =IF(#REF!<>"N/A",Priority!$C10,"") -> #REF! | BR10: =IF(#REF!<>"N/A",Priority!$C10,"") -> #REF! | BS10: =IF(#REF!<>"N/A",Priority!$C10,"") -> #REF! | BT10: =IF(#REF!<>"N/A",Priority!$C10,"") -> #REF! | BV10: =IF(#REF!<>"N/A",Priority!$C10,"") -> #REF! | BW10: =IF(#REF!<>"N/A",Priority!$C10,"") -> #REF! | BX10: =IF(#REF!<>"N/A",Priority!$C10,"") -> #REF! | BY10: =IF(#REF!<>"N/A",Priority!$C10,"") -> #REF! | BZ10: =IF(#REF!<>"N/A",Priority!$C10,"") -> #REF! | CA10: =IF(#REF!<>"N/A",Priority!$C10,"") -> #REF! | CC10: =IF(#REF!<>"N/A",Priority!$C10,"") -> #REF! | CD10: =IF(#REF!<>"N/A",Priority!$C10,"") -> #REF! | CE10: =IF(#REF!<>"N/A",Priority!$C10,"") -> #REF! | CF10: =IF(#REF!<>"N/A",Priority!$C10,"") -> #REF!
A11: =#REF! -> #REF! | B11: =#REF! -> #REF! | C11: =#REF! -> #REF! | D11: TOOLS1 | E11: =IF(COUNTIFS(F11:CF11,"F")+COUNTIFS(F11:CF11,"NT")>0,"In Test",IF(COUNTIFS(F11:CF11,"P")+COUNTIFS(F11:CF11,"A")>0,"Pass","Pending")) -> Pending | F11: ="Pass: "& COUNTIFS(G11:CG11,"P")& " /Accept: "& COUNTIFS(G11:CG11,"A")& "/ Fail: "& COUNTIFS(G11:CG11,"Fail") & "/ NT: "& COUNTIFS(G11:CG11,"NT") -> Pass: 0 /Accept: 0/ Fail: 0/ NT: 0 | G11: =IF(#REF!<>"N/A",Priority!$C11,"") -> #REF! | H11: =IF(#REF!<>"N/A",Priority!$C11,"") -> #REF! | I11: =IF(#REF!<>"N/A",Priority!$C11,"") -> #REF! | J11: =IF(#REF!<>"N/A",Priority!$C11,"") -> #REF! | K11: =IF(#REF!<>"N/A",Priority!$C11,"") -> #REF! | M11: =IF(#REF!<>"N/A",Priority!$C11,"") -> #REF! | N11: =IF(#REF!<>"N/A",Priority!$C11,"") -> #REF! | O11: =IF(#REF!<>"N/A",Priority!$C11,"") -> #REF! | P11: =IF(#REF!<>"N/A",Priority!$C11,"") -> #REF! | Q11: =IF(#REF!<>"N/A",Priority!$C11,"") -> #REF! | S11: =IF(#REF!<>"N/A",Priority!$C11,"") -> #REF! | T11: =IF(#REF!<>"N/A",Priority!$C11,"") -> #REF! | U11: =IF(#REF!<>"N/A",Priority!$C11,"") -> #REF! | V11: =IF(#REF!<>"N/A",Priority!$C11,"") -> #REF! | W11: =IF(#REF!<>"N/A",Priority!$C11,"") -> #REF! | X11: =IF(#REF!<>"N/A",Priority!$C11,"") -> #REF! | Z11: =IF(#REF!<>"N/A",Priority!$C11,"") -> #REF! | AA11: =IF(#REF!<>"N/A",Priority!$C11,"") -> #REF! | AB11: =IF(#REF!<>"N/A",Priority!$C11,"") -> #REF! | AC11: =IF(#REF!<>"N/A",Priority!$C11,"") -> #REF! | AD11: =IF(#REF!<>"N/A",Priority!$C11,"") -> #REF! | AE11: =IF(#REF!<>"N/A",Priority!$C11,"") -> #REF! | AF11: =IF(#REF!<>"N/A",Priority!$C11,"") -> #REF! | AG11: =IF(#REF!<>"N/A",Priority!$C11,"") -> #REF! | ... AI11: =IF(#REF!<>"N/A",Priority!$C11,"") -> #REF! | AK11: =IF(#REF!<>"N/A",Priority!$C11,"") -> #REF! | AL11: =IF(#REF!<>"N/A",Priority!$C11,"") -> #REF! | AM11: =IF(#REF!<>"N/A",Priority!$C11,"") -> #REF! | AN11: =IF(#REF!<>"N/A",Priority!$C11,"") -> #REF! | AO11: =IF(#REF!<>"N/A",Priority!$C11,"") -> #REF! | AP11: =IF(#REF!<>"N/A",Priority!$C11,"") -> #REF! | AQ11: =IF(#REF!<>"N/A",Priority!$C11,"") -> #REF! | AR11: =IF(#REF!<>"N/A",Priority!$C11,"") -> #REF! | ... AT11: =IF(#REF!<>"N/A",Priority!$C11,"") -> #REF! | AV11: =IF(#REF!<>"N/A",Priority!$C11,"") -> #REF! | AW11: =IF(#REF!<>"N/A",Priority!$C11,"") -> #REF! | AX11: =IF(#REF!<>"N/A",Priority!$C11,"") -> #REF! | AY11: =IF(#REF!<>"N/A",Priority!$C11,"") -> #REF! | AZ11: =IF(#REF!<>"N/A",Priority!$C11,"") -> #REF! | BA11: =IF(#REF!<>"N/A",Priority!$C11,"") -> #REF! | BB11: =IF(#REF!<>"N/A",Priority!$C11,"") -> #REF! | BD11: =IF(#REF!<>"N/A",Priority!$C11,"") -> #REF! | BE11: =IF(#REF!<>"N/A",Priority!$C11,"") -> #REF! | BF11: =IF(#REF!<>"N/A",Priority!$C11,"") -> #REF! | BG11: =IF(#REF!<>"N/A",Priority!$C11,"") -> #REF! | BH11: =IF(#REF!<>"N/A",Priority!$C11,"") -> #REF! | BI11: =IF(#REF!<>"N/A",Priority!$C11,"") -> #REF! | BJ11: =IF(#REF!<>"N/A",Priority!$C11,"") -> #REF! | BK11: =IF(#REF!<>"N/A",Priority!$C11,"") -> #REF! | BL11: =IF(#REF!<>"N/A",Priority!$C11,"") -> #REF! | BN11: =IF(#REF!<>"N/A",Priority!$C11,"") -> #REF! | BO11: =IF(#REF!<>"N/A",Priority!$C11,"") -> #REF! | BP11: =IF(#REF!<>"N/A",Priority!$C11,"") -> #REF! | BQ11: =IF(#REF!<>"N/A",Priority!$C11,"") -> #REF! | BR11: =IF(#REF!<>"N/A",Priority!$C11,"") -> #REF! | BS11: =IF(#REF!<>"N/A",Priority!$C11,"") -> #REF! | BT11: =IF(#REF!<>"N/A",Priority!$C11,"") -> #REF! | BV11: =IF(#REF!<>"N/A",Priority!$C11,"") -> #REF! | BW11: =IF(#REF!<>"N/A",Priority!$C11,"") -> #REF! | BX11: =IF(#REF!<>"N/A",Priority!$C11,"") -> #REF! | BY11: =IF(#REF!<>"N/A",Priority!$C11,"") -> #REF! | BZ11: =IF(#REF!<>"N/A",Priority!$C11,"") -> #REF! | CA11: =IF(#REF!<>"N/A",Priority!$C11,"") -> #REF! | CC11: =IF(#REF!<>"N/A",Priority!$C11,"") -> #REF! | CD11: =IF(#REF!<>"N/A",Priority!$C11,"") -> #REF! | CE11: =IF(#REF!<>"N/A",Priority!$C11,"") -> #REF! | CF11: =IF(#REF!<>"N/A",Priority!$C11,"") -> #REF!
A12: =#REF! -> #REF! | B12: =#REF! -> #REF! | C12: =#REF! -> #REF! | D12: TBD | E12: =IF(COUNTIFS(F12:CF12,"F")+COUNTIFS(F12:CF12,"NT")>0,"In Test",IF(COUNTIFS(F12:CF12,"P")+COUNTIFS(F12:CF12,"A")>0,"Pass","Pending")) -> Pending | F12: ="Pass: "& COUNTIFS(G12:CG12,"P")& " /Accept: "& COUNTIFS(G12:CG12,"A")& "/ Fail: "& COUNTIFS(G12:CG12,"Fail") & "/ NT: "& COUNTIFS(G12:CG12,"NT") -> Pass: 0 /Accept: 0/ Fail: 0/ NT: 0 | G12: =IF(#REF!<>"N/A",Priority!$C12,"") -> #REF! | H12: =IF(#REF!<>"N/A",Priority!$C12,"") -> #REF! | I12: =IF(#REF!<>"N/A",Priority!$C12,"") -> #REF! | J12: =IF(#REF!<>"N/A",Priority!$C12,"") -> #REF! | K12: =IF(#REF!<>"N/A",Priority!$C12,"") -> #REF! | M12: =IF(#REF!<>"N/A",Priority!$C12,"") -> #REF! | N12: =IF(#REF!<>"N/A",Priority!$C12,"") -> #REF! | O12: =IF(#REF!<>"N/A",Priority!$C12,"") -> #REF! | P12: =IF(#REF!<>"N/A",Priority!$C12,"") -> #REF! | Q12: =IF(#REF!<>"N/A",Priority!$C12,"") -> #REF! | S12: =IF(#REF!<>"N/A",Priority!$C12,"") -> #REF! | T12: =IF(#REF!<>"N/A",Priority!$C12,"") -> #REF! | U12: =IF(#REF!<>"N/A",Priority!$C12,"") -> #REF! | V12: =IF(#REF!<>"N/A",Priority!$C12,"") -> #REF! | W12: =IF(#REF!<>"N/A",Priority!$C12,"") -> #REF! | X12: =IF(#REF!<>"N/A",Priority!$C12,"") -> #REF! | Z12: =IF(#REF!<>"N/A",Priority!$C12,"") -> #REF! | AA12: =IF(#REF!<>"N/A",Priority!$C12,"") -> #REF! | AB12: =IF(#REF!<>"N/A",Priority!$C12,"") -> #REF! | AC12: =IF(#REF!<>"N/A",Priority!$C12,"") -> #REF! | AD12: =IF(#REF!<>"N/A",Priority!$C12,"") -> #REF! | AE12: =IF(#REF!<>"N/A",Priority!$C12,"") -> #REF! | AF12: =IF(#REF!<>"N/A",Priority!$C12,"") -> #REF! | AG12: =IF(#REF!<>"N/A",Priority!$C12,"") -> #REF! | ... AI12: =IF(#REF!<>"N/A",Priority!$C12,"") -> #REF! | AK12: N/A | AL12: N/A | AM12: N/A | AN12: N/A | AO12: N/A | AP12: N/A | AQ12: N/A | AR12: N/A | AS12: N/A | AT12: N/A | AV12: N/A | AW12: N/A | AX12: N/A | AY12: N/A | AZ12: N/A | BA12: N/A | BB12: N/A | BD12: N/A | BE12: N/A | BF12: N/A | BG12: N/A | BH12: N/A | BI12: N/A | BJ12: N/A | BK12: N/A | BL12: N/A | BN12: N/A | BO12: N/A | BP12: N/A | BQ12: N/A | BR12: N/A | BS12: N/A | BT12: N/A | BV12: N/A | BW12: N/A | BX12: N/A | BY12: N/A | BZ12: N/A | CA12: N/A | CC12: N/A | CD12: N/A | CE12: N/A | CF12: N/A
A13: =#REF! -> #REF!
A14: =#REF! -> #REF! | B14: =#REF! -> #REF! | C14: =#REF! -> #REF! | D14: RPT5 | E14: =IF(COUNTIFS(F14:CF14,"F")+COUNTIFS(F14:CF14,"NT")>0,"In Test",IF(COUNTIFS(F14:CF14,"P")+COUNTIFS(F14:CF14,"A")>0,"Pass","Pending")) -> Pending | F14: ="Pass: "& COUNTIFS(G14:CG14,"P")& " /Accept: "& COUNTIFS(G14:CG14,"A")& "/ Fail: "& COUNTIFS(G14:CG14,"Fail") & "/ NT: "& COUNTIFS(G14:CG14,"NT") -> Pass: 0 /Accept: 0/ Fail: 0/ NT: 0 | G14: =IF(#REF!<>"N/A",Priority!$C14,"") -> #REF! | H14: =IF(#REF!<>"N/A",Priority!$C14,"") -> #REF! | I14: =IF(#REF!<>"N/A",Priority!$C14,"") -> #REF! | J14: =IF(#REF!<>"N/A",Priority!$C14,"") -> #REF! | K14: =IF(#REF!<>"N/A",Priority!$C14,"") -> #REF! | M14: =IF(#REF!<>"N/A",Priority!$C14,"") -> #REF! | N14: =IF(#REF!<>"N/A",Priority!$C14,"") -> #REF! | O14: =IF(#REF!<>"N/A",Priority!$C14,"") -> #REF! | P14: =IF(#REF!<>"N/A",Priority!$C14,"") -> #REF! | Q14: =IF(#REF!<>"N/A",Priority!$C14,"") -> #REF! | S14: =IF(#REF!<>"N/A",Priority!$C14,"") -> #REF! | T14: =IF(#REF!<>"N/A",Priority!$C14,"") -> #REF! | U14: =IF(#REF!<>"N/A",Priority!$C14,"") -> #REF! | V14: =IF(#REF!<>"N/A",Priority!$C14,"") -> #REF! | W14: =IF(#REF!<>"N/A",Priority!$C14,"") -> #REF! | X14: =IF(#REF!<>"N/A",Priority!$C14,"") -> #REF! | Z14: =IF(#REF!<>"N/A",Priority!$C14,"") -> #REF! | AA14: =IF(#REF!<>"N/A",Priority!$C14,"") -> #REF! | AB14: =IF(#REF!<>"N/A",Priority!$C14,"") -> #REF! | AC14: =IF(#REF!<>"N/A",Priority!$C14,"") -> #REF! | AD14: =IF(#REF!<>"N/A",Priority!$C14,"") -> #REF! | AE14: =IF(#REF!<>"N/A",Priority!$C14,"") -> #REF! | AF14: =IF(#REF!<>"N/A",Priority!$C14,"") -> #REF! | AG14: =IF(#REF!<>"N/A",Priority!$C14,"") -> #REF! | ... AI14: =IF(#REF!<>"N/A",Priority!$C14,"") -> #REF! | AK14: =IF(#REF!<>"N/A",Priority!$C14,"") -> #REF! | AL14: =IF(#REF!<>"N/A",Priority!$C14,"") -> #REF! | AM14: =IF(#REF!<>"N/A",Priority!$C14,"") -> #REF! | AN14: =IF(#REF!<>"N/A",Priority!$C14,"") -> #REF! | AO14: =IF(#REF!<>"N/A",Priority!$C14,"") -> #REF! | AP14: =IF(#REF!<>"N/A",Priority!$C14,"") -> #REF! | AQ14: =IF(#REF!<>"N/A",Priority!$C14,"") -> #REF! | AR14: =IF(#REF!<>"N/A",Priority!$C14,"") -> #REF! | ... AT14: =IF(#REF!<>"N/A",Priority!$C14,"") -> #REF! | AV14: =IF(#REF!<>"N/A",Priority!$C14,"") -> #REF! | AW14: =IF(#REF!<>"N/A",Priority!$C14,"") -> #REF! | AX14: =IF(#REF!<>"N/A",Priority!$C14,"") -> #REF! | AY14: =IF(#REF!<>"N/A",Priority!$C14,"") -> #REF! | AZ14: =IF(#REF!<>"N/A",Priority!$C14,"") -> #REF! | BA14: =IF(#REF!<>"N/A",Priority!$C14,"") -> #REF! | BB14: =IF(#REF!<>"N/A",Priority!$C14,"") -> #REF! | BD14: =IF(#REF!<>"N/A",Priority!$C14,"") -> #REF! | BE14: =IF(#REF!<>"N/A",Priority!$C14,"") -> #REF! | BF14: =IF(#REF!<>"N/A",Priority!$C14,"") -> #REF! | BG14: =IF(#REF!<>"N/A",Priority!$C14,"") -> #REF! | BH14: =IF(#REF!<>"N/A",Priority!$C14,"") -> #REF! | BI14: =IF(#REF!<>"N/A",Priority!$C14,"") -> #REF! | BJ14: =IF(#REF!<>"N/A",Priority!$C14,"") -> #REF! | BK14: =IF(#REF!<>"N/A",Priority!$C14,"") -> #REF! | BL14: =IF(#REF!<>"N/A",Priority!$C14,"") -> #REF! | BN14: =IF(#REF!<>"N/A",Priority!$C14,"") -> #REF! | BO14: =IF(#REF!<>"N/A",Priority!$C14,"") -> #REF! | BP14: =IF(#REF!<>"N/A",Priority!$C14,"") -> #REF! | BQ14: =IF(#REF!<>"N/A",Priority!$C14,"") -> #REF! | BR14: =IF(#REF!<>"N/A",Priority!$C14,"") -> #REF! | BS14: =IF(#REF!<>"N/A",Priority!$C14,"") -> #REF! | BT14: =IF(#REF!<>"N/A",Priority!$C14,"") -> #REF! | BV14: =IF(#REF!<>"N/A",Priority!$C14,"") -> #REF! | BW14: =IF(#REF!<>"N/A",Priority!$C14,"") -> #REF! | BX14: =IF(#REF!<>"N/A",Priority!$C14,"") -> #REF! | BY14: =IF(#REF!<>"N/A",Priority!$C14,"") -> #REF! | BZ14: =IF(#REF!<>"N/A",Priority!$C14,"") -> #REF! | CA14: =IF(#REF!<>"N/A",Priority!$C14,"") -> #REF! | CC14: =IF(#REF!<>"N/A",Priority!$C14,"") -> #REF! | CD14: =IF(#REF!<>"N/A",Priority!$C14,"") -> #REF! | CE14: =IF(#REF!<>"N/A",Priority!$C14,"") -> #REF! | CF14: =IF(#REF!<>"N/A",Priority!$C14,"") -> #REF!
A15: =#REF! -> #REF! | B15: =#REF! -> #REF! | C15: =#REF! -> #REF! | D15: RPT5 | E15: =IF(COUNTIFS(F15:CF15,"F")+COUNTIFS(F15:CF15,"NT")>0,"In Test",IF(COUNTIFS(F15:CF15,"P")+COUNTIFS(F15:CF15,"A")>0,"Pass","Pending")) -> Pending | F15: ="Pass: "& COUNTIFS(G15:CG15,"P")& " /Accept: "& COUNTIFS(G15:CG15,"A")& "/ Fail: "& COUNTIFS(G15:CG15,"Fail") & "/ NT: "& COUNTIFS(G15:CG15,"NT") -> Pass: 0 /Accept: 0/ Fail: 0/ NT: 0 | G15: =IF(#REF!<>"N/A",Priority!$C15,"") -> #REF! | H15: =IF(#REF!<>"N/A",Priority!$C15,"") -> #REF! | I15: =IF(#REF!<>"N/A",Priority!$C15,"") -> #REF! | J15: =IF(#REF!<>"N/A",Priority!$C15,"") -> #REF! | K15: =IF(#REF!<>"N/A",Priority!$C15,"") -> #REF! | M15: =IF(#REF!<>"N/A",Priority!$C15,"") -> #REF! | N15: =IF(#REF!<>"N/A",Priority!$C15,"") -> #REF! | O15: =IF(#REF!<>"N/A",Priority!$C15,"") -> #REF! | P15: =IF(#REF!<>"N/A",Priority!$C15,"") -> #REF! | Q15: =IF(#REF!<>"N/A",Priority!$C15,"") -> #REF! | S15: =IF(#REF!<>"N/A",Priority!$C15,"") -> #REF! | T15: =IF(#REF!<>"N/A",Priority!$C15,"") -> #REF! | U15: =IF(#REF!<>"N/A",Priority!$C15,"") -> #REF! | V15: =IF(#REF!<>"N/A",Priority!$C15,"") -> #REF! | W15: =IF(#REF!<>"N/A",Priority!$C15,"") -> #REF! | X15: =IF(#REF!<>"N/A",Priority!$C15,"") -> #REF! | Z15: =IF(#REF!<>"N/A",Priority!$C15,"") -> #REF! | AA15: =IF(#REF!<>"N/A",Priority!$C15,"") -> #REF! | AB15: =IF(#REF!<>"N/A",Priority!$C15,"") -> #REF! | AC15: =IF(#REF!<>"N/A",Priority!$C15,"") -> #REF! | AD15: =IF(#REF!<>"N/A",Priority!$C15,"") -> #REF! | AE15: =IF(#REF!<>"N/A",Priority!$C15,"") -> #REF! | AF15: =IF(#REF!<>"N/A",Priority!$C15,"") -> #REF! | AG15: =IF(#REF!<>"N/A",Priority!$C15,"") -> #REF! | ... AI15: =IF(#REF!<>"N/A",Priority!$C15,"") -> #REF! | AK15: =IF(#REF!<>"N/A",Priority!$C15,"") -> #REF! | AL15: =IF(#REF!<>"N/A",Priority!$C15,"") -> #REF! | AM15: =IF(#REF!<>"N/A",Priority!$C15,"") -> #REF! | AN15: =IF(#REF!<>"N/A",Priority!$C15,"") -> #REF! | AO15: =IF(#REF!<>"N/A",Priority!$C15,"") -> #REF! | AP15: =IF(#REF!<>"N/A",Priority!$C15,"") -> #REF! | AQ15: =IF(#REF!<>"N/A",Priority!$C15,"") -> #REF! | AR15: =IF(#REF!<>"N/A",Priority!$C15,"") -> #REF! | ... AT15: =IF(#REF!<>"N/A",Priority!$C15,"") -> #REF! | AV15: =IF(#REF!<>"N/A",Priority!$C15,"") -> #REF! | AW15: =IF(#REF!<>"N/A",Priority!$C15,"") -> #REF! | AX15: =IF(#REF!<>"N/A",Priority!$C15,"") -> #REF! | AY15: =IF(#REF!<>"N/A",Priority!$C15,"") -> #REF! | AZ15: =IF(#REF!<>"N/A",Priority!$C15,"") -> #REF! | BA15: =IF(#REF!<>"N/A",Priority!$C15,"") -> #REF! | BB15: =IF(#REF!<>"N/A",Priority!$C15,"") -> #REF! | BD15: =IF(#REF!<>"N/A",Priority!$C15,"") -> #REF! | BE15: =IF(#REF!<>"N/A",Priority!$C15,"") -> #REF! | BF15: =IF(#REF!<>"N/A",Priority!$C15,"") -> #REF! | BG15: =IF(#REF!<>"N/A",Priority!$C15,"") -> #REF! | BH15: =IF(#REF!<>"N/A",Priority!$C15,"") -> #REF! | BI15: =IF(#REF!<>"N/A",Priority!$C15,"") -> #REF! | BJ15: =IF(#REF!<>"N/A",Priority!$C15,"") -> #REF! | BK15: =IF(#REF!<>"N/A",Priority!$C15,"") -> #REF! | BL15: =IF(#REF!<>"N/A",Priority!$C15,"") -> #REF! | BN15: =IF(#REF!<>"N/A",Priority!$C15,"") -> #REF! | BO15: =IF(#REF!<>"N/A",Priority!$C15,"") -> #REF! | BP15: =IF(#REF!<>"N/A",Priority!$C15,"") -> #REF! | BQ15: =IF(#REF!<>"N/A",Priority!$C15,"") -> #REF! | BR15: =IF(#REF!<>"N/A",Priority!$C15,"") -> #REF! | BS15: =IF(#REF!<>"N/A",Priority!$C15,"") -> #REF! | BT15: =IF(#REF!<>"N/A",Priority!$C15,"") -> #REF! | BV15: =IF(#REF!<>"N/A",Priority!$C15,"") -> #REF! | BW15: =IF(#REF!<>"N/A",Priority!$C15,"") -> #REF! | BX15: =IF(#REF!<>"N/A",Priority!$C15,"") -> #REF! | BY15: =IF(#REF!<>"N/A",Priority!$C15,"") -> #REF! | BZ15: =IF(#REF!<>"N/A",Priority!$C15,"") -> #REF! | CA15: =IF(#REF!<>"N/A",Priority!$C15,"") -> #REF! | CC15: =IF(#REF!<>"N/A",Priority!$C15,"") -> #REF! | CD15: =IF(#REF!<>"N/A",Priority!$C15,"") -> #REF! | CE15: =IF(#REF!<>"N/A",Priority!$C15,"") -> #REF! | CF15: =IF(#REF!<>"N/A",Priority!$C15,"") -> #REF!
A16: =#REF! -> #REF! | B16: =#REF! -> #REF! | C16: =#REF! -> #REF! | D16: RPT5 | E16: =IF(COUNTIFS(F16:CF16,"F")+COUNTIFS(F16:CF16,"NT")>0,"In Test",IF(COUNTIFS(F16:CF16,"P")+COUNTIFS(F16:CF16,"A")>0,"Pass","Pending")) -> Pending | F16: ="Pass: "& COUNTIFS(G16:CG16,"P")& " /Accept: "& COUNTIFS(G16:CG16,"A")& "/ Fail: "& COUNTIFS(G16:CG16,"Fail") & "/ NT: "& COUNTIFS(G16:CG16,"NT") -> Pass: 0 /Accept: 0/ Fail: 0/ NT: 0 | G16: =IF(#REF!<>"N/A",Priority!$C16,"") -> #REF! | H16: =IF(#REF!<>"N/A",Priority!$C16,"") -> #REF! | I16: =IF(#REF!<>"N/A",Priority!$C16,"") -> #REF! | J16: =IF(#REF!<>"N/A",Priority!$C16,"") -> #REF! | K16: =IF(#REF!<>"N/A",Priority!$C16,"") -> #REF! | M16: =IF(#REF!<>"N/A",Priority!$C16,"") -> #REF! | N16: =IF(#REF!<>"N/A",Priority!$C16,"") -> #REF! | O16: =IF(#REF!<>"N/A",Priority!$C16,"") -> #REF! | P16: =IF(#REF!<>"N/A",Priority!$C16,"") -> #REF! | Q16: =IF(#REF!<>"N/A",Priority!$C16,"") -> #REF! | S16: =IF(#REF!<>"N/A",Priority!$C16,"") -> #REF! | T16: =IF(#REF!<>"N/A",Priority!$C16,"") -> #REF! | U16: =IF(#REF!<>"N/A",Priority!$C16,"") -> #REF! | V16: =IF(#REF!<>"N/A",Priority!$C16,"") -> #REF! | W16: =IF(#REF!<>"N/A",Priority!$C16,"") -> #REF! | X16: =IF(#REF!<>"N/A",Priority!$C16,"") -> #REF! | Z16: =IF(#REF!<>"N/A",Priority!$C16,"") -> #REF! | AA16: =IF(#REF!<>"N/A",Priority!$C16,"") -> #REF! | AB16: =IF(#REF!<>"N/A",Priority!$C16,"") -> #REF! | AC16: =IF(#REF!<>"N/A",Priority!$C16,"") -> #REF! | AD16: =IF(#REF!<>"N/A",Priority!$C16,"") -> #REF! | AE16: =IF(#REF!<>"N/A",Priority!$C16,"") -> #REF! | AF16: =IF(#REF!<>"N/A",Priority!$C16,"") -> #REF! | AG16: =IF(#REF!<>"N/A",Priority!$C16,"") -> #REF! | ... AI16: =IF(#REF!<>"N/A",Priority!$C16,"") -> #REF! | AK16: =IF(#REF!<>"N/A",Priority!$C16,"") -> #REF! | AL16: =IF(#REF!<>"N/A",Priority!$C16,"") -> #REF! | AM16: =IF(#REF!<>"N/A",Priority!$C16,"") -> #REF! | AN16: =IF(#REF!<>"N/A",Priority!$C16,"") -> #REF! | AO16: =IF(#REF!<>"N/A",Priority!$C16,"") -> #REF! | AP16: =IF(#REF!<>"N/A",Priority!$C16,"") -> #REF! | AQ16: =IF(#REF!<>"N/A",Priority!$C16,"") -> #REF! | AR16: =IF(#REF!<>"N/A",Priority!$C16,"") -> #REF! | ... AT16: =IF(#REF!<>"N/A",Priority!$C16,"") -> #REF! | AV16: =IF(#REF!<>"N/A",Priority!$C16,"") -> #REF! | AW16: =IF(#REF!<>"N/A",Priority!$C16,"") -> #REF! | AX16: =IF(#REF!<>"N/A",Priority!$C16,"") -> #REF! | AY16: =IF(#REF!<>"N/A",Priority!$C16,"") -> #REF! | AZ16: =IF(#REF!<>"N/A",Priority!$C16,"") -> #REF! | BA16: =IF(#REF!<>"N/A",Priority!$C16,"") -> #REF! | BB16: =IF(#REF!<>"N/A",Priority!$C16,"") -> #REF! | BD16: =IF(#REF!<>"N/A",Priority!$C16,"") -> #REF! | BE16: =IF(#REF!<>"N/A",Priority!$C16,"") -> #REF! | BF16: =IF(#REF!<>"N/A",Priority!$C16,"") -> #REF! | BG16: =IF(#REF!<>"N/A",Priority!$C16,"") -> #REF! | BH16: =IF(#REF!<>"N/A",Priority!$C16,"") -> #REF! | BI16: =IF(#REF!<>"N/A",Priority!$C16,"") -> #REF! | BJ16: =IF(#REF!<>"N/A",Priority!$C16,"") -> #REF! | BK16: =IF(#REF!<>"N/A",Priority!$C16,"") -> #REF! | BL16: =IF(#REF!<>"N/A",Priority!$C16,"") -> #REF! | BN16: =IF(#REF!<>"N/A",Priority!$C16,"") -> #REF! | BO16: =IF(#REF!<>"N/A",Priority!$C16,"") -> #REF! | BP16: =IF(#REF!<>"N/A",Priority!$C16,"") -> #REF! | BQ16: =IF(#REF!<>"N/A",Priority!$C16,"") -> #REF! | BR16: =IF(#REF!<>"N/A",Priority!$C16,"") -> #REF! | BS16: =IF(#REF!<>"N/A",Priority!$C16,"") -> #REF! | BT16: =IF(#REF!<>"N/A",Priority!$C16,"") -> #REF! | BV16: =IF(#REF!<>"N/A",Priority!$C16,"") -> #REF! | BW16: =IF(#REF!<>"N/A",Priority!$C16,"") -> #REF! | BX16: =IF(#REF!<>"N/A",Priority!$C16,"") -> #REF! | BY16: =IF(#REF!<>"N/A",Priority!$C16,"") -> #REF! | BZ16: =IF(#REF!<>"N/A",Priority!$C16,"") -> #REF! | CA16: =IF(#REF!<>"N/A",Priority!$C16,"") -> #REF! | CC16: =IF(#REF!<>"N/A",Priority!$C16,"") -> #REF! | CD16: =IF(#REF!<>"N/A",Priority!$C16,"") -> #REF! | CE16: =IF(#REF!<>"N/A",Priority!$C16,"") -> #REF! | CF16: =IF(#REF!<>"N/A",Priority!$C16,"") -> #REF!
A17: =#REF! -> #REF! | B17: =#REF! -> #REF! | C17: =#REF! -> #REF! | D17: RPT5 | E17: =IF(COUNTIFS(F17:CF17,"F")+COUNTIFS(F17:CF17,"NT")>0,"In Test",IF(COUNTIFS(F17:CF17,"P")+COUNTIFS(F17:CF17,"A")>0,"Pass","Pending")) -> Pending | F17: ="Pass: "& COUNTIFS(G17:CG17,"P")& " /Accept: "& COUNTIFS(G17:CG17,"A")& "/ Fail: "& COUNTIFS(G17:CG17,"Fail") & "/ NT: "& COUNTIFS(G17:CG17,"NT") -> Pass: 0 /Accept: 0/ Fail: 0/ NT: 0 | G17: =IF(#REF!<>"N/A",Priority!$C17,"") -> #REF! | H17: =IF(#REF!<>"N/A",Priority!$C17,"") -> #REF! | I17: =IF(#REF!<>"N/A",Priority!$C17,"") -> #REF! | J17: =IF(#REF!<>"N/A",Priority!$C17,"") -> #REF! | K17: =IF(#REF!<>"N/A",Priority!$C17,"") -> #REF! | M17: =IF(#REF!<>"N/A",Priority!$C17,"") -> #REF! | N17: =IF(#REF!<>"N/A",Priority!$C17,"") -> #REF! | O17: =IF(#REF!<>"N/A",Priority!$C17,"") -> #REF! | P17: =IF(#REF!<>"N/A",Priority!$C17,"") -> #REF! | Q17: =IF(#REF!<>"N/A",Priority!$C17,"") -> #REF! | S17: =IF(#REF!<>"N/A",Priority!$C17,"") -> #REF! | T17: =IF(#REF!<>"N/A",Priority!$C17,"") -> #REF! | U17: =IF(#REF!<>"N/A",Priority!$C17,"") -> #REF! | V17: =IF(#REF!<>"N/A",Priority!$C17,"") -> #REF! | W17: =IF(#REF!<>"N/A",Priority!$C17,"") -> #REF! | X17: =IF(#REF!<>"N/A",Priority!$C17,"") -> #REF! | Z17: =IF(#REF!<>"N/A",Priority!$C17,"") -> #REF! | AA17: =IF(#REF!<>"N/A",Priority!$C17,"") -> #REF! | AB17: =IF(#REF!<>"N/A",Priority!$C17,"") -> #REF! | AC17: =IF(#REF!<>"N/A",Priority!$C17,"") -> #REF! | AD17: =IF(#REF!<>"N/A",Priority!$C17,"") -> #REF! | AE17: =IF(#REF!<>"N/A",Priority!$C17,"") -> #REF! | AF17: =IF(#REF!<>"N/A",Priority!$C17,"") -> #REF! | AG17: =IF(#REF!<>"N/A",Priority!$C17,"") -> #REF! | ... AI17: =IF(#REF!<>"N/A",Priority!$C17,"") -> #REF! | AK17: =IF(#REF!<>"N/A",Priority!$C17,"") -> #REF! | AL17: =IF(#REF!<>"N/A",Priority!$C17,"") -> #REF! | AM17: =IF(#REF!<>"N/A",Priority!$C17,"") -> #REF! | AN17: =IF(#REF!<>"N/A",Priority!$C17,"") -> #REF! | AO17: =IF(#REF!<>"N/A",Priority!$C17,"") -> #REF! | AP17: =IF(#REF!<>"N/A",Priority!$C17,"") -> #REF! | AQ17: =IF(#REF!<>"N/A",Priority!$C17,"") -> #REF! | AR17: =IF(#REF!<>"N/A",Priority!$C17,"") -> #REF! | ... AT17: =IF(#REF!<>"N/A",Priority!$C17,"") -> #REF! | AV17: =IF(#REF!<>"N/A",Priority!$C17,"") -> #REF! | AW17: =IF(#REF!<>"N/A",Priority!$C17,"") -> #REF! | AX17: =IF(#REF!<>"N/A",Priority!$C17,"") -> #REF! | AY17: =IF(#REF!<>"N/A",Priority!$C17,"") -> #REF! | AZ17: =IF(#REF!<>"N/A",Priority!$C17,"") -> #REF! | BA17: =IF(#REF!<>"N/A",Priority!$C17,"") -> #REF! | BB17: =IF(#REF!<>"N/A",Priority!$C17,"") -> #REF! | BD17: =IF(#REF!<>"N/A",Priority!$C17,"") -> #REF! | BE17: =IF(#REF!<>"N/A",Priority!$C17,"") -> #REF! | BF17: =IF(#REF!<>"N/A",Priority!$C17,"") -> #REF! | BG17: =IF(#REF!<>"N/A",Priority!$C17,"") -> #REF! | BH17: =IF(#REF!<>"N/A",Priority!$C17,"") -> #REF! | BI17: =IF(#REF!<>"N/A",Priority!$C17,"") -> #REF! | BJ17: =IF(#REF!<>"N/A",Priority!$C17,"") -> #REF! | BK17: =IF(#REF!<>"N/A",Priority!$C17,"") -> #REF! | BL17: =IF(#REF!<>"N/A",Priority!$C17,"") -> #REF! | BN17: =IF(#REF!<>"N/A",Priority!$C17,"") -> #REF! | BO17: =IF(#REF!<>"N/A",Priority!$C17,"") -> #REF! | BP17: =IF(#REF!<>"N/A",Priority!$C17,"") -> #REF! | BQ17: =IF(#REF!<>"N/A",Priority!$C17,"") -> #REF! | BR17: =IF(#REF!<>"N/A",Priority!$C17,"") -> #REF! | BS17: =IF(#REF!<>"N/A",Priority!$C17,"") -> #REF! | BT17: =IF(#REF!<>"N/A",Priority!$C17,"") -> #REF! | BV17: =IF(#REF!<>"N/A",Priority!$C17,"") -> #REF! | BW17: =IF(#REF!<>"N/A",Priority!$C17,"") -> #REF! | BX17: =IF(#REF!<>"N/A",Priority!$C17,"") -> #REF! | BY17: =IF(#REF!<>"N/A",Priority!$C17,"") -> #REF! | BZ17: =IF(#REF!<>"N/A",Priority!$C17,"") -> #REF! | CA17: =IF(#REF!<>"N/A",Priority!$C17,"") -> #REF! | CC17: =IF(#REF!<>"N/A",Priority!$C17,"") -> #REF! | CD17: =IF(#REF!<>"N/A",Priority!$C17,"") -> #REF! | CE17: =IF(#REF!<>"N/A",Priority!$C17,"") -> #REF! | CF17: =IF(#REF!<>"N/A",Priority!$C17,"") -> #REF!
A18: =#REF! -> #REF! | B18: =#REF! -> #REF! | C18: =#REF! -> #REF! | D18: RPT2 | E18: =IF(COUNTIFS(F18:CF18,"F")+COUNTIFS(F18:CF18,"NT")>0,"In Test",IF(COUNTIFS(F18:CF18,"P")+COUNTIFS(F18:CF18,"A")>0,"Pass","Pending")) -> Pending | F18: ="Pass: "& COUNTIFS(G18:CG18,"P")& " /Accept: "& COUNTIFS(G18:CG18,"A")& "/ Fail: "& COUNTIFS(G18:CG18,"Fail") & "/ NT: "& COUNTIFS(G18:CG18,"NT") -> Pass: 0 /Accept: 0/ Fail: 0/ NT: 0 | G18: =IF(#REF!<>"N/A",Priority!$C18,"") -> #REF! | H18: =IF(#REF!<>"N/A",Priority!$C18,"") -> #REF! | I18: =IF(#REF!<>"N/A",Priority!$C18,"") -> #REF! | J18: =IF(#REF!<>"N/A",Priority!$C18,"") -> #REF! | K18: =IF(#REF!<>"N/A",Priority!$C18,"") -> #REF! | M18: =IF(#REF!<>"N/A",Priority!$C18,"") -> #REF! | N18: =IF(#REF!<>"N/A",Priority!$C18,"") -> #REF! | O18: =IF(#REF!<>"N/A",Priority!$C18,"") -> #REF! | P18: =IF(#REF!<>"N/A",Priority!$C18,"") -> #REF! | Q18: =IF(#REF!<>"N/A",Priority!$C18,"") -> #REF! | S18: =IF(#REF!<>"N/A",Priority!$C18,"") -> #REF! | T18: =IF(#REF!<>"N/A",Priority!$C18,"") -> #REF! | U18: =IF(#REF!<>"N/A",Priority!$C18,"") -> #REF! | V18: =IF(#REF!<>"N/A",Priority!$C18,"") -> #REF! | W18: =IF(#REF!<>"N/A",Priority!$C18,"") -> #REF! | X18: =IF(#REF!<>"N/A",Priority!$C18,"") -> #REF! | Z18: =IF(#REF!<>"N/A",Priority!$C18,"") -> #REF! | AA18: =IF(#REF!<>"N/A",Priority!$C18,"") -> #REF! | AB18: =IF(#REF!<>"N/A",Priority!$C18,"") -> #REF! | AC18: =IF(#REF!<>"N/A",Priority!$C18,"") -> #REF! | AD18: =IF(#REF!<>"N/A",Priority!$C18,"") -> #REF! | AE18: =IF(#REF!<>"N/A",Priority!$C18,"") -> #REF! | AF18: =IF(#REF!<>"N/A",Priority!$C18,"") -> #REF! | AG18: =IF(#REF!<>"N/A",Priority!$C18,"") -> #REF! | ... AI18: =IF(#REF!<>"N/A",Priority!$C18,"") -> #REF! | AK18: =IF(#REF!<>"N/A",Priority!$C18,"") -> #REF! | AL18: =IF(#REF!<>"N/A",Priority!$C18,"") -> #REF! | AM18: =IF(#REF!<>"N/A",Priority!$C18,"") -> #REF! | AN18: =IF(#REF!<>"N/A",Priority!$C18,"") -> #REF! | AO18: =IF(#REF!<>"N/A",Priority!$C18,"") -> #REF! | AP18: =IF(#REF!<>"N/A",Priority!$C18,"") -> #REF! | AQ18: =IF(#REF!<>"N/A",Priority!$C18,"") -> #REF! | AR18: =IF(#REF!<>"N/A",Priority!$C18,"") -> #REF! | ... AT18: =IF(#REF!<>"N/A",Priority!$C18,"") -> #REF! | AV18: =IF(#REF!<>"N/A",Priority!$C18,"") -> #REF! | AW18: =IF(#REF!<>"N/A",Priority!$C18,"") -> #REF! | AX18: =IF(#REF!<>"N/A",Priority!$C18,"") -> #REF! | AY18: =IF(#REF!<>"N/A",Priority!$C18,"") -> #REF! | AZ18: =IF(#REF!<>"N/A",Priority!$C18,"") -> #REF! | BA18: =IF(#REF!<>"N/A",Priority!$C18,"") -> #REF! | BB18: =IF(#REF!<>"N/A",Priority!$C18,"") -> #REF! | BD18: =IF(#REF!<>"N/A",Priority!$C18,"") -> #REF! | BE18: =IF(#REF!<>"N/A",Priority!$C18,"") -> #REF! | BF18: =IF(#REF!<>"N/A",Priority!$C18,"") -> #REF! | BG18: =IF(#REF!<>"N/A",Priority!$C18,"") -> #REF! | BH18: =IF(#REF!<>"N/A",Priority!$C18,"") -> #REF! | BI18: =IF(#REF!<>"N/A",Priority!$C18,"") -> #REF! | BJ18: =IF(#REF!<>"N/A",Priority!$C18,"") -> #REF! | BK18: =IF(#REF!<>"N/A",Priority!$C18,"") -> #REF! | BL18: =IF(#REF!<>"N/A",Priority!$C18,"") -> #REF! | BN18: =IF(#REF!<>"N/A",Priority!$C18,"") -> #REF! | BO18: =IF(#REF!<>"N/A",Priority!$C18,"") -> #REF! | BP18: =IF(#REF!<>"N/A",Priority!$C18,"") -> #REF! | BQ18: =IF(#REF!<>"N/A",Priority!$C18,"") -> #REF! | BR18: =IF(#REF!<>"N/A",Priority!$C18,"") -> #REF! | BS18: =IF(#REF!<>"N/A",Priority!$C18,"") -> #REF! | BT18: =IF(#REF!<>"N/A",Priority!$C18,"") -> #REF! | BV18: =IF(#REF!<>"N/A",Priority!$C18,"") -> #REF! | BW18: =IF(#REF!<>"N/A",Priority!$C18,"") -> #REF! | BX18: =IF(#REF!<>"N/A",Priority!$C18,"") -> #REF! | BY18: =IF(#REF!<>"N/A",Priority!$C18,"") -> #REF! | BZ18: =IF(#REF!<>"N/A",Priority!$C18,"") -> #REF! | CA18: =IF(#REF!<>"N/A",Priority!$C18,"") -> #REF! | CC18: =IF(#REF!<>"N/A",Priority!$C18,"") -> #REF! | CD18: =IF(#REF!<>"N/A",Priority!$C18,"") -> #REF! | CE18: =IF(#REF!<>"N/A",Priority!$C18,"") -> #REF! | CF18: =IF(#REF!<>"N/A",Priority!$C18,"") -> #REF!
A19: =#REF! -> #REF! | B19: =#REF! -> #REF! | C19: =#REF! -> #REF! | D19: RPT3 | E19: =IF(COUNTIFS(F19:CF19,"F")+COUNTIFS(F19:CF19,"NT")>0,"In Test",IF(COUNTIFS(F19:CF19,"P")+COUNTIFS(F19:CF19,"A")>0,"Pass","Pending")) -> Pending | F19: ="Pass: "& COUNTIFS(G19:CG19,"P")& " /Accept: "& COUNTIFS(G19:CG19,"A")& "/ Fail: "& COUNTIFS(G19:CG19,"Fail") & "/ NT: "& COUNTIFS(G19:CG19,"NT") -> Pass: 0 /Accept: 0/ Fail: 0/ NT: 0 | G19: =IF(#REF!<>"N/A",Priority!$C19,"") -> #REF! | H19: =IF(#REF!<>"N/A",Priority!$C19,"") -> #REF! | I19: =IF(#REF!<>"N/A",Priority!$C19,"") -> #REF! | J19: =IF(#REF!<>"N/A",Priority!$C19,"") -> #REF! | K19: =IF(#REF!<>"N/A",Priority!$C19,"") -> #REF! | M19: =IF(#REF!<>"N/A",Priority!$C19,"") -> #REF! | N19: =IF(#REF!<>"N/A",Priority!$C19,"") -> #REF! | O19: =IF(#REF!<>"N/A",Priority!$C19,"") -> #REF! | P19: =IF(#REF!<>"N/A",Priority!$C19,"") -> #REF! | Q19: =IF(#REF!<>"N/A",Priority!$C19,"") -> #REF! | S19: =IF(#REF!<>"N/A",Priority!$C19,"") -> #REF! | T19: =IF(#REF!<>"N/A",Priority!$C19,"") -> #REF! | U19: =IF(#REF!<>"N/A",Priority!$C19,"") -> #REF! | V19: =IF(#REF!<>"N/A",Priority!$C19,"") -> #REF! | W19: =IF(#REF!<>"N/A",Priority!$C19,"") -> #REF! | X19: =IF(#REF!<>"N/A",Priority!$C19,"") -> #REF! | Z19: =IF(#REF!<>"N/A",Priority!$C19,"") -> #REF! | AA19: =IF(#REF!<>"N/A",Priority!$C19,"") -> #REF! | AB19: =IF(#REF!<>"N/A",Priority!$C19,"") -> #REF! | AC19: =IF(#REF!<>"N/A",Priority!$C19,"") -> #REF! | AD19: =IF(#REF!<>"N/A",Priority!$C19,"") -> #REF! | AE19: =IF(#REF!<>"N/A",Priority!$C19,"") -> #REF! | AF19: =IF(#REF!<>"N/A",Priority!$C19,"") -> #REF! | AG19: =IF(#REF!<>"N/A",Priority!$C19,"") -> #REF! | ... AI19: =IF(#REF!<>"N/A",Priority!$C19,"") -> #REF! | AK19: =IF(#REF!<>"N/A",Priority!$C19,"") -> #REF! | AL19: =IF(#REF!<>"N/A",Priority!$C19,"") -> #REF! | AM19: =IF(#REF!<>"N/A",Priority!$C19,"") -> #REF! | AN19: =IF(#REF!<>"N/A",Priority!$C19,"") -> #REF! | AO19: =IF(#REF!<>"N/A",Priority!$C19,"") -> #REF! | AP19: =IF(#REF!<>"N/A",Priority!$C19,"") -> #REF! | AQ19: =IF(#REF!<>"N/A",Priority!$C19,"") -> #REF! | AR19: =IF(#REF!<>"N/A",Priority!$C19,"") -> #REF! | ... AT19: =IF(#REF!<>"N/A",Priority!$C19,"") -> #REF! | AV19: =IF(#REF!<>"N/A",Priority!$C19,"") -> #REF! | AW19: =IF(#REF!<>"N/A",Priority!$C19,"") -> #REF! | AX19: =IF(#REF!<>"N/A",Priority!$C19,"") -> #REF! | AY19: =IF(#REF!<>"N/A",Priority!$C19,"") -> #REF! | AZ19: =IF(#REF!<>"N/A",Priority!$C19,"") -> #REF! | BA19: =IF(#REF!<>"N/A",Priority!$C19,"") -> #REF! | BB19: =IF(#REF!<>"N/A",Priority!$C19,"") -> #REF! | BD19: =IF(#REF!<>"N/A",Priority!$C19,"") -> #REF! | BE19: =IF(#REF!<>"N/A",Priority!$C19,"") -> #REF! | BF19: =IF(#REF!<>"N/A",Priority!$C19,"") -> #REF! | BG19: =IF(#REF!<>"N/A",Priority!$C19,"") -> #REF! | BH19: =IF(#REF!<>"N/A",Priority!$C19,"") -> #REF! | BI19: =IF(#REF!<>"N/A",Priority!$C19,"") -> #REF! | BJ19: =IF(#REF!<>"N/A",Priority!$C19,"") -> #REF! | BK19: =IF(#REF!<>"N/A",Priority!$C19,"") -> #REF! | BL19: =IF(#REF!<>"N/A",Priority!$C19,"") -> #REF! | BN19: =IF(#REF!<>"N/A",Priority!$C19,"") -> #REF! | BO19: =IF(#REF!<>"N/A",Priority!$C19,"") -> #REF! | BP19: =IF(#REF!<>"N/A",Priority!$C19,"") -> #REF! | BQ19: =IF(#REF!<>"N/A",Priority!$C19,"") -> #REF! | BR19: =IF(#REF!<>"N/A",Priority!$C19,"") -> #REF! | BS19: =IF(#REF!<>"N/A",Priority!$C19,"") -> #REF! | BT19: =IF(#REF!<>"N/A",Priority!$C19,"") -> #REF! | BV19: =IF(#REF!<>"N/A",Priority!$C19,"") -> #REF! | BW19: =IF(#REF!<>"N/A",Priority!$C19,"") -> #REF! | BX19: =IF(#REF!<>"N/A",Priority!$C19,"") -> #REF! | BY19: =IF(#REF!<>"N/A",Priority!$C19,"") -> #REF! | BZ19: =IF(#REF!<>"N/A",Priority!$C19,"") -> #REF! | CA19: =IF(#REF!<>"N/A",Priority!$C19,"") -> #REF! | CC19: =IF(#REF!<>"N/A",Priority!$C19,"") -> #REF! | CD19: =IF(#REF!<>"N/A",Priority!$C19,"") -> #REF! | CE19: =IF(#REF!<>"N/A",Priority!$C19,"") -> #REF! | CF19: =IF(#REF!<>"N/A",Priority!$C19,"") -> #REF!
A20: =#REF! -> #REF!
A21: =#REF! -> #REF! | B21: =#REF! -> #REF! | C21: =#REF! -> #REF! | D21: TOOLS5 | E21: =IF(COUNTIFS(F21:CF21,"F")+COUNTIFS(F21:CF21,"NT")>0,"In Test",IF(COUNTIFS(F21:CF21,"P")+COUNTIFS(F21:CF21,"A")>0,"Pass","Pending")) -> Pending | F21: ="Pass: "& COUNTIFS(G21:CG21,"P")& " /Accept: "& COUNTIFS(G21:CG21,"A")& "/ Fail: "& COUNTIFS(G21:CG21,"Fail") & "/ NT: "& COUNTIFS(G21:CG21,"NT") -> Pass: 0 /Accept: 0/ Fail: 0/ NT: 0 | G21: =IF(#REF!<>"N/A",Priority!$C21,"") -> #REF! | H21: =IF(#REF!<>"N/A",Priority!$C21,"") -> #REF! | I21: =IF(#REF!<>"N/A",Priority!$C21,"") -> #REF! | J21: =IF(#REF!<>"N/A",Priority!$C21,"") -> #REF! | K21: =IF(#REF!<>"N/A",Priority!$C21,"") -> #REF! | M21: =IF(#REF!<>"N/A",Priority!$C21,"") -> #REF! | N21: =IF(#REF!<>"N/A",Priority!$C21,"") -> #REF! | O21: =IF(#REF!<>"N/A",Priority!$C21,"") -> #REF! | P21: =IF(#REF!<>"N/A",Priority!$C21,"") -> #REF! | Q21: =IF(#REF!<>"N/A",Priority!$C21,"") -> #REF! | S21: =IF(#REF!<>"N/A",Priority!$C21,"") -> #REF! | T21: =IF(#REF!<>"N/A",Priority!$C21,"") -> #REF! | U21: =IF(#REF!<>"N/A",Priority!$C21,"") -> #REF! | V21: =IF(#REF!<>"N/A",Priority!$C21,"") -> #REF! | W21: =IF(#REF!<>"N/A",Priority!$C21,"") -> #REF! | X21: =IF(#REF!<>"N/A",Priority!$C21,"") -> #REF! | Z21: =IF(#REF!<>"N/A",Priority!$C21,"") -> #REF! | AA21: =IF(#REF!<>"N/A",Priority!$C21,"") -> #REF! | AB21: =IF(#REF!<>"N/A",Priority!$C21,"") -> #REF! | AC21: =IF(#REF!<>"N/A",Priority!$C21,"") -> #REF! | AD21: =IF(#REF!<>"N/A",Priority!$C21,"") -> #REF! | AE21: =IF(#REF!<>"N/A",Priority!$C21,"") -> #REF! | AF21: =IF(#REF!<>"N/A",Priority!$C21,"") -> #REF! | AG21: =IF(#REF!<>"N/A",Priority!$C21,"") -> #REF! | ... AI21: =IF(#REF!<>"N/A",Priority!$C21,"") -> #REF! | AK21: =IF(#REF!<>"N/A",Priority!$C21,"") -> #REF! | AL21: =IF(#REF!<>"N/A",Priority!$C21,"") -> #REF! | AM21: =IF(#REF!<>"N/A",Priority!$C21,"") -> #REF! | AN21: =IF(#REF!<>"N/A",Priority!$C21,"") -> #REF! | AO21: =IF(#REF!<>"N/A",Priority!$C21,"") -> #REF! | AP21: =IF(#REF!<>"N/A",Priority!$C21,"") -> #REF! | AQ21: =IF(#REF!<>"N/A",Priority!$C21,"") -> #REF! | AR21: =IF(#REF!<>"N/A",Priority!$C21,"") -> #REF! | ... AT21: =IF(#REF!<>"N/A",Priority!$C21,"") -> #REF! | AV21: =IF(#REF!<>"N/A",Priority!$C21,"") -> #REF! | AW21: =IF(#REF!<>"N/A",Priority!$C21,"") -> #REF! | AX21: =IF(#REF!<>"N/A",Priority!$C21,"") -> #REF! | AY21: =IF(#REF!<>"N/A",Priority!$C21,"") -> #REF! | AZ21: =IF(#REF!<>"N/A",Priority!$C21,"") -> #REF! | BA21: =IF(#REF!<>"N/A",Priority!$C21,"") -> #REF! | BB21: =IF(#REF!<>"N/A",Priority!$C21,"") -> #REF! | BD21: =IF(#REF!<>"N/A",Priority!$C21,"") -> #REF! | BE21: =IF(#REF!<>"N/A",Priority!$C21,"") -> #REF! | BF21: =IF(#REF!<>"N/A",Priority!$C21,"") -> #REF! | BG21: =IF(#REF!<>"N/A",Priority!$C21,"") -> #REF! | BH21: =IF(#REF!<>"N/A",Priority!$C21,"") -> #REF! | BI21: =IF(#REF!<>"N/A",Priority!$C21,"") -> #REF! | BJ21: =IF(#REF!<>"N/A",Priority!$C21,"") -> #REF! | BK21: =IF(#REF!<>"N/A",Priority!$C21,"") -> #REF! | BL21: =IF(#REF!<>"N/A",Priority!$C21,"") -> #REF! | BN21: =IF(#REF!<>"N/A",Priority!$C21,"") -> #REF! | BO21: =IF(#REF!<>"N/A",Priority!$C21,"") -> #REF! | BP21: =IF(#REF!<>"N/A",Priority!$C21,"") -> #REF! | BQ21: =IF(#REF!<>"N/A",Priority!$C21,"") -> #REF! | BR21: =IF(#REF!<>"N/A",Priority!$C21,"") -> #REF! | BS21: =IF(#REF!<>"N/A",Priority!$C21,"") -> #REF! | BT21: =IF(#REF!<>"N/A",Priority!$C21,"") -> #REF! | BV21: =IF(#REF!<>"N/A",Priority!$C21,"") -> #REF! | BW21: =IF(#REF!<>"N/A",Priority!$C21,"") -> #REF! | BX21: =IF(#REF!<>"N/A",Priority!$C21,"") -> #REF! | BY21: =IF(#REF!<>"N/A",Priority!$C21,"") -> #REF! | BZ21: =IF(#REF!<>"N/A",Priority!$C21,"") -> #REF! | CA21: =IF(#REF!<>"N/A",Priority!$C21,"") -> #REF! | CC21: =IF(#REF!<>"N/A",Priority!$C21,"") -> #REF! | CD21: =IF(#REF!<>"N/A",Priority!$C21,"") -> #REF! | CE21: =IF(#REF!<>"N/A",Priority!$C21,"") -> #REF! | CF21: =IF(#REF!<>"N/A",Priority!$C21,"") -> #REF!
A22: =#REF! -> #REF! | B22: =#REF! -> #REF! | C22: =#REF! -> #REF! | D22: RQMT1 | E22: =IF(COUNTIFS(F22:CF22,"F")+COUNTIFS(F22:CF22,"NT")>0,"In Test",IF(COUNTIFS(F22:CF22,"P")+COUNTIFS(F22:CF22,"A")>0,"Pass","Pending")) -> Pending | F22: ="Pass: "& COUNTIFS(G22:CG22,"P")& " /Accept: "& COUNTIFS(G22:CG22,"A")& "/ Fail: "& COUNTIFS(G22:CG22,"Fail") & "/ NT: "& COUNTIFS(G22:CG22,"NT") -> Pass: 0 /Accept: 0/ Fail: 0/ NT: 0 | G22: =IF(#REF!<>"N/A",Priority!$C22,"") -> #REF! | H22: =IF(#REF!<>"N/A",Priority!$C22,"") -> #REF! | I22: =IF(#REF!<>"N/A",Priority!$C22,"") -> #REF! | J22: =IF(#REF!<>"N/A",Priority!$C22,"") -> #REF! | K22: =IF(#REF!<>"N/A",Priority!$C22,"") -> #REF! | M22: =IF(#REF!<>"N/A",Priority!$C22,"") -> #REF! | N22: =IF(#REF!<>"N/A",Priority!$C22,"") -> #REF! | O22: =IF(#REF!<>"N/A",Priority!$C22,"") -> #REF! | P22: =IF(#REF!<>"N/A",Priority!$C22,"") -> #REF! | Q22: =IF(#REF!<>"N/A",Priority!$C22,"") -> #REF! | S22: =IF(#REF!<>"N/A",Priority!$C22,"") -> #REF! | T22: =IF(#REF!<>"N/A",Priority!$C22,"") -> #REF! | U22: =IF(#REF!<>"N/A",Priority!$C22,"") -> #REF! | V22: =IF(#REF!<>"N/A",Priority!$C22,"") -> #REF! | W22: =IF(#REF!<>"N/A",Priority!$C22,"") -> #REF! | X22: =IF(#REF!<>"N/A",Priority!$C22,"") -> #REF! | Z22: =IF(#REF!<>"N/A",Priority!$C22,"") -> #REF! | AA22: =IF(#REF!<>"N/A",Priority!$C22,"") -> #REF! | AB22: =IF(#REF!<>"N/A",Priority!$C22,"") -> #REF! | AC22: =IF(#REF!<>"N/A",Priority!$C22,"") -> #REF! | AD22: =IF(#REF!<>"N/A",Priority!$C22,"") -> #REF! | AE22: =IF(#REF!<>"N/A",Priority!$C22,"") -> #REF! | AF22: =IF(#REF!<>"N/A",Priority!$C22,"") -> #REF! | AG22: =IF(#REF!<>"N/A",Priority!$C22,"") -> #REF! | ... AI22: =IF(#REF!<>"N/A",Priority!$C22,"") -> #REF! | AK22: =IF(#REF!<>"N/A",Priority!$C22,"") -> #REF! | AL22: =IF(#REF!<>"N/A",Priority!$C22,"") -> #REF! | AM22: =IF(#REF!<>"N/A",Priority!$C22,"") -> #REF! | AN22: =IF(#REF!<>"N/A",Priority!$C22,"") -> #REF! | AO22: =IF(#REF!<>"N/A",Priority!$C22,"") -> #REF! | AP22: =IF(#REF!<>"N/A",Priority!$C22,"") -> #REF! | AQ22: =IF(#REF!<>"N/A",Priority!$C22,"") -> #REF! | AR22: =IF(#REF!<>"N/A",Priority!$C22,"") -> #REF! | ... AT22: =IF(#REF!<>"N/A",Priority!$C22,"") -> #REF! | AV22: =IF(#REF!<>"N/A",Priority!$C22,"") -> #REF! | AW22: =IF(#REF!<>"N/A",Priority!$C22,"") -> #REF! | AX22: =IF(#REF!<>"N/A",Priority!$C22,"") -> #REF! | AY22: =IF(#REF!<>"N/A",Priority!$C22,"") -> #REF! | AZ22: =IF(#REF!<>"N/A",Priority!$C22,"") -> #REF! | BA22: =IF(#REF!<>"N/A",Priority!$C22,"") -> #REF! | BB22: =IF(#REF!<>"N/A",Priority!$C22,"") -> #REF! | BD22: =IF(#REF!<>"N/A",Priority!$C22,"") -> #REF! | BE22: =IF(#REF!<>"N/A",Priority!$C22,"") -> #REF! | BF22: =IF(#REF!<>"N/A",Priority!$C22,"") -> #REF! | BG22: =IF(#REF!<>"N/A",Priority!$C22,"") -> #REF! | BH22: =IF(#REF!<>"N/A",Priority!$C22,"") -> #REF! | BI22: =IF(#REF!<>"N/A",Priority!$C22,"") -> #REF! | BJ22: =IF(#REF!<>"N/A",Priority!$C22,"") -> #REF! | BK22: =IF(#REF!<>"N/A",Priority!$C22,"") -> #REF! | BL22: =IF(#REF!<>"N/A",Priority!$C22,"") -> #REF! | BN22: =IF(#REF!<>"N/A",Priority!$C22,"") -> #REF! | BO22: =IF(#REF!<>"N/A",Priority!$C22,"") -> #REF! | BP22: =IF(#REF!<>"N/A",Priority!$C22,"") -> #REF! | BQ22: =IF(#REF!<>"N/A",Priority!$C22,"") -> #REF! | BR22: =IF(#REF!<>"N/A",Priority!$C22,"") -> #REF! | BS22: =IF(#REF!<>"N/A",Priority!$C22,"") -> #REF! | BT22: =IF(#REF!<>"N/A",Priority!$C22,"") -> #REF! | BV22: =IF(#REF!<>"N/A",Priority!$C22,"") -> #REF! | BW22: =IF(#REF!<>"N/A",Priority!$C22,"") -> #REF! | BX22: =IF(#REF!<>"N/A",Priority!$C22,"") -> #REF! | BY22: =IF(#REF!<>"N/A",Priority!$C22,"") -> #REF! | BZ22: =IF(#REF!<>"N/A",Priority!$C22,"") -> #REF! | CA22: =IF(#REF!<>"N/A",Priority!$C22,"") -> #REF! | CC22: =IF(#REF!<>"N/A",Priority!$C22,"") -> #REF! | CD22: =IF(#REF!<>"N/A",Priority!$C22,"") -> #REF! | CE22: =IF(#REF!<>"N/A",Priority!$C22,"") -> #REF! | CF22: =IF(#REF!<>"N/A",Priority!$C22,"") -> #REF!
A23: =#REF! -> #REF! | B23: =#REF! -> #REF! | C23: =#REF! -> #REF! | D23: TOOLS5 | E23: =IF(COUNTIFS(F23:CF23,"F")+COUNTIFS(F23:CF23,"NT")>0,"In Test",IF(COUNTIFS(F23:CF23,"P")+COUNTIFS(F23:CF23,"A")>0,"Pass","Pending")) -> Pending | F23: ="Pass: "& COUNTIFS(G23:CG23,"P")& " /Accept: "& COUNTIFS(G23:CG23,"A")& "/ Fail: "& COUNTIFS(G23:CG23,"Fail") & "/ NT: "& COUNTIFS(G23:CG23,"NT") -> Pass: 0 /Accept: 0/ Fail: 0/ NT: 0 | G23: =IF(#REF!<>"N/A",Priority!$C23,"") -> #REF! | H23: =IF(#REF!<>"N/A",Priority!$C23,"") -> #REF! | I23: =IF(#REF!<>"N/A",Priority!$C23,"") -> #REF! | J23: =IF(#REF!<>"N/A",Priority!$C23,"") -> #REF! | K23: =IF(#REF!<>"N/A",Priority!$C23,"") -> #REF! | M23: =IF(#REF!<>"N/A",Priority!$C23,"") -> #REF! | N23: =IF(#REF!<>"N/A",Priority!$C23,"") -> #REF! | O23: =IF(#REF!<>"N/A",Priority!$C23,"") -> #REF! | P23: =IF(#REF!<>"N/A",Priority!$C23,"") -> #REF! | Q23: =IF(#REF!<>"N/A",Priority!$C23,"") -> #REF! | S23: =IF(#REF!<>"N/A",Priority!$C23,"") -> #REF! | T23: =IF(#REF!<>"N/A",Priority!$C23,"") -> #REF! | U23: =IF(#REF!<>"N/A",Priority!$C23,"") -> #REF! | V23: =IF(#REF!<>"N/A",Priority!$C23,"") -> #REF! | W23: =IF(#REF!<>"N/A",Priority!$C23,"") -> #REF! | X23: =IF(#REF!<>"N/A",Priority!$C23,"") -> #REF! | Z23: =IF(#REF!<>"N/A",Priority!$C23,"") -> #REF! | AA23: =IF(#REF!<>"N/A",Priority!$C23,"") -> #REF! | AB23: =IF(#REF!<>"N/A",Priority!$C23,"") -> #REF! | AC23: =IF(#REF!<>"N/A",Priority!$C23,"") -> #REF! | AD23: =IF(#REF!<>"N/A",Priority!$C23,"") -> #REF! | AE23: =IF(#REF!<>"N/A",Priority!$C23,"") -> #REF! | AF23: =IF(#REF!<>"N/A",Priority!$C23,"") -> #REF! | AG23: =IF(#REF!<>"N/A",Priority!$C23,"") -> #REF! | ... AI23: =IF(#REF!<>"N/A",Priority!$C23,"") -> #REF! | AK23: =IF(#REF!<>"N/A",Priority!$C23,"") -> #REF! | AL23: =IF(#REF!<>"N/A",Priority!$C23,"") -> #REF! | AM23: =IF(#REF!<>"N/A",Priority!$C23,"") -> #REF! | AN23: =IF(#REF!<>"N/A",Priority!$C23,"") -> #REF! | AO23: =IF(#REF!<>"N/A",Priority!$C23,"") -> #REF! | AP23: =IF(#REF!<>"N/A",Priority!$C23,"") -> #REF! | AQ23: =IF(#REF!<>"N/A",Priority!$C23,"") -> #REF! | AR23: =IF(#REF!<>"N/A",Priority!$C23,"") -> #REF! | ... AT23: =IF(#REF!<>"N/A",Priority!$C23,"") -> #REF! | AV23: =IF(#REF!<>"N/A",Priority!$C23,"") -> #REF! | AW23: =IF(#REF!<>"N/A",Priority!$C23,"") -> #REF! | AX23: =IF(#REF!<>"N/A",Priority!$C23,"") -> #REF! | AY23: =IF(#REF!<>"N/A",Priority!$C23,"") -> #REF! | AZ23: =IF(#REF!<>"N/A",Priority!$C23,"") -> #REF! | BA23: =IF(#REF!<>"N/A",Priority!$C23,"") -> #REF! | BB23: =IF(#REF!<>"N/A",Priority!$C23,"") -> #REF! | BD23: =IF(#REF!<>"N/A",Priority!$C23,"") -> #REF! | BE23: =IF(#REF!<>"N/A",Priority!$C23,"") -> #REF! | BF23: =IF(#REF!<>"N/A",Priority!$C23,"") -> #REF! | BG23: =IF(#REF!<>"N/A",Priority!$C23,"") -> #REF! | BH23: =IF(#REF!<>"N/A",Priority!$C23,"") -> #REF! | BI23: =IF(#REF!<>"N/A",Priority!$C23,"") -> #REF! | BJ23: =IF(#REF!<>"N/A",Priority!$C23,"") -> #REF! | BK23: =IF(#REF!<>"N/A",Priority!$C23,"") -> #REF! | BL23: =IF(#REF!<>"N/A",Priority!$C23,"") -> #REF! | BN23: =IF(#REF!<>"N/A",Priority!$C23,"") -> #REF! | BO23: =IF(#REF!<>"N/A",Priority!$C23,"") -> #REF! | BP23: =IF(#REF!<>"N/A",Priority!$C23,"") -> #REF! | BQ23: =IF(#REF!<>"N/A",Priority!$C23,"") -> #REF! | BR23: =IF(#REF!<>"N/A",Priority!$C23,"") -> #REF! | BS23: =IF(#REF!<>"N/A",Priority!$C23,"") -> #REF! | BT23: =IF(#REF!<>"N/A",Priority!$C23,"") -> #REF! | BV23: =IF(#REF!<>"N/A",Priority!$C23,"") -> #REF! | BW23: =IF(#REF!<>"N/A",Priority!$C23,"") -> #REF! | BX23: =IF(#REF!<>"N/A",Priority!$C23,"") -> #REF! | BY23: =IF(#REF!<>"N/A",Priority!$C23,"") -> #REF! | BZ23: =IF(#REF!<>"N/A",Priority!$C23,"") -> #REF! | CA23: =IF(#REF!<>"N/A",Priority!$C23,"") -> #REF! | CC23: =IF(#REF!<>"N/A",Priority!$C23,"") -> #REF! | CD23: =IF(#REF!<>"N/A",Priority!$C23,"") -> #REF! | CE23: =IF(#REF!<>"N/A",Priority!$C23,"") -> #REF! | CF23: =IF(#REF!<>"N/A",Priority!$C23,"") -> #REF!
A24: =#REF! -> #REF! | B24: =#REF! -> #REF! | C24: =#REF! -> #REF! | D24: MassDC2, FS11, TGT6 | E24: =IF(COUNTIFS(F24:CF24,"F")+COUNTIFS(F24:CF24,"NT")>0,"In Test",IF(COUNTIFS(F24:CF24,"P")+COUNTIFS(F24:CF24,"A")>0,"Pass","Pending")) -> Pending | F24: ="Pass: "& COUNTIFS(G24:CG24,"P")& " /Accept: "& COUNTIFS(G24:CG24,"A")& "/ Fail: "& COUNTIFS(G24:CG24,"Fail") & "/ NT: "& COUNTIFS(G24:CG24,"NT") -> Pass: 0 /Accept: 0/ Fail: 0/ NT: 0 | G24: =IF(#REF!<>"N/A",Priority!$C24,"") -> #REF! | H24: =IF(#REF!<>"N/A",Priority!$C24,"") -> #REF! | I24: =IF(#REF!<>"N/A",Priority!$C24,"") -> #REF! | J24: =IF(#REF!<>"N/A",Priority!$C24,"") -> #REF! | K24: =IF(#REF!<>"N/A",Priority!$C24,"") -> #REF! | M24: =IF(#REF!<>"N/A",Priority!$C24,"") -> #REF! | N24: =IF(#REF!<>"N/A",Priority!$C24,"") -> #REF! | O24: =IF(#REF!<>"N/A",Priority!$C24,"") -> #REF! | P24: =IF(#REF!<>"N/A",Priority!$C24,"") -> #REF! | Q24: =IF(#REF!<>"N/A",Priority!$C24,"") -> #REF! | S24: =IF(#REF!<>"N/A",Priority!$C24,"") -> #REF! | T24: =IF(#REF!<>"N/A",Priority!$C24,"") -> #REF! | U24: =IF(#REF!<>"N/A",Priority!$C24,"") -> #REF! | V24: =IF(#REF!<>"N/A",Priority!$C24,"") -> #REF! | W24: =IF(#REF!<>"N/A",Priority!$C24,"") -> #REF! | X24: =IF(#REF!<>"N/A",Priority!$C24,"") -> #REF! | Z24: =IF(#REF!<>"N/A",Priority!$C24,"") -> #REF! | AA24: =IF(#REF!<>"N/A",Priority!$C24,"") -> #REF! | AB24: =IF(#REF!<>"N/A",Priority!$C24,"") -> #REF! | AC24: =IF(#REF!<>"N/A",Priority!$C24,"") -> #REF! | AD24: =IF(#REF!<>"N/A",Priority!$C24,"") -> #REF! | AE24: =IF(#REF!<>"N/A",Priority!$C24,"") -> #REF! | AF24: =IF(#REF!<>"N/A",Priority!$C24,"") -> #REF! | AG24: =IF(#REF!<>"N/A",Priority!$C24,"") -> #REF! | ... AI24: =IF(#REF!<>"N/A",Priority!$C24,"") -> #REF! | AK24: =IF(#REF!<>"N/A",Priority!$C24,"") -> #REF! | AL24: =IF(#REF!<>"N/A",Priority!$C24,"") -> #REF! | AM24: =IF(#REF!<>"N/A",Priority!$C24,"") -> #REF! | AN24: =IF(#REF!<>"N/A",Priority!$C24,"") -> #REF! | AO24: =IF(#REF!<>"N/A",Priority!$C24,"") -> #REF! | AP24: =IF(#REF!<>"N/A",Priority!$C24,"") -> #REF! | AQ24: =IF(#REF!<>"N/A",Priority!$C24,"") -> #REF! | AR24: =IF(#REF!<>"N/A",Priority!$C24,"") -> #REF! | ... AT24: =IF(#REF!<>"N/A",Priority!$C24,"") -> #REF! | AV24: =IF(#REF!<>"N/A",Priority!$C24,"") -> #REF! | AW24: =IF(#REF!<>"N/A",Priority!$C24,"") -> #REF! | AX24: =IF(#REF!<>"N/A",Priority!$C24,"") -> #REF! | AY24: =IF(#REF!<>"N/A",Priority!$C24,"") -> #REF! | AZ24: =IF(#REF!<>"N/A",Priority!$C24,"") -> #REF! | BA24: =IF(#REF!<>"N/A",Priority!$C24,"") -> #REF! | BB24: =IF(#REF!<>"N/A",Priority!$C24,"") -> #REF! | BD24: =IF(#REF!<>"N/A",Priority!$C24,"") -> #REF! | BE24: =IF(#REF!<>"N/A",Priority!$C24,"") -> #REF! | BF24: =IF(#REF!<>"N/A",Priority!$C24,"") -> #REF! | BG24: =IF(#REF!<>"N/A",Priority!$C24,"") -> #REF! | BH24: =IF(#REF!<>"N/A",Priority!$C24,"") -> #REF! | BI24: =IF(#REF!<>"N/A",Priority!$C24,"") -> #REF! | BJ24: =IF(#REF!<>"N/A",Priority!$C24,"") -> #REF! | BK24: =IF(#REF!<>"N/A",Priority!$C24,"") -> #REF! | BL24: =IF(#REF!<>"N/A",Priority!$C24,"") -> #REF! | BN24: =IF(#REF!<>"N/A",Priority!$C24,"") -> #REF! | BO24: =IF(#REF!<>"N/A",Priority!$C24,"") -> #REF! | BP24: =IF(#REF!<>"N/A",Priority!$C24,"") -> #REF! | BQ24: =IF(#REF!<>"N/A",Priority!$C24,"") -> #REF! | BR24: =IF(#REF!<>"N/A",Priority!$C24,"") -> #REF! | BS24: =IF(#REF!<>"N/A",Priority!$C24,"") -> #REF! | BT24: =IF(#REF!<>"N/A",Priority!$C24,"") -> #REF! | BV24: =IF(#REF!<>"N/A",Priority!$C24,"") -> #REF! | BW24: =IF(#REF!<>"N/A",Priority!$C24,"") -> #REF! | BX24: =IF(#REF!<>"N/A",Priority!$C24,"") -> #REF! | BY24: =IF(#REF!<>"N/A",Priority!$C24,"") -> #REF! | BZ24: =IF(#REF!<>"N/A",Priority!$C24,"") -> #REF! | CA24: =IF(#REF!<>"N/A",Priority!$C24,"") -> #REF! | CC24: =IF(#REF!<>"N/A",Priority!$C24,"") -> #REF! | CD24: =IF(#REF!<>"N/A",Priority!$C24,"") -> #REF! | CE24: =IF(#REF!<>"N/A",Priority!$C24,"") -> #REF! | CF24: =IF(#REF!<>"N/A",Priority!$C24,"") -> #REF!
A25: =#REF! -> #REF! | B25: =#REF! -> #REF! | C25: =#REF! -> #REF! | D25: DCROLE1 - 6 | E25: =IF(COUNTIFS(F25:CF25,"F")+COUNTIFS(F25:CF25,"NT")>0,"In Test",IF(COUNTIFS(F25:CF25,"P")+COUNTIFS(F25:CF25,"A")>0,"Pass","Pending")) -> Pending | F25: ="Pass: "& COUNTIFS(G25:CG25,"P")& " /Accept: "& COUNTIFS(G25:CG25,"A")& "/ Fail: "& COUNTIFS(G25:CG25,"Fail") & "/ NT: "& COUNTIFS(G25:CG25,"NT") -> Pass: 0 /Accept: 0/ Fail: 0/ NT: 0 | G25: =IF(#REF!<>"N/A",Priority!$C25,"") -> #REF! | H25: =IF(#REF!<>"N/A",Priority!$C25,"") -> #REF! | I25: =IF(#REF!<>"N/A",Priority!$C25,"") -> #REF! | J25: =IF(#REF!<>"N/A",Priority!$C25,"") -> #REF! | K25: =IF(#REF!<>"N/A",Priority!$C25,"") -> #REF! | M25: =IF(#REF!<>"N/A",Priority!$C25,"") -> #REF! | N25: =IF(#REF!<>"N/A",Priority!$C25,"") -> #REF! | O25: =IF(#REF!<>"N/A",Priority!$C25,"") -> #REF! | P25: =IF(#REF!<>"N/A",Priority!$C25,"") -> #REF! | Q25: =IF(#REF!<>"N/A",Priority!$C25,"") -> #REF! | S25: =IF(#REF!<>"N/A",Priority!$C25,"") -> #REF! | T25: =IF(#REF!<>"N/A",Priority!$C25,"") -> #REF! | U25: =IF(#REF!<>"N/A",Priority!$C25,"") -> #REF! | V25: =IF(#REF!<>"N/A",Priority!$C25,"") -> #REF! | W25: =IF(#REF!<>"N/A",Priority!$C25,"") -> #REF! | X25: =IF(#REF!<>"N/A",Priority!$C25,"") -> #REF! | Z25: =IF(#REF!<>"N/A",Priority!$C25,"") -> #REF! | AA25: =IF(#REF!<>"N/A",Priority!$C25,"") -> #REF! | AB25: =IF(#REF!<>"N/A",Priority!$C25,"") -> #REF! | AC25: =IF(#REF!<>"N/A",Priority!$C25,"") -> #REF! | AD25: =IF(#REF!<>"N/A",Priority!$C25,"") -> #REF! | AE25: =IF(#REF!<>"N/A",Priority!$C25,"") -> #REF! | AF25: =IF(#REF!<>"N/A",Priority!$C25,"") -> #REF! | AG25: =IF(#REF!<>"N/A",Priority!$C25,"") -> #REF! | ... AI25: =IF(#REF!<>"N/A",Priority!$C25,"") -> #REF! | AK25: =IF(#REF!<>"N/A",Priority!$C25,"") -> #REF! | AL25: =IF(#REF!<>"N/A",Priority!$C25,"") -> #REF! | AM25: =IF(#REF!<>"N/A",Priority!$C25,"") -> #REF! | AN25: =IF(#REF!<>"N/A",Priority!$C25,"") -> #REF! | AO25: =IF(#REF!<>"N/A",Priority!$C25,"") -> #REF! | AP25: =IF(#REF!<>"N/A",Priority!$C25,"") -> #REF! | AQ25: =IF(#REF!<>"N/A",Priority!$C25,"") -> #REF! | AR25: =IF(#REF!<>"N/A",Priority!$C25,"") -> #REF! | ... AT25: =IF(#REF!<>"N/A",Priority!$C25,"") -> #REF! | AV25: =IF(#REF!<>"N/A",Priority!$C25,"") -> #REF! | AW25: =IF(#REF!<>"N/A",Priority!$C25,"") -> #REF! | AX25: =IF(#REF!<>"N/A",Priority!$C25,"") -> #REF! | AY25: =IF(#REF!<>"N/A",Priority!$C25,"") -> #REF! | AZ25: =IF(#REF!<>"N/A",Priority!$C25,"") -> #REF! | BA25: =IF(#REF!<>"N/A",Priority!$C25,"") -> #REF! | BB25: =IF(#REF!<>"N/A",Priority!$C25,"") -> #REF! | BD25: =IF(#REF!<>"N/A",Priority!$C25,"") -> #REF! | BE25: =IF(#REF!<>"N/A",Priority!$C25,"") -> #REF! | BF25: =IF(#REF!<>"N/A",Priority!$C25,"") -> #REF! | BG25: =IF(#REF!<>"N/A",Priority!$C25,"") -> #REF! | BH25: =IF(#REF!<>"N/A",Priority!$C25,"") -> #REF! | BI25: =IF(#REF!<>"N/A",Priority!$C25,"") -> #REF! | BJ25: =IF(#REF!<>"N/A",Priority!$C25,"") -> #REF! | BK25: =IF(#REF!<>"N/A",Priority!$C25,"") -> #REF! | BL25: =IF(#REF!<>"N/A",Priority!$C25,"") -> #REF! | BN25: =IF(#REF!<>"N/A",Priority!$C25,"") -> #REF! | BO25: =IF(#REF!<>"N/A",Priority!$C25,"") -> #REF! | BP25: =IF(#REF!<>"N/A",Priority!$C25,"") -> #REF! | BQ25: =IF(#REF!<>"N/A",Priority!$C25,"") -> #REF! | BR25: =IF(#REF!<>"N/A",Priority!$C25,"") -> #REF! | BS25: =IF(#REF!<>"N/A",Priority!$C25,"") -> #REF! | BT25: =IF(#REF!<>"N/A",Priority!$C25,"") -> #REF! | BV25: =IF(#REF!<>"N/A",Priority!$C25,"") -> #REF! | BW25: =IF(#REF!<>"N/A",Priority!$C25,"") -> #REF! | BX25: =IF(#REF!<>"N/A",Priority!$C25,"") -> #REF! | BY25: =IF(#REF!<>"N/A",Priority!$C25,"") -> #REF! | BZ25: =IF(#REF!<>"N/A",Priority!$C25,"") -> #REF! | CA25: =IF(#REF!<>"N/A",Priority!$C25,"") -> #REF! | CC25: =IF(#REF!<>"N/A",Priority!$C25,"") -> #REF! | CD25: =IF(#REF!<>"N/A",Priority!$C25,"") -> #REF! | CE25: =IF(#REF!<>"N/A",Priority!$C25,"") -> #REF! | CF25: =IF(#REF!<>"N/A",Priority!$C25,"") -> #REF!
A26: =#REF! -> #REF! | B26: =#REF! -> #REF! | C26: =#REF! -> #REF! | D26: DC1, DC2 | E26: =IF(COUNTIFS(F26:CF26,"F")+COUNTIFS(F26:CF26,"NT")>0,"In Test",IF(COUNTIFS(F26:CF26,"P")+COUNTIFS(F26:CF26,"A")>0,"Pass","Pending")) -> Pending | F26: ="Pass: "& COUNTIFS(G26:CG26,"P")& " /Accept: "& COUNTIFS(G26:CG26,"A")& "/ Fail: "& COUNTIFS(G26:CG26,"Fail") & "/ NT: "& COUNTIFS(G26:CG26,"NT") -> Pass: 0 /Accept: 0/ Fail: 0/ NT: 0 | G26: =IF(#REF!<>"N/A",Priority!$C26,"") -> #REF! | H26: =IF(#REF!<>"N/A",Priority!$C26,"") -> #REF! | I26: =IF(#REF!<>"N/A",Priority!$C26,"") -> #REF! | J26: =IF(#REF!<>"N/A",Priority!$C26,"") -> #REF! | K26: =IF(#REF!<>"N/A",Priority!$C26,"") -> #REF! | M26: =IF(#REF!<>"N/A",Priority!$C26,"") -> #REF! | N26: =IF(#REF!<>"N/A",Priority!$C26,"") -> #REF! | O26: =IF(#REF!<>"N/A",Priority!$C26,"") -> #REF! | P26: =IF(#REF!<>"N/A",Priority!$C26,"") -> #REF! | Q26: =IF(#REF!<>"N/A",Priority!$C26,"") -> #REF! | S26: =IF(#REF!<>"N/A",Priority!$C26,"") -> #REF! | T26: =IF(#REF!<>"N/A",Priority!$C26,"") -> #REF! | U26: =IF(#REF!<>"N/A",Priority!$C26,"") -> #REF! | V26: =IF(#REF!<>"N/A",Priority!$C26,"") -> #REF! | W26: =IF(#REF!<>"N/A",Priority!$C26,"") -> #REF! | X26: =IF(#REF!<>"N/A",Priority!$C26,"") -> #REF! | Z26: =IF(#REF!<>"N/A",Priority!$C26,"") -> #REF! | AA26: =IF(#REF!<>"N/A",Priority!$C26,"") -> #REF! | AB26: =IF(#REF!<>"N/A",Priority!$C26,"") -> #REF! | AC26: =IF(#REF!<>"N/A",Priority!$C26,"") -> #REF! | AD26: =IF(#REF!<>"N/A",Priority!$C26,"") -> #REF! | AE26: =IF(#REF!<>"N/A",Priority!$C26,"") -> #REF! | AF26: =IF(#REF!<>"N/A",Priority!$C26,"") -> #REF! | AG26: =IF(#REF!<>"N/A",Priority!$C26,"") -> #REF! | ... AI26: =IF(#REF!<>"N/A",Priority!$C26,"") -> #REF! | AK26: =IF(#REF!<>"N/A",Priority!$C26,"") -> #REF! | AL26: =IF(#REF!<>"N/A",Priority!$C26,"") -> #REF! | AM26: =IF(#REF!<>"N/A",Priority!$C26,"") -> #REF! | AN26: =IF(#REF!<>"N/A",Priority!$C26,"") -> #REF! | AO26: =IF(#REF!<>"N/A",Priority!$C26,"") -> #REF! | AP26: =IF(#REF!<>"N/A",Priority!$C26,"") -> #REF! | AQ26: =IF(#REF!<>"N/A",Priority!$C26,"") -> #REF! | AR26: =IF(#REF!<>"N/A",Priority!$C26,"") -> #REF! | ... AT26: =IF(#REF!<>"N/A",Priority!$C26,"") -> #REF! | AV26: =IF(#REF!<>"N/A",Priority!$C26,"") -> #REF! | AW26: =IF(#REF!<>"N/A",Priority!$C26,"") -> #REF! | AX26: =IF(#REF!<>"N/A",Priority!$C26,"") -> #REF! | AY26: =IF(#REF!<>"N/A",Priority!$C26,"") -> #REF! | AZ26: =IF(#REF!<>"N/A",Priority!$C26,"") -> #REF! | BA26: =IF(#REF!<>"N/A",Priority!$C26,"") -> #REF! | BB26: =IF(#REF!<>"N/A",Priority!$C26,"") -> #REF! | BD26: =IF(#REF!<>"N/A",Priority!$C26,"") -> #REF! | BE26: =IF(#REF!<>"N/A",Priority!$C26,"") -> #REF! | BF26: =IF(#REF!<>"N/A",Priority!$C26,"") -> #REF! | BG26: =IF(#REF!<>"N/A",Priority!$C26,"") -> #REF! | BH26: =IF(#REF!<>"N/A",Priority!$C26,"") -> #REF! | BI26: =IF(#REF!<>"N/A",Priority!$C26,"") -> #REF! | BJ26: =IF(#REF!<>"N/A",Priority!$C26,"") -> #REF! | BK26: =IF(#REF!<>"N/A",Priority!$C26,"") -> #REF! | BL26: =IF(#REF!<>"N/A",Priority!$C26,"") -> #REF! | BN26: =IF(#REF!<>"N/A",Priority!$C26,"") -> #REF! | BO26: =IF(#REF!<>"N/A",Priority!$C26,"") -> #REF! | BP26: =IF(#REF!<>"N/A",Priority!$C26,"") -> #REF! | BQ26: =IF(#REF!<>"N/A",Priority!$C26,"") -> #REF! | BR26: =IF(#REF!<>"N/A",Priority!$C26,"") -> #REF! | BS26: =IF(#REF!<>"N/A",Priority!$C26,"") -> #REF! | BT26: =IF(#REF!<>"N/A",Priority!$C26,"") -> #REF! | BV26: =IF(#REF!<>"N/A",Priority!$C26,"") -> #REF! | BW26: =IF(#REF!<>"N/A",Priority!$C26,"") -> #REF! | BX26: =IF(#REF!<>"N/A",Priority!$C26,"") -> #REF! | BY26: =IF(#REF!<>"N/A",Priority!$C26,"") -> #REF! | BZ26: =IF(#REF!<>"N/A",Priority!$C26,"") -> #REF! | CA26: =IF(#REF!<>"N/A",Priority!$C26,"") -> #REF! | CC26: =IF(#REF!<>"N/A",Priority!$C26,"") -> #REF! | CD26: =IF(#REF!<>"N/A",Priority!$C26,"") -> #REF! | CE26: =IF(#REF!<>"N/A",Priority!$C26,"") -> #REF! | CF26: =IF(#REF!<>"N/A",Priority!$C26,"") -> #REF!
A27: =#REF! -> #REF! | B27: =#REF! -> #REF! | C27: =#REF! -> #REF! | D27: DC1, DC2 | E27: =IF(COUNTIFS(F27:CF27,"F")+COUNTIFS(F27:CF27,"NT")>0,"In Test",IF(COUNTIFS(F27:CF27,"P")+COUNTIFS(F27:CF27,"A")>0,"Pass","Pending")) -> Pending | F27: ="Pass: "& COUNTIFS(G27:CG27,"P")& " /Accept: "& COUNTIFS(G27:CG27,"A")& "/ Fail: "& COUNTIFS(G27:CG27,"Fail") & "/ NT: "& COUNTIFS(G27:CG27,"NT") -> Pass: 0 /Accept: 0/ Fail: 0/ NT: 0 | G27: =IF(#REF!<>"N/A",Priority!$C27,"") -> #REF! | H27: =IF(#REF!<>"N/A",Priority!$C27,"") -> #REF! | I27: =IF(#REF!<>"N/A",Priority!$C27,"") -> #REF! | J27: =IF(#REF!<>"N/A",Priority!$C27,"") -> #REF! | K27: =IF(#REF!<>"N/A",Priority!$C27,"") -> #REF! | M27: =IF(#REF!<>"N/A",Priority!$C27,"") -> #REF! | N27: =IF(#REF!<>"N/A",Priority!$C27,"") -> #REF! | O27: =IF(#REF!<>"N/A",Priority!$C27,"") -> #REF! | P27: =IF(#REF!<>"N/A",Priority!$C27,"") -> #REF! | Q27: =IF(#REF!<>"N/A",Priority!$C27,"") -> #REF! | S27: =IF(#REF!<>"N/A",Priority!$C27,"") -> #REF! | T27: =IF(#REF!<>"N/A",Priority!$C27,"") -> #REF! | U27: =IF(#REF!<>"N/A",Priority!$C27,"") -> #REF! | V27: =IF(#REF!<>"N/A",Priority!$C27,"") -> #REF! | W27: =IF(#REF!<>"N/A",Priority!$C27,"") -> #REF! | X27: =IF(#REF!<>"N/A",Priority!$C27,"") -> #REF! | Z27: =IF(#REF!<>"N/A",Priority!$C27,"") -> #REF! | AA27: =IF(#REF!<>"N/A",Priority!$C27,"") -> #REF! | AB27: =IF(#REF!<>"N/A",Priority!$C27,"") -> #REF! | AC27: =IF(#REF!<>"N/A",Priority!$C27,"") -> #REF! | AD27: =IF(#REF!<>"N/A",Priority!$C27,"") -> #REF! | AE27: =IF(#REF!<>"N/A",Priority!$C27,"") -> #REF! | AF27: =IF(#REF!<>"N/A",Priority!$C27,"") -> #REF! | AG27: =IF(#REF!<>"N/A",Priority!$C27,"") -> #REF! | ... AI27: =IF(#REF!<>"N/A",Priority!$C27,"") -> #REF! | AK27: =IF(#REF!<>"N/A",Priority!$C27,"") -> #REF! | AL27: =IF(#REF!<>"N/A",Priority!$C27,"") -> #REF! | AM27: =IF(#REF!<>"N/A",Priority!$C27,"") -> #REF! | AN27: =IF(#REF!<>"N/A",Priority!$C27,"") -> #REF! | AO27: =IF(#REF!<>"N/A",Priority!$C27,"") -> #REF! | AP27: =IF(#REF!<>"N/A",Priority!$C27,"") -> #REF! | AQ27: =IF(#REF!<>"N/A",Priority!$C27,"") -> #REF! | AR27: =IF(#REF!<>"N/A",Priority!$C27,"") -> #REF! | ... AT27: =IF(#REF!<>"N/A",Priority!$C27,"") -> #REF! | AV27: =IF(#REF!<>"N/A",Priority!$C27,"") -> #REF! | AW27: =IF(#REF!<>"N/A",Priority!$C27,"") -> #REF! | AX27: =IF(#REF!<>"N/A",Priority!$C27,"") -> #REF! | AY27: =IF(#REF!<>"N/A",Priority!$C27,"") -> #REF! | AZ27: =IF(#REF!<>"N/A",Priority!$C27,"") -> #REF! | BA27: =IF(#REF!<>"N/A",Priority!$C27,"") -> #REF! | BB27: =IF(#REF!<>"N/A",Priority!$C27,"") -> #REF! | BD27: =IF(#REF!<>"N/A",Priority!$C27,"") -> #REF! | BE27: =IF(#REF!<>"N/A",Priority!$C27,"") -> #REF! | BF27: =IF(#REF!<>"N/A",Priority!$C27,"") -> #REF! | BG27: =IF(#REF!<>"N/A",Priority!$C27,"") -> #REF! | BH27: =IF(#REF!<>"N/A",Priority!$C27,"") -> #REF! | BI27: =IF(#REF!<>"N/A",Priority!$C27,"") -> #REF! | BJ27: =IF(#REF!<>"N/A",Priority!$C27,"") -> #REF! | BK27: =IF(#REF!<>"N/A",Priority!$C27,"") -> #REF! | BL27: =IF(#REF!<>"N/A",Priority!$C27,"") -> #REF! | BN27: =IF(#REF!<>"N/A",Priority!$C27,"") -> #REF! | BO27: =IF(#REF!<>"N/A",Priority!$C27,"") -> #REF! | BP27: =IF(#REF!<>"N/A",Priority!$C27,"") -> #REF! | BQ27: =IF(#REF!<>"N/A",Priority!$C27,"") -> #REF! | BR27: =IF(#REF!<>"N/A",Priority!$C27,"") -> #REF! | BS27: =IF(#REF!<>"N/A",Priority!$C27,"") -> #REF! | BT27: =IF(#REF!<>"N/A",Priority!$C27,"") -> #REF! | BV27: =IF(#REF!<>"N/A",Priority!$C27,"") -> #REF! | BW27: =IF(#REF!<>"N/A",Priority!$C27,"") -> #REF! | BX27: =IF(#REF!<>"N/A",Priority!$C27,"") -> #REF! | BY27: =IF(#REF!<>"N/A",Priority!$C27,"") -> #REF! | BZ27: =IF(#REF!<>"N/A",Priority!$C27,"") -> #REF! | CA27: =IF(#REF!<>"N/A",Priority!$C27,"") -> #REF! | CC27: =IF(#REF!<>"N/A",Priority!$C27,"") -> #REF! | CD27: =IF(#REF!<>"N/A",Priority!$C27,"") -> #REF! | CE27: =IF(#REF!<>"N/A",Priority!$C27,"") -> #REF! | CF27: =IF(#REF!<>"N/A",Priority!$C27,"") -> #REF!
A28: =#REF! -> #REF! | B28: =#REF! -> #REF! | C28: =#REF! -> #REF! | D28: DC4 | E28: =IF(COUNTIFS(F28:CF28,"F")+COUNTIFS(F28:CF28,"NT")>0,"In Test",IF(COUNTIFS(F28:CF28,"P")+COUNTIFS(F28:CF28,"A")>0,"Pass","Pending")) -> Pending | F28: ="Pass: "& COUNTIFS(G28:CG28,"P")& " /Accept: "& COUNTIFS(G28:CG28,"A")& "/ Fail: "& COUNTIFS(G28:CG28,"Fail") & "/ NT: "& COUNTIFS(G28:CG28,"NT") -> Pass: 0 /Accept: 0/ Fail: 0/ NT: 0 | G28: =IF(#REF!<>"N/A",Priority!$C28,"") -> #REF! | H28: =IF(#REF!<>"N/A",Priority!$C28,"") -> #REF! | I28: =IF(#REF!<>"N/A",Priority!$C28,"") -> #REF! | J28: =IF(#REF!<>"N/A",Priority!$C28,"") -> #REF! | K28: =IF(#REF!<>"N/A",Priority!$C28,"") -> #REF! | M28: =IF(#REF!<>"N/A",Priority!$C28,"") -> #REF! | N28: =IF(#REF!<>"N/A",Priority!$C28,"") -> #REF! | O28: =IF(#REF!<>"N/A",Priority!$C28,"") -> #REF! | P28: =IF(#REF!<>"N/A",Priority!$C28,"") -> #REF! | Q28: =IF(#REF!<>"N/A",Priority!$C28,"") -> #REF! | S28: =IF(#REF!<>"N/A",Priority!$C28,"") -> #REF! | T28: =IF(#REF!<>"N/A",Priority!$C28,"") -> #REF! | U28: =IF(#REF!<>"N/A",Priority!$C28,"") -> #REF! | V28: =IF(#REF!<>"N/A",Priority!$C28,"") -> #REF! | W28: =IF(#REF!<>"N/A",Priority!$C28,"") -> #REF! | X28: =IF(#REF!<>"N/A",Priority!$C28,"") -> #REF! | Z28: =IF(#REF!<>"N/A",Priority!$C28,"") -> #REF! | AA28: =IF(#REF!<>"N/A",Priority!$C28,"") -> #REF! | AB28: =IF(#REF!<>"N/A",Priority!$C28,"") -> #REF! | AC28: =IF(#REF!<>"N/A",Priority!$C28,"") -> #REF! | AD28: =IF(#REF!<>"N/A",Priority!$C28,"") -> #REF! | AE28: =IF(#REF!<>"N/A",Priority!$C28,"") -> #REF! | AF28: =IF(#REF!<>"N/A",Priority!$C28,"") -> #REF! | AG28: =IF(#REF!<>"N/A",Priority!$C28,"") -> #REF! | ... AI28: =IF(#REF!<>"N/A",Priority!$C28,"") -> #REF! | AK28: =IF(#REF!<>"N/A",Priority!$C28,"") -> #REF! | AL28: =IF(#REF!<>"N/A",Priority!$C28,"") -> #REF! | AM28: =IF(#REF!<>"N/A",Priority!$C28,"") -> #REF! | AN28: =IF(#REF!<>"N/A",Priority!$C28,"") -> #REF! | AO28: =IF(#REF!<>"N/A",Priority!$C28,"") -> #REF! | AP28: =IF(#REF!<>"N/A",Priority!$C28,"") -> #REF! | AQ28: =IF(#REF!<>"N/A",Priority!$C28,"") -> #REF! | AR28: =IF(#REF!<>"N/A",Priority!$C28,"") -> #REF! | ... AT28: =IF(#REF!<>"N/A",Priority!$C28,"") -> #REF! | AV28: =IF(#REF!<>"N/A",Priority!$C28,"") -> #REF! | AW28: =IF(#REF!<>"N/A",Priority!$C28,"") -> #REF! | AX28: =IF(#REF!<>"N/A",Priority!$C28,"") -> #REF! | AY28: =IF(#REF!<>"N/A",Priority!$C28,"") -> #REF! | AZ28: =IF(#REF!<>"N/A",Priority!$C28,"") -> #REF! | BA28: =IF(#REF!<>"N/A",Priority!$C28,"") -> #REF! | BB28: =IF(#REF!<>"N/A",Priority!$C28,"") -> #REF! | BD28: =IF(#REF!<>"N/A",Priority!$C28,"") -> #REF! | BE28: =IF(#REF!<>"N/A",Priority!$C28,"") -> #REF! | BF28: =IF(#REF!<>"N/A",Priority!$C28,"") -> #REF! | BG28: =IF(#REF!<>"N/A",Priority!$C28,"") -> #REF! | BH28: =IF(#REF!<>"N/A",Priority!$C28,"") -> #REF! | BI28: =IF(#REF!<>"N/A",Priority!$C28,"") -> #REF! | BJ28: =IF(#REF!<>"N/A",Priority!$C28,"") -> #REF! | BK28: =IF(#REF!<>"N/A",Priority!$C28,"") -> #REF! | BL28: =IF(#REF!<>"N/A",Priority!$C28,"") -> #REF! | BN28: =IF(#REF!<>"N/A",Priority!$C28,"") -> #REF! | BO28: =IF(#REF!<>"N/A",Priority!$C28,"") -> #REF! | BP28: =IF(#REF!<>"N/A",Priority!$C28,"") -> #REF! | BQ28: =IF(#REF!<>"N/A",Priority!$C28,"") -> #REF! | BR28: =IF(#REF!<>"N/A",Priority!$C28,"") -> #REF! | BS28: =IF(#REF!<>"N/A",Priority!$C28,"") -> #REF! | BT28: =IF(#REF!<>"N/A",Priority!$C28,"") -> #REF! | BV28: =IF(#REF!<>"N/A",Priority!$C28,"") -> #REF! | BW28: =IF(#REF!<>"N/A",Priority!$C28,"") -> #REF! | BX28: =IF(#REF!<>"N/A",Priority!$C28,"") -> #REF! | BY28: =IF(#REF!<>"N/A",Priority!$C28,"") -> #REF! | BZ28: =IF(#REF!<>"N/A",Priority!$C28,"") -> #REF! | CA28: =IF(#REF!<>"N/A",Priority!$C28,"") -> #REF! | CC28: =IF(#REF!<>"N/A",Priority!$C28,"") -> #REF! | CD28: =IF(#REF!<>"N/A",Priority!$C28,"") -> #REF! | CE28: =IF(#REF!<>"N/A",Priority!$C28,"") -> #REF! | CF28: =IF(#REF!<>"N/A",Priority!$C28,"") -> #REF!
A29: =#REF! -> #REF! | B29: =#REF! -> #REF! | C29: =#REF! -> #REF! | D29: DC2. DC3 | E29: =IF(COUNTIFS(F29:CF29,"F")+COUNTIFS(F29:CF29,"NT")>0,"In Test",IF(COUNTIFS(F29:CF29,"P")+COUNTIFS(F29:CF29,"A")>0,"Pass","Pending")) -> Pending | F29: ="Pass: "& COUNTIFS(G29:CG29,"P")& " /Accept: "& COUNTIFS(G29:CG29,"A")& "/ Fail: "& COUNTIFS(G29:CG29,"Fail") & "/ NT: "& COUNTIFS(G29:CG29,"NT") -> Pass: 0 /Accept: 0/ Fail: 0/ NT: 0 | G29: =IF(#REF!<>"N/A",Priority!$C29,"") -> #REF! | H29: =IF(#REF!<>"N/A",Priority!$C29,"") -> #REF! | I29: =IF(#REF!<>"N/A",Priority!$C29,"") -> #REF! | J29: =IF(#REF!<>"N/A",Priority!$C29,"") -> #REF! | K29: =IF(#REF!<>"N/A",Priority!$C29,"") -> #REF! | M29: =IF(#REF!<>"N/A",Priority!$C29,"") -> #REF! | N29: =IF(#REF!<>"N/A",Priority!$C29,"") -> #REF! | O29: =IF(#REF!<>"N/A",Priority!$C29,"") -> #REF! | P29: =IF(#REF!<>"N/A",Priority!$C29,"") -> #REF! | Q29: =IF(#REF!<>"N/A",Priority!$C29,"") -> #REF! | S29: =IF(#REF!<>"N/A",Priority!$C29,"") -> #REF! | T29: =IF(#REF!<>"N/A",Priority!$C29,"") -> #REF! | U29: =IF(#REF!<>"N/A",Priority!$C29,"") -> #REF! | V29: =IF(#REF!<>"N/A",Priority!$C29,"") -> #REF! | W29: =IF(#REF!<>"N/A",Priority!$C29,"") -> #REF! | X29: =IF(#REF!<>"N/A",Priority!$C29,"") -> #REF! | Z29: =IF(#REF!<>"N/A",Priority!$C29,"") -> #REF! | AA29: =IF(#REF!<>"N/A",Priority!$C29,"") -> #REF! | AB29: =IF(#REF!<>"N/A",Priority!$C29,"") -> #REF! | AC29: =IF(#REF!<>"N/A",Priority!$C29,"") -> #REF! | AD29: =IF(#REF!<>"N/A",Priority!$C29,"") -> #REF! | AE29: =IF(#REF!<>"N/A",Priority!$C29,"") -> #REF! | AF29: =IF(#REF!<>"N/A",Priority!$C29,"") -> #REF! | AG29: =IF(#REF!<>"N/A",Priority!$C29,"") -> #REF! | ... AI29: =IF(#REF!<>"N/A",Priority!$C29,"") -> #REF! | AK29: =IF(#REF!<>"N/A",Priority!$C29,"") -> #REF! | AL29: =IF(#REF!<>"N/A",Priority!$C29,"") -> #REF! | AM29: =IF(#REF!<>"N/A",Priority!$C29,"") -> #REF! | AN29: =IF(#REF!<>"N/A",Priority!$C29,"") -> #REF! | AO29: =IF(#REF!<>"N/A",Priority!$C29,"") -> #REF! | AP29: =IF(#REF!<>"N/A",Priority!$C29,"") -> #REF! | AQ29: =IF(#REF!<>"N/A",Priority!$C29,"") -> #REF! | AR29: =IF(#REF!<>"N/A",Priority!$C29,"") -> #REF! | ... AT29: =IF(#REF!<>"N/A",Priority!$C29,"") -> #REF! | AV29: =IF(#REF!<>"N/A",Priority!$C29,"") -> #REF! | AW29: =IF(#REF!<>"N/A",Priority!$C29,"") -> #REF! | AX29: =IF(#REF!<>"N/A",Priority!$C29,"") -> #REF! | AY29: =IF(#REF!<>"N/A",Priority!$C29,"") -> #REF! | AZ29: =IF(#REF!<>"N/A",Priority!$C29,"") -> #REF! | BA29: =IF(#REF!<>"N/A",Priority!$C29,"") -> #REF! | BB29: =IF(#REF!<>"N/A",Priority!$C29,"") -> #REF! | BD29: =IF(#REF!<>"N/A",Priority!$C29,"") -> #REF! | BE29: =IF(#REF!<>"N/A",Priority!$C29,"") -> #REF! | BF29: =IF(#REF!<>"N/A",Priority!$C29,"") -> #REF! | BG29: =IF(#REF!<>"N/A",Priority!$C29,"") -> #REF! | BH29: =IF(#REF!<>"N/A",Priority!$C29,"") -> #REF! | BI29: =IF(#REF!<>"N/A",Priority!$C29,"") -> #REF! | BJ29: =IF(#REF!<>"N/A",Priority!$C29,"") -> #REF! | BK29: =IF(#REF!<>"N/A",Priority!$C29,"") -> #REF! | BL29: =IF(#REF!<>"N/A",Priority!$C29,"") -> #REF! | BN29: =IF(#REF!<>"N/A",Priority!$C29,"") -> #REF! | BO29: =IF(#REF!<>"N/A",Priority!$C29,"") -> #REF! | BP29: =IF(#REF!<>"N/A",Priority!$C29,"") -> #REF! | BQ29: =IF(#REF!<>"N/A",Priority!$C29,"") -> #REF! | BR29: =IF(#REF!<>"N/A",Priority!$C29,"") -> #REF! | BS29: =IF(#REF!<>"N/A",Priority!$C29,"") -> #REF! | BT29: =IF(#REF!<>"N/A",Priority!$C29,"") -> #REF! | BV29: =IF(#REF!<>"N/A",Priority!$C29,"") -> #REF! | BW29: =IF(#REF!<>"N/A",Priority!$C29,"") -> #REF! | BX29: =IF(#REF!<>"N/A",Priority!$C29,"") -> #REF! | BY29: =IF(#REF!<>"N/A",Priority!$C29,"") -> #REF! | BZ29: =IF(#REF!<>"N/A",Priority!$C29,"") -> #REF! | CA29: =IF(#REF!<>"N/A",Priority!$C29,"") -> #REF! | CC29: =IF(#REF!<>"N/A",Priority!$C29,"") -> #REF! | CD29: =IF(#REF!<>"N/A",Priority!$C29,"") -> #REF! | CE29: =IF(#REF!<>"N/A",Priority!$C29,"") -> #REF! | CF29: =IF(#REF!<>"N/A",Priority!$C29,"") -> #REF!
A30: =#REF! -> #REF! | B30: =#REF! -> #REF! | C30: =#REF! -> #REF! | D30: DC1, DC2, MASSDC1- MASSDC10 | E30: =IF(COUNTIFS(F30:CF30,"F")+COUNTIFS(F30:CF30,"NT")>0,"In Test",IF(COUNTIFS(F30:CF30,"P")+COUNTIFS(F30:CF30,"A")>0,"Pass","Pending")) -> Pending | F30: ="Pass: "& COUNTIFS(G30:CG30,"P")& " /Accept: "& COUNTIFS(G30:CG30,"A")& "/ Fail: "& COUNTIFS(G30:CG30,"Fail") & "/ NT: "& COUNTIFS(G30:CG30,"NT") -> Pass: 0 /Accept: 0/ Fail: 0/ NT: 0 | G30: =IF(#REF!<>"N/A",Priority!$C30,"") -> #REF! | H30: =IF(#REF!<>"N/A",Priority!$C30,"") -> #REF! | I30: =IF(#REF!<>"N/A",Priority!$C30,"") -> #REF! | J30: =IF(#REF!<>"N/A",Priority!$C30,"") -> #REF! | K30: =IF(#REF!<>"N/A",Priority!$C30,"") -> #REF! | M30: =IF(#REF!<>"N/A",Priority!$C30,"") -> #REF! | N30: =IF(#REF!<>"N/A",Priority!$C30,"") -> #REF! | O30: =IF(#REF!<>"N/A",Priority!$C30,"") -> #REF! | P30: =IF(#REF!<>"N/A",Priority!$C30,"") -> #REF! | Q30: =IF(#REF!<>"N/A",Priority!$C30,"") -> #REF! | S30: =IF(#REF!<>"N/A",Priority!$C30,"") -> #REF! | T30: =IF(#REF!<>"N/A",Priority!$C30,"") -> #REF! | U30: =IF(#REF!<>"N/A",Priority!$C30,"") -> #REF! | V30: =IF(#REF!<>"N/A",Priority!$C30,"") -> #REF! | W30: =IF(#REF!<>"N/A",Priority!$C30,"") -> #REF! | X30: =IF(#REF!<>"N/A",Priority!$C30,"") -> #REF! | Z30: =IF(#REF!<>"N/A",Priority!$C30,"") -> #REF! | AA30: =IF(#REF!<>"N/A",Priority!$C30,"") -> #REF! | AB30: =IF(#REF!<>"N/A",Priority!$C30,"") -> #REF! | AC30: =IF(#REF!<>"N/A",Priority!$C30,"") -> #REF! | AD30: =IF(#REF!<>"N/A",Priority!$C30,"") -> #REF! | AE30: =IF(#REF!<>"N/A",Priority!$C30,"") -> #REF! | AF30: =IF(#REF!<>"N/A",Priority!$C30,"") -> #REF! | AG30: =IF(#REF!<>"N/A",Priority!$C30,"") -> #REF! | ... AI30: =IF(#REF!<>"N/A",Priority!$C30,"") -> #REF! | AK30: =IF(#REF!<>"N/A",Priority!$C30,"") -> #REF! | AL30: =IF(#REF!<>"N/A",Priority!$C30,"") -> #REF! | AM30: =IF(#REF!<>"N/A",Priority!$C30,"") -> #REF! | AN30: =IF(#REF!<>"N/A",Priority!$C30,"") -> #REF! | AO30: =IF(#REF!<>"N/A",Priority!$C30,"") -> #REF! | AP30: =IF(#REF!<>"N/A",Priority!$C30,"") -> #REF! | AQ30: =IF(#REF!<>"N/A",Priority!$C30,"") -> #REF! | AR30: =IF(#REF!<>"N/A",Priority!$C30,"") -> #REF! | ... AT30: =IF(#REF!<>"N/A",Priority!$C30,"") -> #REF! | AV30: =IF(#REF!<>"N/A",Priority!$C30,"") -> #REF! | AW30: =IF(#REF!<>"N/A",Priority!$C30,"") -> #REF! | AX30: =IF(#REF!<>"N/A",Priority!$C30,"") -> #REF! | AY30: =IF(#REF!<>"N/A",Priority!$C30,"") -> #REF! | AZ30: =IF(#REF!<>"N/A",Priority!$C30,"") -> #REF! | BA30: =IF(#REF!<>"N/A",Priority!$C30,"") -> #REF! | BB30: =IF(#REF!<>"N/A",Priority!$C30,"") -> #REF! | BD30: =IF(#REF!<>"N/A",Priority!$C30,"") -> #REF! | BE30: =IF(#REF!<>"N/A",Priority!$C30,"") -> #REF! | BF30: =IF(#REF!<>"N/A",Priority!$C30,"") -> #REF! | BG30: =IF(#REF!<>"N/A",Priority!$C30,"") -> #REF! | BH30: =IF(#REF!<>"N/A",Priority!$C30,"") -> #REF! | BI30: =IF(#REF!<>"N/A",Priority!$C30,"") -> #REF! | BJ30: =IF(#REF!<>"N/A",Priority!$C30,"") -> #REF! | BK30: =IF(#REF!<>"N/A",Priority!$C30,"") -> #REF! | BL30: =IF(#REF!<>"N/A",Priority!$C30,"") -> #REF! | BN30: =IF(#REF!<>"N/A",Priority!$C30,"") -> #REF! | BO30: =IF(#REF!<>"N/A",Priority!$C30,"") -> #REF! | BP30: =IF(#REF!<>"N/A",Priority!$C30,"") -> #REF! | BQ30: =IF(#REF!<>"N/A",Priority!$C30,"") -> #REF! | BR30: =IF(#REF!<>"N/A",Priority!$C30,"") -> #REF! | BS30: =IF(#REF!<>"N/A",Priority!$C30,"") -> #REF! | BT30: =IF(#REF!<>"N/A",Priority!$C30,"") -> #REF! | BV30: =IF(#REF!<>"N/A",Priority!$C30,"") -> #REF! | BW30: =IF(#REF!<>"N/A",Priority!$C30,"") -> #REF! | BX30: =IF(#REF!<>"N/A",Priority!$C30,"") -> #REF! | BY30: =IF(#REF!<>"N/A",Priority!$C30,"") -> #REF! | BZ30: =IF(#REF!<>"N/A",Priority!$C30,"") -> #REF! | CA30: =IF(#REF!<>"N/A",Priority!$C30,"") -> #REF! | CC30: =IF(#REF!<>"N/A",Priority!$C30,"") -> #REF! | CD30: =IF(#REF!<>"N/A",Priority!$C30,"") -> #REF! | CE30: =IF(#REF!<>"N/A",Priority!$C30,"") -> #REF! | CF30: =IF(#REF!<>"N/A",Priority!$C30,"") -> #REF!
A31: =#REF! -> #REF! | B31: =#REF! -> #REF! | C31: =#REF! -> #REF! | D31: DC1, DC2 | E31: =IF(COUNTIFS(F31:CF31,"F")+COUNTIFS(F31:CF31,"NT")>0,"In Test",IF(COUNTIFS(F31:CF31,"P")+COUNTIFS(F31:CF31,"A")>0,"Pass","Pending")) -> Pending | F31: ="Pass: "& COUNTIFS(G31:CG31,"P")& " /Accept: "& COUNTIFS(G31:CG31,"A")& "/ Fail: "& COUNTIFS(G31:CG31,"Fail") & "/ NT: "& COUNTIFS(G31:CG31,"NT") -> Pass: 0 /Accept: 0/ Fail: 0/ NT: 0 | G31: =IF(#REF!<>"N/A",Priority!$C31,"") -> #REF! | H31: =IF(#REF!<>"N/A",Priority!$C31,"") -> #REF! | I31: =IF(#REF!<>"N/A",Priority!$C31,"") -> #REF! | J31: =IF(#REF!<>"N/A",Priority!$C31,"") -> #REF! | K31: =IF(#REF!<>"N/A",Priority!$C31,"") -> #REF! | M31: =IF(#REF!<>"N/A",Priority!$C31,"") -> #REF! | N31: =IF(#REF!<>"N/A",Priority!$C31,"") -> #REF! | O31: =IF(#REF!<>"N/A",Priority!$C31,"") -> #REF! | P31: =IF(#REF!<>"N/A",Priority!$C31,"") -> #REF! | Q31: =IF(#REF!<>"N/A",Priority!$C31,"") -> #REF! | S31: =IF(#REF!<>"N/A",Priority!$C31,"") -> #REF! | T31: =IF(#REF!<>"N/A",Priority!$C31,"") -> #REF! | U31: =IF(#REF!<>"N/A",Priority!$C31,"") -> #REF! | V31: =IF(#REF!<>"N/A",Priority!$C31,"") -> #REF! | W31: =IF(#REF!<>"N/A",Priority!$C31,"") -> #REF! | X31: =IF(#REF!<>"N/A",Priority!$C31,"") -> #REF! | Z31: =IF(#REF!<>"N/A",Priority!$C31,"") -> #REF! | AA31: =IF(#REF!<>"N/A",Priority!$C31,"") -> #REF! | AB31: =IF(#REF!<>"N/A",Priority!$C31,"") -> #REF! | AC31: =IF(#REF!<>"N/A",Priority!$C31,"") -> #REF! | AD31: =IF(#REF!<>"N/A",Priority!$C31,"") -> #REF! | AE31: =IF(#REF!<>"N/A",Priority!$C31,"") -> #REF! | AF31: =IF(#REF!<>"N/A",Priority!$C31,"") -> #REF! | AG31: =IF(#REF!<>"N/A",Priority!$C31,"") -> #REF! | ... AI31: =IF(#REF!<>"N/A",Priority!$C31,"") -> #REF! | AK31: =IF(#REF!<>"N/A",Priority!$C31,"") -> #REF! | AL31: =IF(#REF!<>"N/A",Priority!$C31,"") -> #REF! | AM31: =IF(#REF!<>"N/A",Priority!$C31,"") -> #REF! | AN31: =IF(#REF!<>"N/A",Priority!$C31,"") -> #REF! | AO31: =IF(#REF!<>"N/A",Priority!$C31,"") -> #REF! | AP31: =IF(#REF!<>"N/A",Priority!$C31,"") -> #REF! | AQ31: =IF(#REF!<>"N/A",Priority!$C31,"") -> #REF! | AR31: =IF(#REF!<>"N/A",Priority!$C31,"") -> #REF! | ... AT31: =IF(#REF!<>"N/A",Priority!$C31,"") -> #REF! | AV31: =IF(#REF!<>"N/A",Priority!$C31,"") -> #REF! | AW31: =IF(#REF!<>"N/A",Priority!$C31,"") -> #REF! | AX31: =IF(#REF!<>"N/A",Priority!$C31,"") -> #REF! | AY31: =IF(#REF!<>"N/A",Priority!$C31,"") -> #REF! | AZ31: =IF(#REF!<>"N/A",Priority!$C31,"") -> #REF! | BA31: =IF(#REF!<>"N/A",Priority!$C31,"") -> #REF! | BB31: =IF(#REF!<>"N/A",Priority!$C31,"") -> #REF! | BD31: =IF(#REF!<>"N/A",Priority!$C31,"") -> #REF! | BE31: =IF(#REF!<>"N/A",Priority!$C31,"") -> #REF! | BF31: =IF(#REF!<>"N/A",Priority!$C31,"") -> #REF! | BG31: =IF(#REF!<>"N/A",Priority!$C31,"") -> #REF! | BH31: =IF(#REF!<>"N/A",Priority!$C31,"") -> #REF! | BI31: =IF(#REF!<>"N/A",Priority!$C31,"") -> #REF! | BJ31: =IF(#REF!<>"N/A",Priority!$C31,"") -> #REF! | BK31: =IF(#REF!<>"N/A",Priority!$C31,"") -> #REF! | BL31: =IF(#REF!<>"N/A",Priority!$C31,"") -> #REF! | BN31: =IF(#REF!<>"N/A",Priority!$C31,"") -> #REF! | BO31: =IF(#REF!<>"N/A",Priority!$C31,"") -> #REF! | BP31: =IF(#REF!<>"N/A",Priority!$C31,"") -> #REF! | BQ31: =IF(#REF!<>"N/A",Priority!$C31,"") -> #REF! | BR31: =IF(#REF!<>"N/A",Priority!$C31,"") -> #REF! | BS31: =IF(#REF!<>"N/A",Priority!$C31,"") -> #REF! | BT31: =IF(#REF!<>"N/A",Priority!$C31,"") -> #REF! | BV31: =IF(#REF!<>"N/A",Priority!$C31,"") -> #REF! | BW31: =IF(#REF!<>"N/A",Priority!$C31,"") -> #REF! | BX31: =IF(#REF!<>"N/A",Priority!$C31,"") -> #REF! | BY31: =IF(#REF!<>"N/A",Priority!$C31,"") -> #REF! | BZ31: =IF(#REF!<>"N/A",Priority!$C31,"") -> #REF! | CA31: =IF(#REF!<>"N/A",Priority!$C31,"") -> #REF! | CC31: =IF(#REF!<>"N/A",Priority!$C31,"") -> #REF! | CD31: =IF(#REF!<>"N/A",Priority!$C31,"") -> #REF! | CE31: =IF(#REF!<>"N/A",Priority!$C31,"") -> #REF! | CF31: =IF(#REF!<>"N/A",Priority!$C31,"") -> #REF!
A32: =#REF! -> #REF! | B32: =#REF! -> #REF! | C32: =#REF! -> #REF! | D32: DC1, DC2 | E32: =IF(COUNTIFS(F32:CF32,"F")+COUNTIFS(F32:CF32,"NT")>0,"In Test",IF(COUNTIFS(F32:CF32,"P")+COUNTIFS(F32:CF32,"A")>0,"Pass","Pending")) -> Pending | F32: ="Pass: "& COUNTIFS(G32:CG32,"P")& " /Accept: "& COUNTIFS(G32:CG32,"A")& "/ Fail: "& COUNTIFS(G32:CG32,"Fail") & "/ NT: "& COUNTIFS(G32:CG32,"NT") -> Pass: 0 /Accept: 0/ Fail: 0/ NT: 0 | G32: =IF(#REF!<>"N/A",Priority!$C32,"") -> #REF! | H32: =IF(#REF!<>"N/A",Priority!$C32,"") -> #REF! | I32: =IF(#REF!<>"N/A",Priority!$C32,"") -> #REF! | J32: =IF(#REF!<>"N/A",Priority!$C32,"") -> #REF! | K32: =IF(#REF!<>"N/A",Priority!$C32,"") -> #REF! | M32: =IF(#REF!<>"N/A",Priority!$C32,"") -> #REF! | N32: =IF(#REF!<>"N/A",Priority!$C32,"") -> #REF! | O32: =IF(#REF!<>"N/A",Priority!$C32,"") -> #REF! | P32: =IF(#REF!<>"N/A",Priority!$C32,"") -> #REF! | Q32: =IF(#REF!<>"N/A",Priority!$C32,"") -> #REF! | S32: =IF(#REF!<>"N/A",Priority!$C32,"") -> #REF! | T32: =IF(#REF!<>"N/A",Priority!$C32,"") -> #REF! | U32: =IF(#REF!<>"N/A",Priority!$C32,"") -> #REF! | V32: =IF(#REF!<>"N/A",Priority!$C32,"") -> #REF! | W32: =IF(#REF!<>"N/A",Priority!$C32,"") -> #REF! | X32: =IF(#REF!<>"N/A",Priority!$C32,"") -> #REF! | Z32: =IF(#REF!<>"N/A",Priority!$C32,"") -> #REF! | AA32: =IF(#REF!<>"N/A",Priority!$C32,"") -> #REF! | AB32: =IF(#REF!<>"N/A",Priority!$C32,"") -> #REF! | AC32: =IF(#REF!<>"N/A",Priority!$C32,"") -> #REF! | AD32: =IF(#REF!<>"N/A",Priority!$C32,"") -> #REF! | AE32: =IF(#REF!<>"N/A",Priority!$C32,"") -> #REF! | AF32: =IF(#REF!<>"N/A",Priority!$C32,"") -> #REF! | AG32: =IF(#REF!<>"N/A",Priority!$C32,"") -> #REF! | ... AI32: =IF(#REF!<>"N/A",Priority!$C32,"") -> #REF! | AK32: =IF(#REF!<>"N/A",Priority!$C32,"") -> #REF! | AL32: =IF(#REF!<>"N/A",Priority!$C32,"") -> #REF! | AM32: =IF(#REF!<>"N/A",Priority!$C32,"") -> #REF! | AN32: =IF(#REF!<>"N/A",Priority!$C32,"") -> #REF! | AO32: =IF(#REF!<>"N/A",Priority!$C32,"") -> #REF! | AP32: =IF(#REF!<>"N/A",Priority!$C32,"") -> #REF! | AQ32: =IF(#REF!<>"N/A",Priority!$C32,"") -> #REF! | AR32: =IF(#REF!<>"N/A",Priority!$C32,"") -> #REF! | ... AT32: =IF(#REF!<>"N/A",Priority!$C32,"") -> #REF! | AV32: =IF(#REF!<>"N/A",Priority!$C32,"") -> #REF! | AW32: =IF(#REF!<>"N/A",Priority!$C32,"") -> #REF! | AX32: =IF(#REF!<>"N/A",Priority!$C32,"") -> #REF! | AY32: =IF(#REF!<>"N/A",Priority!$C32,"") -> #REF! | AZ32: =IF(#REF!<>"N/A",Priority!$C32,"") -> #REF! | BA32: =IF(#REF!<>"N/A",Priority!$C32,"") -> #REF! | BB32: =IF(#REF!<>"N/A",Priority!$C32,"") -> #REF! | BD32: =IF(#REF!<>"N/A",Priority!$C32,"") -> #REF! | BE32: =IF(#REF!<>"N/A",Priority!$C32,"") -> #REF! | BF32: =IF(#REF!<>"N/A",Priority!$C32,"") -> #REF! | BG32: =IF(#REF!<>"N/A",Priority!$C32,"") -> #REF! | BH32: =IF(#REF!<>"N/A",Priority!$C32,"") -> #REF! | BI32: =IF(#REF!<>"N/A",Priority!$C32,"") -> #REF! | BJ32: =IF(#REF!<>"N/A",Priority!$C32,"") -> #REF! | BK32: =IF(#REF!<>"N/A",Priority!$C32,"") -> #REF! | BL32: =IF(#REF!<>"N/A",Priority!$C32,"") -> #REF! | BN32: =IF(#REF!<>"N/A",Priority!$C32,"") -> #REF! | BO32: =IF(#REF!<>"N/A",Priority!$C32,"") -> #REF! | BP32: =IF(#REF!<>"N/A",Priority!$C32,"") -> #REF! | BQ32: =IF(#REF!<>"N/A",Priority!$C32,"") -> #REF! | BR32: =IF(#REF!<>"N/A",Priority!$C32,"") -> #REF! | BS32: =IF(#REF!<>"N/A",Priority!$C32,"") -> #REF! | BT32: =IF(#REF!<>"N/A",Priority!$C32,"") -> #REF! | BV32: =IF(#REF!<>"N/A",Priority!$C32,"") -> #REF! | BW32: =IF(#REF!<>"N/A",Priority!$C32,"") -> #REF! | BX32: =IF(#REF!<>"N/A",Priority!$C32,"") -> #REF! | BY32: =IF(#REF!<>"N/A",Priority!$C32,"") -> #REF! | BZ32: =IF(#REF!<>"N/A",Priority!$C32,"") -> #REF! | CA32: =IF(#REF!<>"N/A",Priority!$C32,"") -> #REF! | CC32: =IF(#REF!<>"N/A",Priority!$C32,"") -> #REF! | CD32: =IF(#REF!<>"N/A",Priority!$C32,"") -> #REF! | CE32: =IF(#REF!<>"N/A",Priority!$C32,"") -> #REF! | CF32: =IF(#REF!<>"N/A",Priority!$C32,"") -> #REF!
... A44: =#REF! -> #REF! | B44: =#REF! -> #REF! | C44: =#REF! -> #REF! | D44: Various | E44: =IF(COUNTIFS(F44:CF44,"F")+COUNTIFS(F44:CF44,"NT")>0,"In Test",IF(COUNTIFS(F44:CF44,"P")+COUNTIFS(F44:CF44,"A")>0,"Pass","Pending")) -> Pending | F44: ="Pass: "& COUNTIFS(G44:CG44,"P")& " /Accept: "& COUNTIFS(G44:CG44,"A")& "/ Fail: "& COUNTIFS(G44:CG44,"Fail") & "/ NT: "& COUNTIFS(G44:CG44,"NT") -> Pass: 0 /Accept: 0/ Fail: 0/ NT: 0 | G44: =IF(#REF!<>"N/A",Priority!$C44,"") -> #REF! | H44: =IF(#REF!<>"N/A",Priority!$C44,"") -> #REF! | I44: =IF(#REF!<>"N/A",Priority!$C44,"") -> #REF! | J44: =IF(#REF!<>"N/A",Priority!$C44,"") -> #REF! | K44: =IF(#REF!<>"N/A",Priority!$C44,"") -> #REF! | M44: =IF(#REF!<>"N/A",Priority!$C44,"") -> #REF! | N44: =IF(#REF!<>"N/A",Priority!$C44,"") -> #REF! | O44: =IF(#REF!<>"N/A",Priority!$C44,"") -> #REF! | P44: =IF(#REF!<>"N/A",Priority!$C44,"") -> #REF! | Q44: =IF(#REF!<>"N/A",Priority!$C44,"") -> #REF! | S44: =IF(#REF!<>"N/A",Priority!$C44,"") -> #REF! | T44: =IF(#REF!<>"N/A",Priority!$C44,"") -> #REF! | U44: =IF(#REF!<>"N/A",Priority!$C44,"") -> #REF! | V44: =IF(#REF!<>"N/A",Priority!$C44,"") -> #REF! | W44: =IF(#REF!<>"N/A",Priority!$C44,"") -> #REF! | X44: =IF(#REF!<>"N/A",Priority!$C44,"") -> #REF! | Z44: =IF(#REF!<>"N/A",Priority!$C44,"") -> #REF! | AA44: =IF(#REF!<>"N/A",Priority!$C44,"") -> #REF! | AB44: =IF(#REF!<>"N/A",Priority!$C44,"") -> #REF! | AC44: =IF(#REF!<>"N/A",Priority!$C44,"") -> #REF! | AD44: =IF(#REF!<>"N/A",Priority!$C44,"") -> #REF! | AE44: =IF(#REF!<>"N/A",Priority!$C44,"") -> #REF! | AF44: =IF(#REF!<>"N/A",Priority!$C44,"") -> #REF! | AG44: =IF(#REF!<>"N/A",Priority!$C44,"") -> #REF! | ... AI44: =IF(#REF!<>"N/A",Priority!$C44,"") -> #REF! | AK44: =IF(#REF!<>"N/A",Priority!$C44,"") -> #REF! | AL44: =IF(#REF!<>"N/A",Priority!$C44,"") -> #REF! | AM44: =IF(#REF!<>"N/A",Priority!$C44,"") -> #REF! | AN44: =IF(#REF!<>"N/A",Priority!$C44,"") -> #REF! | AO44: =IF(#REF!<>"N/A",Priority!$C44,"") -> #REF! | AP44: =IF(#REF!<>"N/A",Priority!$C44,"") -> #REF! | AQ44: =IF(#REF!<>"N/A",Priority!$C44,"") -> #REF! | AR44: =IF(#REF!<>"N/A",Priority!$C44,"") -> #REF! | ... AT44: =IF(#REF!<>"N/A",Priority!$C44,"") -> #REF! | AV44: =IF(#REF!<>"N/A",Priority!$C44,"") -> #REF! | AW44: =IF(#REF!<>"N/A",Priority!$C44,"") -> #REF! | AX44: =IF(#REF!<>"N/A",Priority!$C44,"") -> #REF! | AY44: =IF(#REF!<>"N/A",Priority!$C44,"") -> #REF! | AZ44: =IF(#REF!<>"N/A",Priority!$C44,"") -> #REF! | BA44: =IF(#REF!<>"N/A",Priority!$C44,"") -> #REF! | BB44: =IF(#REF!<>"N/A",Priority!$C44,"") -> #REF! | BD44: =IF(#REF!<>"N/A",Priority!$C44,"") -> #REF! | BE44: =IF(#REF!<>"N/A",Priority!$C44,"") -> #REF! | BF44: =IF(#REF!<>"N/A",Priority!$C44,"") -> #REF! | BG44: =IF(#REF!<>"N/A",Priority!$C44,"") -> #REF! | BH44: =IF(#REF!<>"N/A",Priority!$C44,"") -> #REF! | BI44: =IF(#REF!<>"N/A",Priority!$C44,"") -> #REF! | BJ44: =IF(#REF!<>"N/A",Priority!$C44,"") -> #REF! | BK44: =IF(#REF!<>"N/A",Priority!$C44,"") -> #REF! | BL44: =IF(#REF!<>"N/A",Priority!$C44,"") -> #REF! | BN44: =IF(#REF!<>"N/A",Priority!$C44,"") -> #REF! | BO44: =IF(#REF!<>"N/A",Priority!$C44,"") -> #REF! | BP44: =IF(#REF!<>"N/A",Priority!$C44,"") -> #REF! | BQ44: =IF(#REF!<>"N/A",Priority!$C44,"") -> #REF! | BR44: =IF(#REF!<>"N/A",Priority!$C44,"") -> #REF! | BS44: =IF(#REF!<>"N/A",Priority!$C44,"") -> #REF! | BT44: =IF(#REF!<>"N/A",Priority!$C44,"") -> #REF! | BV44: =IF(#REF!<>"N/A",Priority!$C44,"") -> #REF! | BW44: =IF(#REF!<>"N/A",Priority!$C44,"") -> #REF! | BX44: =IF(#REF!<>"N/A",Priority!$C44,"") -> #REF! | BY44: =IF(#REF!<>"N/A",Priority!$C44,"") -> #REF! | BZ44: =IF(#REF!<>"N/A",Priority!$C44,"") -> #REF! | CA44: =IF(#REF!<>"N/A",Priority!$C44,"") -> #REF! | CC44: =IF(#REF!<>"N/A",Priority!$C44,"") -> #REF! | CD44: =IF(#REF!<>"N/A",Priority!$C44,"") -> #REF! | CE44: =IF(#REF!<>"N/A",Priority!$C44,"") -> #REF! | CF44: =IF(#REF!<>"N/A",Priority!$C44,"") -> #REF!
A45: =#REF! -> #REF! | B45: =#REF! -> #REF!
